Workbook
Name NativeTimeline_Date_Of_Joining: #N/A
Name Slicer_Department: #N/A
Name Slicer_Department1: #N/A
Name Slicer_Gender: #N/A
Name Slicer_Location: #N/A
Name Slicer_Payroll_Month: #N/A
Name Slicer_Status: #N/A
Name Slicer_Work_Location: #N/A

Sheet Employee Profile
A1: S. No. | B1: Employee Id | C1: First Name | D1: Last Name | E1: Gender | F1: Marital Status | G1: Age | H1: Date Of Birth | I1: Date Of Joining | J1: Date of Leaving | K1: Designation | L1: Department | M1: Reporting Manager | N1: Work Location | O1: Status | P1: Qualification | Q1: Shift Details | R1: PAN | S1: Email ID | T1: Phone | U1: Column1
A2: 1 | B2: ASG0001 | C2: Ajay | D2: Sharma | E2: Male | F2: Single | G2: =DATEDIF(H2, TODAY(), "Y") -> 48 | H2: 28678 | I2: 44593 | K2: HR Manager | L2: HR | M2: CEO | N2: Bangalore | O2: Active | P2: PG | Q2: Day | R2: BEJNS1637K | S2: ajay.sharma@asg.com | T2: 9100013338 | U2: =VLOOKUP($B2,Table2[[Employee Id]:[Annual CTC]],14,0) -> 1850000
A3: 2 | B3: ASG0002 | C3: Priya | D3: Kumar | E3: Female | F3: Married | G3: =DATEDIF(H3, TODAY(), "Y") -> 46 | H3: 29166 | I3: 44613 | K3: Analytics Manager | L3: Analytics | M3: CEO | N3: Chennai | O3: Active | P3: PG | Q3: Day | R3: EHMRV2048G | S3: priya.kumar@asg.com | T3: 9100053364 | U3: =VLOOKUP($B3,Table2[[Employee Id]:[Annual CTC]],14,0) -> 2500000 | V3: Total Employees | W3: =COUNTA(Table1[Employee Id]) -> 50
A4: 3 | B4: ASG0003 | C4: Aarav | D4: Pillai | E4: Male | F4: Single | G4: =DATEDIF(H4, TODAY(), "Y") -> 44 | H4: 29999 | I4: 44634 | K4: HR Manager | L4: HR | M4: CEO | N4: Bangalore | O4: Active | P4: PG | Q4: Day | R4: KNSWA2733T | S4: aarav.pillai@asg.com | T4: 9100120114 | U4: =VLOOKUP($B4,Table2[[Employee Id]:[Annual CTC]],14,0) -> 1750000
A5: 4 | B5: ASG0004 | C5: Pooja | D5: Reddy | E5: Female | F5: Single | G5: =DATEDIF(H5, TODAY(), "Y") -> 35 | H5: 33365 | I5: 44676 | J5: 45886 | K5: BI Developer | L5: Analytics | M5: ASG0002 | N5: Mumbai | O5: Relieved | P5: PG | Q5: Night | R5: LPTXB2870A | S5: pooja.reddy@asg.com | T5: 9100133470 | U5: =VLOOKUP($B5,Table2[[Employee Id]:[Annual CTC]],14,0) -> 1350000 | V5: Active Employees | W5: =COUNTIF(Table1[Status],"Active") -> 38
A6: 5 | B6: ASG0005 | C6: Tarun | D6: Shah | E6: Male | F6: Married | G6: =DATEDIF(H6, TODAY(), "Y") -> 34 | H6: 33723 | I6: 44697 | K6: Payroll Manager | L6: Payroll | M6: CEO | N6: Chennai | O6: Active | P6: PG | Q6: Day | R6: NRVZD3144Q | S6: tarun.shah@asg.com | T6: 9100160188 | U6: =VLOOKUP($B6,Table2[[Employee Id]:[Annual CTC]],14,0) -> 1700000
A7: 6 | B7: ASG0006 | C7: Varun | D7: Iyer | E7: Male | F7: Single | G7: =DATEDIF(H7, TODAY(), "Y") -> 33 | H7: 34064 | I7: 44704 | K7: Senior Payroll Analyst | L7: Payroll | M7: ASG0005 | N7: Mumbai | O7: Active | P7: PG | Q7: Mid | R7: QTXBF3418E | S7: varun.iyer@asg.com | T7: 9100186914 | U7: =VLOOKUP($B7,Table2[[Employee Id]:[Annual CTC]],14,0) -> 1000000 | V7: No. of Departments | W7: =COUNTA(_xlfn.UNIQUE(Table1[Department])) -> 5
A8: 7 | B8: ASG0007 | C8: Sachin | D8: Sinha | E8: Male | F8: Single | G8: =DATEDIF(H8, TODAY(), "Y") -> 32 | H8: 34296 | I8: 44802 | J8: 45951 | K8: Senior Payroll Analyst | L8: Payroll | M8: ASG0005 | N8: Chennai | O8: Relieved | P8: UG | Q8: Night | R8: WZDHM4240Y | S8: sachin.sinha@asg.com | T8: 9100253764 | U8: =VLOOKUP($B8,Table2[[Employee Id]:[Annual CTC]],14,0) -> 950000
A9: 8 | B9: ASG0008 | C9: Rajesh | D9: Mishra | E9: Male | F9: Single | G9: =DATEDIF(H9, TODAY(), "Y") -> 33 | H9: 34123 | I9: 44886 | K9: Sales Manager | L9: Sales | M9: CEO | N9: Kolkata | O9: Active | P9: PG | Q9: Day | R9: YBFKP4514N | S9: rajesh.mishra@asg.com | T9: 9100280518 | U9: =VLOOKUP($B9,Table2[[Employee Id]:[Annual CTC]],14,0) -> 2100000 | V9: No. of Locations | W9: =COUNTA(_xlfn.UNIQUE(Table1[Work Location])) -> 5
A10: 9 | B10: ASG0009 | C10: Arnav | D10: Pandey | E10: Male | F10: Married | G10: =DATEDIF(H10, TODAY(), "Y") -> 32 | H10: 34429 | I10: 44893 | K10: Regional Sales Lead | L10: Sales | M10: ASG0008 | N10: Hyderabad | O10: Active | P10: PG | Q10: Day | R10: DGLQU5199Z | S10: arnav.pandey@asg.com | T10: 9100347438 | U10: =VLOOKUP($B10,Table2[[Employee Id]:[Annual CTC]],14,0) -> 1800000
A11: 10 | B11: ASG0010 | C11: Tushar | D11: Arora | E11: Male | F11: Single | G11: =DATEDIF(H11, TODAY(), "Y") -> 32 | H11: 34309 | I11: 44907 | K11: Finance Manager | L11: Finance | M11: CEO | N11: Mumbai | O11: Active | P11: PG | Q11: Day | R11: GKPTX5610W | S11: tushar.arora@asg.com | T11: 9100387614 | U11: =VLOOKUP($B11,Table2[[Employee Id]:[Annual CTC]],14,0) -> 1750000
A12: 11 | B12: ASG0011 | C12: Nidhi | D12: Nayak | E12: Female | F12: Single | G12: =DATEDIF(H12, TODAY(), "Y") -> 31 | H12: 34753 | I12: 44935 | J12: 45979 | K12: Regional Sales Lead | L12: Sales | M12: ASG0008 | N12: Hyderabad | O12: Relieved | P12: PG | Q12: Day | R12: MQUYC6295H | S12: nidhi.nayak@asg.com | T12: 9100494838 | U12: =VLOOKUP($B12,Table2[[Employee Id]:[Annual CTC]],14,0) -> 1800000
A13: 12 | B13: ASG0012 | C13: Manish | D13: Hegde | E13: Male | F13: Single | G13: =DATEDIF(H13, TODAY(), "Y") -> 30 | H13: 35180 | I13: 44956 | K13: Senior Sales Executive | L13: Sales | M13: ASG0009 | N13: Chennai | O13: Active | P13: PG | Q13: Day | R13: NRVZD6432Q | S13: manish.hegde@asg.com | T13: 9100508250 | U13: =VLOOKUP($B13,Table2[[Employee Id]:[Annual CTC]],14,0) -> 1150000
A14: 13 | B14: ASG0013 | C14: Piyush | D14: Shetty | E14: Male | F14: Single | G14: =DATEDIF(H14, TODAY(), "Y") -> 31 | H14: 34869 | I14: 44963 | K14: Senior Data Analyst | L14: Analytics | M14: ASG0002 | N14: Bangalore | O14: Active | P14: PG | Q14: Day | R14: PSWAE6569X | S14: piyush.shetty@asg.com | T14: 9100521664 | U14: =VLOOKUP($B14,Table2[[Employee Id]:[Annual CTC]],14,0) -> 1550000
A15: 14 | B15: ASG0014 | C15: Shruti | D15: Gowda | E15: Female | F15: Single | G15: =DATEDIF(H15, TODAY(), "Y") -> 30 | H15: 35228 | I15: 45005 | J15: 45919 | K15: Payroll Analyst | L15: Payroll | M15: ASG0006 | N15: Kolkata | O15: Relieved | P15: UG | Q15: Mid | R15: QTXBF6706E | S15: shruti.gowda@asg.com | T15: 9100535080 | U15: =VLOOKUP($B15,Table2[[Employee Id]:[Annual CTC]],14,0) -> 650000
A16: 15 | B16: ASG0015 | C16: Sumit | D16: Garg | E16: Male | F16: Single | G16: =DATEDIF(H16, TODAY(), "Y") -> 29 | H16: 35553 | I16: 45033 | K16: Senior Data Analyst | L16: Analytics | M16: ASG0002 | N16: Hyderabad | O16: Active | P16: PG | Q16: Mid | R16: RUYCG6843M | S16: sumit.garg@asg.com | T16: 9100548498 | U16: =VLOOKUP($B16,Table2[[Employee Id]:[Annual CTC]],14,0) -> 1475000
A17: 16 | B17: ASG0016 | C17: Saurab | D17: Bansal | E17: Male | F17: Single | G17: =DATEDIF(H17, TODAY(), "Y") -> 28 | H17: 35855 | I17: 45040 | K17: Senior Data Analyst | L17: Analytics | M17: ASG0002 | N17: Bangalore | O17: Active | P17: PG | Q17: Night | R17: TWAEJ7117B | S17: saurab.bansal@asg.com | T17: 9100575340 | U17: =VLOOKUP($B17,Table2[[Employee Id]:[Annual CTC]],14,0) -> 1875000
A18: 17 | B18: ASG0017 | C18: Yuvraj | D18: Saxena | E18: Male | F18: Single | G18: =DATEDIF(H18, TODAY(), "Y") -> 29 | H18: 35631 | I18: 45048 | J18: 46055 | K18: Sr Accountant | L18: Finance | M18: ASG0010 | N18: Chennai | O18: Relieved | P18: PG | Q18: Mid | R18: WZDHM7528Y | S18: yuvraj.saxena@asg.com | T18: 9100615618 | U18: =VLOOKUP($B18,Table2[[Employee Id]:[Annual CTC]],14,0) -> 1150000
A19: 18 | B19: ASG0018 | C19: Pranav | D19: Tripathi | E19: Male | F19: Single | G19: =DATEDIF(H19, TODAY(), "Y") -> 28 | H19: 35818 | I19: 45075 | K19: Sr Accountant | L19: Finance | M19: ASG0010 | N19: Bangalore | O19: Active | P19: PG | Q19: Day | R19: XAEJN7665F | S19: pranav.tripathi@asg.com | T19: 9100629048 | U19: =VLOOKUP($B19,Table2[[Employee Id]:[Annual CTC]],14,0) -> 1125000
A20: 19 | B20: ASG0019 | C20: Simran | D20: Jain | E20: Female | F20: Single | G20: =DATEDIF(H20, TODAY(), "Y") -> 28 | H20: 35785 | I20: 45170 | K20: Senior Sales Executive | L20: Sales | M20: ASG0009 | N20: Mumbai | O20: Active | P20: UG | Q20: Mid | R20: YBFKP7802N | S20: simran.jain@asg.com | T20: 9100642480 | U20: =VLOOKUP($B20,Table2[[Employee Id]:[Annual CTC]],14,0) -> 1100000
A21: 20 | B21: ASG0020 | C21: Kartik | D21: Batra | E21: Male | F21: Single | G21: =DATEDIF(H21, TODAY(), "Y") -> 29 | H21: 35644 | I21: 45173 | K21: Sales Executive | L21: Sales | M21: ASG0012 | N21: Kolkata | O21: Active | P21: UG | Q21: Day | R21: CFKPT8350S | S21: kartik.batra@asg.com | T21: 9100736560 | U21: =VLOOKUP($B21,Table2[[Employee Id]:[Annual CTC]],14,0) -> 780000
A22: 21 | B22: ASG0021 | C22: Ritesh | D22: Luthra | E22: Male | F22: Single | G22: =DATEDIF(H22, TODAY(), "Y") -> 28 | H22: 35993 | I22: 45222 | J22: 45950 | K22: Payroll Analyst | L22: Payroll | M22: ASG0006 | N22: Hyderabad | O22: Relieved | P22: PG | Q22: Night | R22: EHMRV8624G | S22: ritesh.luthra@asg.com | T22: 9100750008 | U22: =VLOOKUP($B22,Table2[[Employee Id]:[Annual CTC]],14,0) -> 675000
A23: 22 | B23: ASG0022 | C23: Lokesh | D23: Ahuja | E23: Male | F23: Single | G23: =DATEDIF(H23, TODAY(), "Y") -> 27 | H23: 36255 | I23: 45236 | K23: Payroll Analyst | L23: Payroll | M23: ASG0006 | N23: Mumbai | O23: Active | P23: UG | Q23: Mid | R23: GKPTX8898W | S23: lokesh.ahuja@asg.com | T23: 9100776910 | U23: =VLOOKUP($B23,Table2[[Employee Id]:[Annual CTC]],14,0) -> 680000
A24: 23 | B24: ASG0023 | C24: Sonia | D24: Khanna | E24: Female | F24: Single | G24: =DATEDIF(H24, TODAY(), "Y") -> 27 | H24: 36069 | I24: 45320 | K24: HR Analyst | L24: HR | M24: ASG0001 | N24: Hyderabad | O24: Active | P24: PG | Q24: Mid | R24: HLQUY9035D | S24: sonia.khanna@asg.com | T24: 9100790364 | U24: =VLOOKUP($B24,Table2[[Employee Id]:[Annual CTC]],14,0) -> 1200000
A25: 24 | B25: ASG0024 | C25: Parth | D25: Madaan | E25: Male | F25: Married | G25: =DATEDIF(H25, TODAY(), "Y") -> 26 | H25: 36527 | I25: 45327 | J25: 46084 | K25: Accounts Executive | L25: Finance | M25: ASG0018 | N25: Kolkata | O25: Relieved | P25: PG | Q25: Day | R25: YBFKP2090N | S25: parth.madaan@asg.com | T25: 9100803820 | U25: =VLOOKUP($B25,Table2[[Employee Id]:[Annual CTC]],14,0) -> 780000
A26: 25 | B26: ASG0025 | C26: Akshay | D26: Mohan | E26: Male | F26: Single | G26: =DATEDIF(H26, TODAY(), "Y") -> 26 | H26: 36614 | I26: 45328 | K26: Accounts Executive | L26: Finance | M26: ASG0018 | N26: Chennai | O26: Active | P26: PG | Q26: Mid | R26: NRVZD9720Q | S26: akshay.mohan@asg.com | T26: 9100884598 | U26: =VLOOKUP($B26,Table2[[Employee Id]:[Annual CTC]],14,0) -> 725000
A27: 26 | B27: ASG0026 | C27: Sanjay | D27: Lal | E27: Male | F27: Single | G27: =DATEDIF(H27, TODAY(), "Y") -> 26 | H27: 36446 | I27: 45404 | J27: 46012 | K27: Sales Executive | L27: Sales | M27: ASG0019 | N27: Bangalore | O27: Relieved | P27: UG | Q27: Mid | R27: PSWAE9857X | S27: sanjay.lal@asg.com | T27: 9100898068 | U27: =VLOOKUP($B27,Table2[[Employee Id]:[Annual CTC]],14,0) -> 825000
A28: 27 | B28: ASG0027 | C28: Ashwin | D28: Gill | E28: Male | F28: Single | G28: =DATEDIF(H28, TODAY(), "Y") -> 28 | H28: 35935 | I28: 45418 | K28: HR Analyst | L28: HR | M28: ASG0003 | N28: Mumbai | O28: Active | P28: PG | Q28: Day | R28: QTXBF9994E | S28: ashwin.gill@asg.com | T28: 9100911540 | U28: =VLOOKUP($B28,Table2[[Employee Id]:[Annual CTC]],14,0) -> 1150000
A29: 28 | B29: ASG0028 | C29: Naveen | D29: Samant | E29: Male | F29: Single | G29: =DATEDIF(H29, TODAY(), "Y") -> 27 | H29: 36318 | I29: 45502 | K29: Sales Trainee | L29: Sales | M29: ASG0012 | N29: Hyderabad | O29: Active | P29: UG | Q29: Day | R29: RUYCG1131M | S29: naveen.samant@asg.com | T29: 9100925014 | U29: =VLOOKUP($B29,Table2[[Employee Id]:[Annual CTC]],14,0) -> 450000
A30: 29 | B30: ASG0029 | C30: Girish | D30: Mistry | E30: Male | F30: Single | G30: =DATEDIF(H30, TODAY(), "Y") -> 26 | H30: 36597 | I30: 45509 | K30: Payroll Analyst | L30: Payroll | M30: ASG0006 | N30: Kolkata | O30: Active | P30: UG | Q30: Night | R30: UXBFK1542J | S30: girish.mistry@asg.com | T30: 9100965448 | U30: =VLOOKUP($B30,Table2[[Employee Id]:[Annual CTC]],14,0) -> 650000
A31: 30 | B31: ASG0030 | C31: Kavya | D31: Shroff | E31: Female | F31: Single | G31: =DATEDIF(H31, TODAY(), "Y") -> 26 | H31: 36496 | I31: 45537 | J31: 46098 | K31: Senior Data Analyst | L31: Analytics | M31: ASG0002 | N31: Hyderabad | O31: Relieved | P31: PG | Q31: Day | R31: ZCGLQ2227V | S31: kavya.shroff@asg.com | T31: 9100992414 | U31: =VLOOKUP($B31,Table2[[Employee Id]:[Annual CTC]],14,0) -> 1435000
A32: 31 | B32: ASG0031 | C32: Harish | D32: Dalal | E32: Male | F32: Single | G32: =DATEDIF(H32, TODAY(), "Y") -> 26 | H32: 36663 | I32: 45579 | K32: Accounts Executive | L32: Finance | M32: ASG0018 | N32: Bangalore | O32: Active | P32: UG | Q32: Mid | R32: BEJNS2501K | S32: harish.dalal@asg.com | T32: 9101005900 | U32: =VLOOKUP($B32,Table2[[Employee Id]:[Annual CTC]],14,0) -> 700000
A33: 32 | B33: ASG0032 | C33: Ramesh | D33: Sibal | E33: Male | F33: Married | G33: =DATEDIF(H33, TODAY(), "Y") -> 26 | H33: 36754 | I33: 45607 | K33: HR Executive | L33: HR | M33: ASG0023 | N33: Chennai | O33: Active | P33: PG | Q33: Mid | R33: SVZDH4556U | S33: ramesh.sibal@asg.com | T33: 9101032878 | U33: =VLOOKUP($B33,Table2[[Employee Id]:[Annual CTC]],14,0) -> 750000
A34: 33 | B34: ASG0033 | C34: Nisha | D34: Madan | E34: Female | F34: Married | G34: =DATEDIF(H34, TODAY(), "Y") -> 25 | H34: 36935 | I34: 45614 | K34: Data Analyst | L34: Analytics | M34: ASG0013 | N34: Bangalore | O34: Active | P34: UG | Q34: Day | R34: TWAEJ4693B | S34: nisha.madan@asg.com | T34: 9101046370 | U34: =VLOOKUP($B34,Table2[[Employee Id]:[Annual CTC]],14,0) -> 1250000
A35: 34 | B35: ASG0034 | C35: Dinesh | D35: Kohli | E35: Male | F35: Single | G35: =DATEDIF(H35, TODAY(), "Y") -> 26 | H35: 36784 | I35: 45649 | J35: 46041 | K35: HR Executive | L35: HR | M35: ASG0027 | N35: Chennai | O35: Relieved | P35: UG | Q35: Day | R35: ADHMR2364C | S35: dinesh.kohli@asg.com | T35: 9101059864 | U35: =VLOOKUP($B35,Table2[[Employee Id]:[Annual CTC]],14,0) -> 625000
A36: 35 | B36: ASG0035 | C36: Sunil | D36: Jolly | E36: Male | F36: Single | G36: =DATEDIF(H36, TODAY(), "Y") -> 25 | H36: 36892 | I36: 45663 | K36: HR Executive | L36: HR | M36: ASG0027 | N36: Mumbai | O36: Active | P36: UG | Q36: Day | R36: CFKPT2638S | S36: sunil.jolly@asg.com | T36: 9101073360 | U36: =VLOOKUP($B36,Table2[[Employee Id]:[Annual CTC]],14,0) -> 600000
A37: 36 | B37: ASG0036 | C37: Bikram | D37: Monga | E37: Male | F37: Single | G37: =DATEDIF(H37, TODAY(), "Y") -> 26 | H37: 36678 | I37: 45782 | K37: Payroll Executive | L37: Payroll | M37: ASG0022 | N37: Chennai | O37: Active | P37: UG | Q37: Mid | R37: EHMRV2912G | S37: bikram.monga@asg.com | T37: 9101100358 | U37: =VLOOKUP($B37,Table2[[Employee Id]:[Annual CTC]],14,0) -> 475000
A38: 37 | B38: ASG0037 | C38: Pratik | D38: Nanda | E38: Male | F38: Single | G38: =DATEDIF(H38, TODAY(), "Y") -> 25 | H38: 36860 | I38: 45831 | J38: 46008 | K38: Accounts Trainee | L38: Finance | M38: ASG0018 | N38: Bangalore | O38: Relieved | P38: UG | Q38: Day | R38: FJNSW3049P | S38: pratik.nanda@asg.com | T38: 9101113860 | U38: =VLOOKUP($B38,Table2[[Employee Id]:[Annual CTC]],14,0) -> 450000
A39: 38 | B39: ASG0038 | C39: Rohini | D39: Suri | E39: Female | F39: Single | G39: =DATEDIF(H39, TODAY(), "Y") -> 25 | H39: 36926 | I39: 45852 | K39: Accounts Trainee | L39: Finance | M39: ASG0018 | N39: Mumbai | O39: Active | P39: UG | Q39: Mid | R39: GKPTX3186W | S39: rohini.suri@asg.com | T39: 9101127364 | U39: =VLOOKUP($B39,Table2[[Employee Id]:[Annual CTC]],14,0) -> 450000
A40: 39 | B40: ASG0039 | C40: Abhinav | D40: Khera | E40: Male | F40: Single | G40: =DATEDIF(H40, TODAY(), "Y") -> 25 | H40: 36937 | I40: 45901 | K40: BI Developer | L40: Analytics | M40: ASG0002 | N40: Kolkata | O40: Active | P40: UG | Q40: Night | R40: UXBFK4830J | S40: abhinav.khera@asg.com | T40: 9101140870 | U40: =VLOOKUP($B40,Table2[[Employee Id]:[Annual CTC]],14,0) -> 1275000
A41: 40 | B41: ASG0040 | C41: Vikram | D41: Bedi | E41: Male | F41: Single | G41: =DATEDIF(H41, TODAY(), "Y") -> 25 | H41: 36989 | I41: 45908 | J41: 46077 | K41: Payroll Executive | L41: Payroll | M41: ASG0029 | N41: Mumbai | O41: Relieved | P41: UG | Q41: Night | R41: LPTXB3734A | S41: vikram.bedi@asg.com | T41: 9101167888 | U41: =VLOOKUP($B41,Table2[[Employee Id]:[Annual CTC]],14,0) -> 475000
A42: 41 | B42: ASG0041 | C42: Swati | D42: Chadha | E42: Female | F42: Single | G42: =DATEDIF(H42, TODAY(), "Y") -> 25 | H42: 36947 | I42: 45978 | K42: Data Analyst | L42: Analytics | M42: ASG0015 | N42: Chennai | O42: Active | P42: PG | Q42: Mid | R42: NRVZD4008Q | S42: swati.chadha@asg.com | T42: 9101194914 | U42: =VLOOKUP($B42,Table2[[Employee Id]:[Annual CTC]],14,0) -> 1180000
A43: 42 | B43: ASG0042 | C43: Naresh | D43: Rajput | E43: Male | F43: Single | G43: =DATEDIF(H43, TODAY(), "Y") -> 25 | H43: 36930 | I43: 45992 | K43: Sales Trainee | L43: Sales | M43: ASG0012 | N43: Chennai | O43: Active | P43: UG | Q43: Day | R43: WZDHM5104Y | S43: naresh.rajput@asg.com | T43: 9101235468 | U43: =VLOOKUP($B43,Table2[[Employee Id]:[Annual CTC]],14,0) -> 450000
A44: 43 | B44: ASG0043 | C44: Preeti | D44: Chauhan | E44: Female | F44: Single | G44: =DATEDIF(H44, TODAY(), "Y") -> 25 | H44: 37033 | I44: 46027 | K44: HR Executive | L44: HR | M44: ASG0023 | N44: Bangalore | O44: Active | P44: PG | Q44: Mid | R44: XAEJN5241F | S44: preeti.chauhan@asg.com | T44: 9101248990 | U44: =VLOOKUP($B44,Table2[[Employee Id]:[Annual CTC]],14,0) -> 575000
A45: 44 | B45: ASG0044 | C45: Devraj | D45: Thakur | E45: Male | F45: Single | G45: =DATEDIF(H45, TODAY(), "Y") -> 24 | H45: 37371 | I45: 46041 | K45: Data Analyst | L45: Analytics | M45: ASG0016 | N45: Kolkata | O45: Active | P45: PG | Q45: Night | R45: YBFKP5378N | S45: devraj.thakur@asg.com | T45: 9101262514 | U45: =VLOOKUP($B45,Table2[[Employee Id]:[Annual CTC]],14,0) -> 1150000
A46: 45 | B46: ASG0045 | C46: Paresh | D46: Rana | E46: Male | F46: Single | G46: =DATEDIF(H46, TODAY(), "Y") -> 24 | H46: 37182 | I46: 46056 | K46: Accounts Trainee | L46: Finance | M46: ASG0018 | N46: Hyderabad | O46: Active | P46: UG | Q46: Day | R46: ZCGLQ5515V | S46: paresh.rana@asg.com | T46: 9101276040 | U46: =VLOOKUP($B46,Table2[[Employee Id]:[Annual CTC]],14,0) -> 450000
A47: 46 | B47: ASG0046 | C47: Usha | D47: Malhotra | E47: Female | F47: Single | G47: =DATEDIF(H47, TODAY(), "Y") -> 24 | H47: 37348 | I47: 46062 | K47: HR Executive | L47: HR | M47: ASG0023 | N47: Chennai | O47: Active | P47: UG | Q47: Day | R47: ADHMR5652C | S47: usha.malhotra@asg.com | T47: 9101289568 | U47: =VLOOKUP($B47,Table2[[Employee Id]:[Annual CTC]],14,0) -> 575000
A48: 47 | B48: ASG0047 | C48: Ambar | D48: Biswas | E48: Male | F48: Single | G48: =DATEDIF(H48, TODAY(), "Y") -> 24 | H48: 37235 | I48: 46063 | K48: HR Executive | L48: HR | M48: ASG0027 | N48: Bangalore | O48: Active | P48: PG | Q48: Day | R48: BEJNS5789K | S48: ambar.biswas@asg.com | T48: 9101303098 | U48: =VLOOKUP($B48,Table2[[Employee Id]:[Annual CTC]],14,0) -> 575000
A49: 48 | B49: ASG0048 | C49: Nakul | D49: Datta | E49: Male | F49: Single | G49: =DATEDIF(H49, TODAY(), "Y") -> 25 | H49: 37079 | I49: 46091 | K49: Accounts Trainee | L49: Finance | M49: ASG0018 | N49: Mumbai | O49: Active | P49: UG | Q49: Mid | R49: CFKPT5926S | S49: nakul.datta@asg.com | T49: 9101316630 | U49: =VLOOKUP($B49,Table2[[Employee Id]:[Annual CTC]],14,0) -> 450000
A50: 49 | B50: ASG0049 | C50: Bharat | D50: Moitra | E50: Male | F50: Single | G50: =DATEDIF(H50, TODAY(), "Y") -> 24 | H50: 37311 | I50: 46098 | K50: Payroll Executive | L50: Payroll | M50: ASG0029 | N50: Hyderabad | O50: Active | P50: UG | Q50: Day | R50: DGLQU6063Z | S50: bharat.moitra@asg.com | T50: 9101330164 | U50: =VLOOKUP($B50,Table2[[Employee Id]:[Annual CTC]],14,0) -> 475000
A51: 50 | B51: ASG0050 | C51: Sameer | D51: Rathi | E51: Male | F51: Single | G51: =DATEDIF(H51, TODAY(), "Y") -> 24 | H51: 37451 | I51: 46105 | K51: Sales Trainee | L51: Sales | M51: ASG0019 | N51: Hyderabad | O51: Active | P51: UG | Q51: Mid | R51: VYCGL4967R | S51: sameer.rathi@asg.com | T51: 9101343700 | U51: =VLOOKUP($B51,Table2[[Employee Id]:[Annual CTC]],14,0) -> 450000

Sheet Pivot Tables - Workforce
A1: Count of Employee Id | B1: Column Labels | D1: Rs. #\.##,"L" | F1: Department | G1: Count of Employee Id | J1: Count of Employee Id | K1: Column Labels
A2: Department | B2: Active | C2: Relieved | F2: PG | G2: 27 | J2: Department | K2: Female | L2: Male
A3: Analytics | B3: 8 | C3: 2 | F3: UG | G3: 23 | J3: Analytics | K3: 5 | L3: 5
A4: Finance | B4: 7 | C4: 3 | J4: Finance | K4: 1 | L4: 9
A5: HR | B5: 9 | C5: 1 | J5: HR | K5: 3 | L5: 7
A6: Payroll | B6: 6 | C6: 4 | J6: Payroll | K6: 1 | L6: 9
A7: Sales | B7: 8 | C7: 2 | J7: Sales | K7: 2 | L7: 8
F23: Department | G23: Count of Employee Id
F24: Day | G24: 25 | J24: Count of Employee Id | K24: Column Labels
F25: Mid | G25: 17 | J25: Department | K25: Analytics | L25: Finance | M25: HR | N25: Payroll | O25: Sales
A26: Location | B26: Count of Employee Id | F26: Night | G26: 8 | J26: Bangalore | K26: 3 | L26: 3 | M26: 4 | O26: 1
A27: Bangalore | B27: 11 | J27: Chennai | K27: 2 | L27: 2 | M27: 3 | N27: 3 | O27: 2
A28: Chennai | B28: 12 | J28: Hyderabad | K28: 2 | L28: 1 | M28: 1 | N28: 2 | O28: 4
A29: Hyderabad | B29: 10 | J29: Kolkata | K29: 2 | L29: 1 | N29: 2 | O29: 2
A30: Mumbai | B30: 10 | J30: Mumbai | K30: 1 | L30: 3 | M30: 2 | N30: 3 | O30: 1
A31: Kolkata | B31: 7

Sheet Dashboard for Emp Workforce

Sheet Business Insights for Workforce

Sheet CTC Breakup
A1: S. No. | B1: Employee Id | C1: Date Of Joining | D1: Date of Leaving | E1: Status | F1: Designation | G1: Department | H1: Basic (50% of CTC) | I1: HRA (40% of Basic) | J1: Special Allowance (Adjusting Figure) | K1: Fuel Allowance (Fixed Rs 2000) | L1: Internet Allowance (Fixed Rs 1000) | M1: Employer PF (Basic * 12%) | N1: Monthly CTC | O1: Annual CTC
A2: 1 | B2: ASG0001 | C2: 44593 | E2: Active | F2: HR Manager | G2: HR | H2: =ROUND(N2/2,0) -> 77084 | I2: =ROUND(H2*40%,0) -> 30834 | J2: =N2-H2-I2-K2-L2-M2 -> 33999 | K2: 2000 | L2: 1000 | M2: =ROUND(H2*12%,0) -> 9250 | N2: =ROUND(O2/12,0) -> 154167 | O2: 1850000
A3: 2 | B3: ASG0002 | C3: 44613 | E3: Active | F3: Analytics Manager | G3: Analytics | H3: =ROUND(N3/2,0) -> 104167 | I3: =ROUND(H3*40%,0) -> 41667 | J3: =N3-H3-I3-K3-L3-M3 -> 49999 | M3: =ROUND(H3*12%,0) -> 12500 | N3: =ROUND(O3/12,0) -> 208333 | O3: 2500000
A4: 3 | B4: ASG0003 | C4: 44634 | E4: Active | F4: HR Manager | G4: HR | H4: =ROUND(N4/2,0) -> 72917 | I4: =ROUND(H4*40%,0) -> 29167 | J4: =N4-H4-I4-K4-L4-M4 -> 31999 | K4: 2000 | L4: 1000 | M4: =ROUND(H4*12%,0) -> 8750 | N4: =ROUND(O4/12,0) -> 145833 | O4: 1750000
A5: 4 | B5: ASG0004 | C5: 44676 | D5: 45886 | E5: Relieved | F5: BI Developer | G5: Analytics | H5: =ROUND(N5/2,0) -> 56250 | I5: =ROUND(H5*40%,0) -> 22500 | J5: =N5-H5-I5-K5-L5-M5 -> 24000 | K5: 2000 | L5: 1000 | M5: =ROUND(H5*12%,0) -> 6750 | N5: =ROUND(O5/12,0) -> 112500 | O5: 1350000
A6: 5 | B6: ASG0005 | C6: 44697 | E6: Active | F6: Payroll Manager | G6: Payroll | H6: =ROUND(N6/2,0) -> 70834 | I6: =ROUND(H6*40%,0) -> 28334 | J6: =N6-H6-I6-K6-L6-M6 -> 30999 | K6: 2000 | L6: 1000 | M6: =ROUND(H6*12%,0) -> 8500 | N6: =ROUND(O6/12,0) -> 141667 | O6: 1700000
A7: 6 | B7: ASG0006 | C7: 44704 | E7: Active | F7: Senior Payroll Analyst | G7: Payroll | H7: =ROUND(N7/2,0) -> 41667 | I7: =ROUND(H7*40%,0) -> 16667 | J7: =N7-H7-I7-K7-L7-M7 -> 16999 | K7: 2000 | L7: 1000 | M7: =ROUND(H7*12%,0) -> 5000 | N7: =ROUND(O7/12,0) -> 83333 | O7: 1000000
A8: 7 | B8: ASG0007 | C8: 44802 | D8: 45951 | E8: Relieved | F8: Senior Payroll Analyst | G8: Payroll | H8: =ROUND(N8/2,0) -> 39584 | I8: =ROUND(H8*40%,0) -> 15834 | J8: =N8-H8-I8-K8-L8-M8 -> 15999 | K8: 2000 | L8: 1000 | M8: =ROUND(H8*12%,0) -> 4750 | N8: =ROUND(O8/12,0) -> 79167 | O8: 950000
A9: 8 | B9: ASG0008 | C9: 44886 | E9: Active | F9: Sales Manager | G9: Sales | H9: =ROUND(N9/2,0) -> 87500 | I9: =ROUND(H9*40%,0) -> 35000 | J9: =N9-H9-I9-K9-L9-M9 -> 39000 | K9: 2000 | L9: 1000 | M9: =ROUND(H9*12%,0) -> 10500 | N9: =ROUND(O9/12,0) -> 175000 | O9: 2100000
A10: 9 | B10: ASG0009 | C10: 44893 | E10: Active | F10: Regional Sales Lead | G10: Sales | H10: =ROUND(N10/2,0) -> 75000 | I10: =ROUND(H10*40%,0) -> 30000 | J10: =N10-H10-I10-K10-L10-M10 -> 33000 | K10: 2000 | L10: 1000 | M10: =ROUND(H10*12%,0) -> 9000 | N10: =ROUND(O10/12,0) -> 150000 | O10: 1800000
A11: 10 | B11: ASG0010 | C11: 44907 | E11: Active | F11: Finance Manager | G11: Finance | H11: =ROUND(N11/2,0) -> 72917 | I11: =ROUND(H11*40%,0) -> 29167 | J11: =N11-H11-I11-K11-L11-M11 -> 31999 | K11: 2000 | L11: 1000 | M11: =ROUND(H11*12%,0) -> 8750 | N11: =ROUND(O11/12,0) -> 145833 | O11: 1750000
A12: 11 | B12: ASG0011 | C12: 44935 | D12: 45979 | E12: Relieved | F12: Regional Sales Lead | G12: Sales | H12: =ROUND(N12/2,0) -> 75000 | I12: =ROUND(H12*40%,0) -> 30000 | J12: =N12-H12-I12-K12-L12-M12 -> 33000 | K12: 2000 | L12: 1000 | M12: =ROUND(H12*12%,0) -> 9000 | N12: =ROUND(O12/12,0) -> 150000 | O12: 1800000
A13: 12 | B13: ASG0012 | C13: 44956 | E13: Active | F13: Senior Sales Executive | G13: Sales | H13: =ROUND(N13/2,0) -> 47917 | I13: =ROUND(H13*40%,0) -> 19167 | J13: =N13-H13-I13-K13-L13-M13 -> 19999 | K13: 2000 | L13: 1000 | M13: =ROUND(H13*12%,0) -> 5750 | N13: =ROUND(O13/12,0) -> 95833 | O13: 1150000
A14: 13 | B14: ASG0013 | C14: 44963 | E14: Active | F14: Senior Data Analyst | G14: Analytics | H14: =ROUND(N14/2,0) -> 64584 | I14: =ROUND(H14*40%,0) -> 25834 | J14: =N14-H14-I14-K14-L14-M14 -> 27999 | K14: 2000 | L14: 1000 | M14: =ROUND(H14*12%,0) -> 7750 | N14: =ROUND(O14/12,0) -> 129167 | O14: 1550000
A15: 14 | B15: ASG0014 | C15: 45005 | D15: 45919 | E15: Relieved | F15: Payroll Analyst | G15: Payroll | H15: =ROUND(N15/2,0) -> 27084 | I15: =ROUND(H15*40%,0) -> 10834 | J15: =N15-H15-I15-K15-L15-M15 -> 12999 | M15: =ROUND(H15*12%,0) -> 3250 | N15: =ROUND(O15/12,0) -> 54167 | O15: 650000
A16: 15 | B16: ASG0015 | C16: 45033 | E16: Active | F16: Senior Data Analyst | G16: Analytics | H16: =ROUND(N16/2,0) -> 61459 | I16: =ROUND(H16*40%,0) -> 24584 | J16: =N16-H16-I16-K16-L16-M16 -> 26499 | K16: 2000 | L16: 1000 | M16: =ROUND(H16*12%,0) -> 7375 | N16: =ROUND(O16/12,0) -> 122917 | O16: 1475000
A17: 16 | B17: ASG0016 | C17: 45040 | E17: Active | F17: Senior Data Analyst | G17: Analytics | H17: =ROUND(N17/2,0) -> 78125 | I17: =ROUND(H17*40%,0) -> 31250 | J17: =N17-H17-I17-K17-L17-M17 -> 34500 | K17: 2000 | L17: 1000 | M17: =ROUND(H17*12%,0) -> 9375 | N17: =ROUND(O17/12,0) -> 156250 | O17: 1875000
A18: 17 | B18: ASG0017 | C18: 45048 | D18: 46055 | E18: Relieved | F18: Sr Accountant | G18: Finance | H18: =ROUND(N18/2,0) -> 47917 | I18: =ROUND(H18*40%,0) -> 19167 | J18: =N18-H18-I18-K18-L18-M18 -> 19999 | K18: 2000 | L18: 1000 | M18: =ROUND(H18*12%,0) -> 5750 | N18: =ROUND(O18/12,0) -> 95833 | O18: 1150000
A19: 18 | B19: ASG0018 | C19: 45075 | E19: Active | F19: Sr Accountant | G19: Finance | H19: =ROUND(N19/2,0) -> 46875 | I19: =ROUND(H19*40%,0) -> 18750 | J19: =N19-H19-I19-K19-L19-M19 -> 19500 | K19: 2000 | L19: 1000 | M19: =ROUND(H19*12%,0) -> 5625 | N19: =ROUND(O19/12,0) -> 93750 | O19: 1125000
A20: 19 | B20: ASG0019 | C20: 45170 | E20: Active | F20: Senior Sales Executive | G20: Sales | H20: =ROUND(N20/2,0) -> 45834 | I20: =ROUND(H20*40%,0) -> 18334 | J20: =N20-H20-I20-K20-L20-M20 -> 18999 | K20: 2000 | L20: 1000 | M20: =ROUND(H20*12%,0) -> 5500 | N20: =ROUND(O20/12,0) -> 91667 | O20: 1100000
A21: 20 | B21: ASG0020 | C21: 45173 | E21: Active | F21: Sales Executive | G21: Sales | H21: =ROUND(N21/2,0) -> 32500 | I21: =ROUND(H21*40%,0) -> 13000 | J21: =N21-H21-I21-K21-L21-M21 -> 15600 | M21: =ROUND(H21*12%,0) -> 3900 | N21: =ROUND(O21/12,0) -> 65000 | O21: 780000
A22: 21 | B22: ASG0021 | C22: 45222 | D22: 45950 | E22: Relieved | F22: Payroll Analyst | G22: Payroll | H22: =ROUND(N22/2,0) -> 28125 | I22: =ROUND(H22*40%,0) -> 11250 | J22: =N22-H22-I22-K22-L22-M22 -> 13500 | M22: =ROUND(H22*12%,0) -> 3375 | N22: =ROUND(O22/12,0) -> 56250 | O22: 675000
A23: 22 | B23: ASG0022 | C23: 45236 | E23: Active | F23: Payroll Analyst | G23: Payroll | H23: =ROUND(N23/2,0) -> 28334 | I23: =ROUND(H23*40%,0) -> 11334 | J23: =N23-H23-I23-K23-L23-M23 -> 13599 | M23: =ROUND(H23*12%,0) -> 3400 | N23: =ROUND(O23/12,0) -> 56667 | O23: 680000
A24: 23 | B24: ASG0023 | C24: 45320 | E24: Active | F24: HR Analyst | G24: HR | H24: =ROUND(N24/2,0) -> 50000 | I24: =ROUND(H24*40%,0) -> 20000 | J24: =N24-H24-I24-K24-L24-M24 -> 21000 | K24: 2000 | L24: 1000 | M24: =ROUND(H24*12%,0) -> 6000 | N24: =ROUND(O24/12,0) -> 100000 | O24: 1200000
A25: 24 | B25: ASG0024 | C25: 45327 | D25: 46084 | E25: Relieved | F25: Accounts Executive | G25: Finance | H25: =ROUND(N25/2,0) -> 32500 | I25: =ROUND(H25*40%,0) -> 13000 | J25: =N25-H25-I25-K25-L25-M25 -> 15600 | M25: =ROUND(H25*12%,0) -> 3900 | N25: =ROUND(O25/12,0) -> 65000 | O25: 780000
A26: 25 | B26: ASG0025 | C26: 45328 | E26: Active | F26: Accounts Executive | G26: Finance | H26: =ROUND(N26/2,0) -> 30209 | I26: =ROUND(H26*40%,0) -> 12084 | J26: =N26-H26-I26-K26-L26-M26 -> 14499 | M26: =ROUND(H26*12%,0) -> 3625 | N26: =ROUND(O26/12,0) -> 60417 | O26: 725000
A27: 26 | B27: ASG0026 | C27: 45404 | D27: 46012 | E27: Relieved | F27: Sales Executive | G27: Sales | H27: =ROUND(N27/2,0) -> 34375 | I27: =ROUND(H27*40%,0) -> 13750 | J27: =N27-H27-I27-K27-L27-M27 -> 16500 | M27: =ROUND(H27*12%,0) -> 4125 | N27: =ROUND(O27/12,0) -> 68750 | O27: 825000
A28: 27 | B28: ASG0027 | C28: 45418 | E28: Active | F28: HR Analyst | G28: HR | H28: =ROUND(N28/2,0) -> 47917 | I28: =ROUND(H28*40%,0) -> 19167 | J28: =N28-H28-I28-K28-L28-M28 -> 19999 | K28: 2000 | L28: 1000 | M28: =ROUND(H28*12%,0) -> 5750 | N28: =ROUND(O28/12,0) -> 95833 | O28: 1150000
A29: 28 | B29: ASG0028 | C29: 45502 | E29: Active | F29: Sales Trainee | G29: Sales | H29: =ROUND(N29/2,0) -> 18750 | I29: =ROUND(H29*40%,0) -> 7500 | J29: =N29-H29-I29-K29-L29-M29 -> 9000 | M29: =ROUND(H29*12%,0) -> 2250 | N29: =ROUND(O29/12,0) -> 37500 | O29: 450000
A30: 29 | B30: ASG0029 | C30: 45509 | E30: Active | F30: Payroll Analyst | G30: Payroll | H30: =ROUND(N30/2,0) -> 27084 | I30: =ROUND(H30*40%,0) -> 10834 | J30: =N30-H30-I30-K30-L30-M30 -> 12999 | M30: =ROUND(H30*12%,0) -> 3250 | N30: =ROUND(O30/12,0) -> 54167 | O30: 650000
A31: 30 | B31: ASG0030 | C31: 45537 | D31: 46098 | E31: Relieved | F31: Senior Data Analyst | G31: Analytics | H31: =ROUND(N31/2,0) -> 59792 | I31: =ROUND(H31*40%,0) -> 23917 | J31: =N31-H31-I31-K31-L31-M31 -> 25699 | K31: 2000 | L31: 1000 | M31: =ROUND(H31*12%,0) -> 7175 | N31: =ROUND(O31/12,0) -> 119583 | O31: 1435000
A32: 31 | B32: ASG0031 | C32: 45579 | E32: Active | F32: Accounts Executive | G32: Finance | H32: =ROUND(N32/2,0) -> 29167 | I32: =ROUND(H32*40%,0) -> 11667 | J32: =N32-H32-I32-K32-L32-M32 -> 13999 | M32: =ROUND(H32*12%,0) -> 3500 | N32: =ROUND(O32/12,0) -> 58333 | O32: 700000
A33: 32 | B33: ASG0032 | C33: 45607 | E33: Active | F33: HR Executive | G33: HR | H33: =ROUND(N33/2,0) -> 31250 | I33: =ROUND(H33*40%,0) -> 12500 | J33: =N33-H33-I33-K33-L33-M33 -> 15000 | M33: =ROUND(H33*12%,0) -> 3750 | N33: =ROUND(O33/12,0) -> 62500 | O33: 750000
A34: 33 | B34: ASG0033 | C34: 45614 | E34: Active | F34: Data Analyst | G34: Analytics | H34: =ROUND(N34/2,0) -> 52084 | I34: =ROUND(H34*40%,0) -> 20834 | J34: =N34-H34-I34-K34-L34-M34 -> 21999 | K34: 2000 | L34: 1000 | M34: =ROUND(H34*12%,0) -> 6250 | N34: =ROUND(O34/12,0) -> 104167 | O34: 1250000
A35: 34 | B35: ASG0034 | C35: 45649 | D35: 46041 | E35: Relieved | F35: HR Executive | G35: HR | H35: =ROUND(N35/2,0) -> 26042 | I35: =ROUND(H35*40%,0) -> 10417 | J35: =N35-H35-I35-K35-L35-M35 -> 12499 | M35: =ROUND(H35*12%,0) -> 3125 | N35: =ROUND(O35/12,0) -> 52083 | O35: 625000
A36: 35 | B36: ASG0035 | C36: 45663 | E36: Active | F36: HR Executive | G36: HR | H36: =ROUND(N36/2,0) -> 25000 | I36: =ROUND(H36*40%,0) -> 10000 | J36: =N36-H36-I36-K36-L36-M36 -> 12000 | M36: =ROUND(H36*12%,0) -> 3000 | N36: =ROUND(O36/12,0) -> 50000 | O36: 600000
A37: 36 | B37: ASG0036 | C37: 45782 | E37: Active | F37: Payroll Executive | G37: Payroll | H37: =ROUND(N37/2,0) -> 19792 | I37: =ROUND(H37*40%,0) -> 7917 | J37: =N37-H37-I37-K37-L37-M37 -> 9499 | M37: =ROUND(H37*12%,0) -> 2375 | N37: =ROUND(O37/12,0) -> 39583 | O37: 475000
A38: 37 | B38: ASG0037 | C38: 45831 | D38: 46008 | E38: Relieved | F38: Accounts Trainee | G38: Finance | H38: =ROUND(N38/2,0) -> 18750 | I38: =ROUND(H38*40%,0) -> 7500 | J38: =N38-H38-I38-K38-L38-M38 -> 9000 | M38: =ROUND(H38*12%,0) -> 2250 | N38: =ROUND(O38/12,0) -> 37500 | O38: 450000
A39: 38 | B39: ASG0038 | C39: 45852 | E39: Active | F39: Accounts Trainee | G39: Finance | H39: =ROUND(N39/2,0) -> 18750 | I39: =ROUND(H39*40%,0) -> 7500 | J39: =N39-H39-I39-K39-L39-M39 -> 9000 | M39: =ROUND(H39*12%,0) -> 2250 | N39: =ROUND(O39/12,0) -> 37500 | O39: 450000
A40: 39 | B40: ASG0039 | C40: 45901 | E40: Active | F40: BI Developer | G40: Analytics | H40: =ROUND(N40/2,0) -> 53125 | I40: =ROUND(H40*40%,0) -> 21250 | J40: =N40-H40-I40-K40-L40-M40 -> 22500 | K40: 2000 | L40: 1000 | M40: =ROUND(H40*12%,0) -> 6375 | N40: =ROUND(O40/12,0) -> 106250 | O40: 1275000
A41: 40 | B41: ASG0040 | C41: 45908 | D41: 46077 | E41: Relieved | F41: Payroll Executive | G41: Payroll | H41: =ROUND(N41/2,0) -> 19792 | I41: =ROUND(H41*40%,0) -> 7917 | J41: =N41-H41-I41-K41-L41-M41 -> 9499 | M41: =ROUND(H41*12%,0) -> 2375 | N41: =ROUND(O41/12,0) -> 39583 | O41: 475000
A42: 41 | B42: ASG0041 | C42: 45978 | E42: Active | F42: Data Analyst | G42: Analytics | H42: =ROUND(N42/2,0) -> 49167 | I42: =ROUND(H42*40%,0) -> 19667 | J42: =N42-H42-I42-K42-L42-M42 -> 20599 | K42: 2000 | L42: 1000 | M42: =ROUND(H42*12%,0) -> 5900 | N42: =ROUND(O42/12,0) -> 98333 | O42: 1180000
A43: 42 | B43: ASG0042 | C43: 45992 | E43: Active | F43: Sales Trainee | G43: Sales | H43: =ROUND(N43/2,0) -> 18750 | I43: =ROUND(H43*40%,0) -> 7500 | J43: =N43-H43-I43-K43-L43-M43 -> 9000 | M43: =ROUND(H43*12%,0) -> 2250 | N43: =ROUND(O43/12,0) -> 37500 | O43: 450000
A44: 43 | B44: ASG0043 | C44: 46027 | E44: Active | F44: HR Executive | G44: HR | H44: =ROUND(N44/2,0) -> 23959 | I44: =ROUND(H44*40%,0) -> 9584 | J44: =N44-H44-I44-K44-L44-M44 -> 11499 | M44: =ROUND(H44*12%,0) -> 2875 | N44: =ROUND(O44/12,0) -> 47917 | O44: 575000
A45: 44 | B45: ASG0044 | C45: 46041 | E45: Active | F45: Data Analyst | G45: Analytics | H45: =ROUND(N45/2,0) -> 47917 | I45: =ROUND(H45*40%,0) -> 19167 | J45: =N45-H45-I45-K45-L45-M45 -> 19999 | K45: 2000 | L45: 1000 | M45: =ROUND(H45*12%,0) -> 5750 | N45: =ROUND(O45/12,0) -> 95833 | O45: 1150000
A46: 45 | B46: ASG0045 | C46: 46056 | E46: Active | F46: Accounts Trainee | G46: Finance | H46: =ROUND(N46/2,0) -> 18750 | I46: =ROUND(H46*40%,0) -> 7500 | J46: =N46-H46-I46-K46-L46-M46 -> 9000 | M46: =ROUND(H46*12%,0) -> 2250 | N46: =ROUND(O46/12,0) -> 37500 | O46: 450000
A47: 46 | B47: ASG0046 | C47: 46062 | E47: Active | F47: HR Executive | G47: HR | H47: =ROUND(N47/2,0) -> 23959 | I47: =ROUND(H47*40%,0) -> 9584 | J47: =N47-H47-I47-K47-L47-M47 -> 11499 | M47: =ROUND(H47*12%,0) -> 2875 | N47: =ROUND(O47/12,0) -> 47917 | O47: 575000
A48: 47 | B48: ASG0047 | C48: 46063 | E48: Active | F48: HR Executive | G48: HR | H48: =ROUND(N48/2,0) -> 23959 | I48: =ROUND(H48*40%,0) -> 9584 | J48: =N48-H48-I48-K48-L48-M48 -> 11499 | M48: =ROUND(H48*12%,0) -> 2875 | N48: =ROUND(O48/12,0) -> 47917 | O48: 575000
A49: 48 | B49: ASG0048 | C49: 46091 | E49: Active | F49: Accounts Trainee | G49: Finance | H49: =ROUND(N49/2,0) -> 18750 | I49: =ROUND(H49*40%,0) -> 7500 | J49: =N49-H49-I49-K49-L49-M49 -> 9000 | M49: =ROUND(H49*12%,0) -> 2250 | N49: =ROUND(O49/12,0) -> 37500 | O49: 450000
A50: 49 | B50: ASG0049 | C50: 46098 | E50: Active | F50: Payroll Executive | G50: Payroll | H50: =ROUND(N50/2,0) -> 19792 | I50: =ROUND(H50*40%,0) -> 7917 | J50: =N50-H50-I50-K50-L50-M50 -> 9499 | M50: =ROUND(H50*12%,0) -> 2375 | N50: =ROUND(O50/12,0) -> 39583 | O50: 475000
A51: 50 | B51: ASG0050 | C51: 46105 | E51: Active | F51: Sales Trainee | G51: Sales | H51: =ROUND(N51/2,0) -> 18750 | I51: =ROUND(H51*40%,0) -> 7500 | J51: =N51-H51-I51-K51-L51-M51 -> 9000 | M51: =ROUND(H51*12%,0) -> 2250 | N51: =ROUND(O51/12,0) -> 37500 | O51: 450000

Sheet Employee Headcount
A1: Year | B1: Month | C1: Department | D1: No.of Employees | E1: New Joiners | F1: Relievers | G1: Head Count
A2: 2022 | B2: February | C2: Analytics | D2: 0 | E2: 1 | F2: 0 | G2: 1
A3: 2022 | B3: February | C3: Finance | D3: 0 | E3: 0 | F3: 0 | G3: 0
A4: 2022 | B4: February | C4: HR | D4: 0 | E4: 1 | F4: 0 | G4: 1
A5: 2022 | B5: February | C5: Payroll | D5: 0 | E5: 0 | F5: 0 | G5: 0
A6: 2022 | B6: February | C6: Sales | D6: 0 | E6: 0 | F6: 0 | G6: 0
A7: 2022 | B7: March | C7: Analytics | D7: 1 | E7: 0 | F7: 0 | G7: 1
A8: 2022 | B8: March | C8: Finance | D8: 0 | E8: 0 | F8: 0 | G8: 0
A9: 2022 | B9: March | C9: HR | D9: 1 | E9: 1 | F9: 0 | G9: 2
A10: 2022 | B10: March | C10: Payroll | D10: 0 | E10: 0 | F10: 0 | G10: 0
A11: 2022 | B11: March | C11: Sales | D11: 0 | E11: 0 | F11: 0 | G11: 0
A12: 2022 | B12: April | C12: Analytics | D12: 1 | E12: 1 | F12: 0 | G12: 2
A13: 2022 | B13: April | C13: Finance | D13: 0 | E13: 0 | F13: 0 | G13: 0
... A251: 2026 | B251: March | C251: Sales | D251: 7 | E251: 1 | F251: 0 | G251: 8

Sheet Monthly Payroll
A1: Payroll Month | B1: Employee Id | C1: Date Of Joining | D1: Date of Leaving | E1: Designation | F1: Department | G1: Location | H1: LOP Days | I1: Pay Days | J1: OT Hours | K1: Basic | L1: HRA | M1: Special Allowance | N1: Fuel Allowance | O1: Internet Allowance | P1: Overtime Pay | Q1: Target Incentive | R1: Gross Salary | S1: Employee PF | T1: Income Tax | U1: Loan Deduction | V1: Net Salary
A2: 46023 | B2: ASG0001 | C2: 44593 | E2: HR Manager | F2: HR | G2: =VLOOKUP(tblPayroll[[#This Row],[Employee Id]],Table1[[Employee Id]:[Work Location]],13,0) -> Bangalore | H2: 6 | I2: =31-H2 -> 25 | J2: 0 | K2: =ROUND(VLOOKUP($B2,'CTC Breakup'!$B$2:$O$51,7,0)/31*$I2,0) -> 62165 | L2: =ROUND(VLOOKUP($B2,'CTC Breakup'!$B$2:$O$51,8,0)/31*$I2,0) -> 24866 | M2: =ROUND(VLOOKUP($B2,'CTC Breakup'!$B$2:$O$51,9,0)/31*$I2,0) -> 27419 | N2: =ROUND(VLOOKUP($B2,'CTC Breakup'!$B$2:$O$51,10,0)/31*$I2,0) -> 1613 | O2: =ROUND(VLOOKUP($B2,'CTC Breakup'!$B$2:$O$51,11,0)/31*$I2,0) -> 806 | P2: =ROUND(((VLOOKUP($B2,'CTC Breakup'!$B$2:$N$51,13,0)-VLOOKUP($B2,'CTC Breakup'!$B$2:$N$51,12,0))/22/9)*$J2,0) -> 0 | Q2: 0 | R2: =SUM(K2:Q2) -> 116869 | S2: =ROUND(K2*12%,0) -> 7460 | T2: =ROUND(IF(R2>100000,R2*30%,IF(R2>75000,R2*20%,IF(R2>50000,R2*5%,0))),0) -> 35061 | U2: 0 | V2: =R2-S2-T2-U2 -> 74348 | X2: Total Net Salary for Q4 | Y2: =SUM(tblPayroll[Net Salary]) -> 6810287
A3: 46023 | B3: ASG0002 | C3: 44613 | E3: Analytics Manager | F3: Analytics | G3: =VLOOKUP(tblPayroll[[#This Row],[Employee Id]],Table1[[Employee Id]:[Work Location]],13,0) -> Chennai | H3: 10 | I3: =31-H3 -> 21 | J3: 0 | K3: =ROUND(VLOOKUP($B3,'CTC Breakup'!$B$2:$O$51,7,0)/31*$I3,0) -> 70565 | L3: =ROUND(VLOOKUP($B3,'CTC Breakup'!$B$2:$O$51,8,0)/31*$I3,0) -> 28226 | M3: =ROUND(VLOOKUP($B3,'CTC Breakup'!$B$2:$O$51,9,0)/31*$I3,0) -> 33870 | N3: =ROUND(VLOOKUP($B3,'CTC Breakup'!$B$2:$O$51,10,0)/31*$I3,0) -> 0 | O3: =ROUND(VLOOKUP($B3,'CTC Breakup'!$B$2:$O$51,11,0)/31*$I3,0) -> 0 | P3: =ROUND(((VLOOKUP($B3,'CTC Breakup'!$B$2:$N$51,13,0)-VLOOKUP($B3,'CTC Breakup'!$B$2:$N$51,12,0))/22/9)*$J3,0) -> 0 | Q3: 0 | R3: =SUM(K3:Q3) -> 132661 | S3: =ROUND(K3*12%,0) -> 8468 | T3: =ROUND(IF(R3>100000,R3*30%,IF(R3>75000,R3*20%,IF(R3>50000,R3*5%,0))),0) -> 39798 | U3: 0 | V3: =R3-S3-T3-U3 -> 84395
A4: 46023 | B4: ASG0003 | C4: 44634 | E4: HR Manager | F4: HR | G4: =VLOOKUP(tblPayroll[[#This Row],[Employee Id]],Table1[[Employee Id]:[Work Location]],13,0) -> Bangalore | H4: 0 | I4: =31-H4 -> 31 | J4: 24 | K4: =ROUND(VLOOKUP($B4,'CTC Breakup'!$B$2:$O$51,7,0)/31*$I4,0) -> 72917 | L4: =ROUND(VLOOKUP($B4,'CTC Breakup'!$B$2:$O$51,8,0)/31*$I4,0) -> 29167 | M4: =ROUND(VLOOKUP($B4,'CTC Breakup'!$B$2:$O$51,9,0)/31*$I4,0) -> 31999 | N4: =ROUND(VLOOKUP($B4,'CTC Breakup'!$B$2:$O$51,10,0)/31*$I4,0) -> 2000 | O4: =ROUND(VLOOKUP($B4,'CTC Breakup'!$B$2:$O$51,11,0)/31*$I4,0) -> 1000 | P4: =ROUND(((VLOOKUP($B4,'CTC Breakup'!$B$2:$N$51,13,0)-VLOOKUP($B4,'CTC Breakup'!$B$2:$N$51,12,0))/22/9)*$J4,0) -> 16616 | Q4: 0 | R4: =SUM(K4:Q4) -> 153699 | S4: =ROUND(K4*12%,0) -> 8750 | T4: =ROUND(IF(R4>100000,R4*30%,IF(R4>75000,R4*20%,IF(R4>50000,R4*5%,0))),0) -> 46110 | U4: 0 | V4: =R4-S4-T4-U4 -> 98839 | X4: Gross Salary Paid | Y4: =SUM(tblPayroll[Gross Salary]) -> 9636624
A5: 46023 | B5: ASG0005 | C5: 44697 | E5: Payroll Manager | F5: Payroll | G5: =VLOOKUP(tblPayroll[[#This Row],[Employee Id]],Table1[[Employee Id]:[Work Location]],13,0) -> Chennai | H5: 7 | I5: =31-H5 -> 24 | J5: 17 | K5: =ROUND(VLOOKUP($B5,'CTC Breakup'!$B$2:$O$51,7,0)/31*$I5,0) -> 54839 | L5: =ROUND(VLOOKUP($B5,'CTC Breakup'!$B$2:$O$51,8,0)/31*$I5,0) -> 21936 | M5: =ROUND(VLOOKUP($B5,'CTC Breakup'!$B$2:$O$51,9,0)/31*$I5,0) -> 23999 | N5: =ROUND(VLOOKUP($B5,'CTC Breakup'!$B$2:$O$51,10,0)/31*$I5,0) -> 1548 | O5: =ROUND(VLOOKUP($B5,'CTC Breakup'!$B$2:$O$51,11,0)/31*$I5,0) -> 774 | P5: =ROUND(((VLOOKUP($B5,'CTC Breakup'!$B$2:$N$51,13,0)-VLOOKUP($B5,'CTC Breakup'!$B$2:$N$51,12,0))/22/9)*$J5,0) -> 11434 | Q5: 0 | R5: =SUM(K5:Q5) -> 114530 | S5: =ROUND(K5*12%,0) -> 6581 | T5: =ROUND(IF(R5>100000,R5*30%,IF(R5>75000,R5*20%,IF(R5>50000,R5*5%,0))),0) -> 34359 | U5: 0 | V5: =R5-S5-T5-U5 -> 73590
A6: 46023 | B6: ASG0006 | C6: 44704 | E6: Senior Payroll Analyst | F6: Payroll | G6: =VLOOKUP(tblPayroll[[#This Row],[Employee Id]],Table1[[Employee Id]:[Work Location]],13,0) -> Mumbai | H6: 0 | I6: =31-H6 -> 31 | J6: 0 | K6: =ROUND(VLOOKUP($B6,'CTC Breakup'!$B$2:$O$51,7,0)/31*$I6,0) -> 41667 | L6: =ROUND(VLOOKUP($B6,'CTC Breakup'!$B$2:$O$51,8,0)/31*$I6,0) -> 16667 | M6: =ROUND(VLOOKUP($B6,'CTC Breakup'!$B$2:$O$51,9,0)/31*$I6,0) -> 16999 | N6: =ROUND(VLOOKUP($B6,'CTC Breakup'!$B$2:$O$51,10,0)/31*$I6,0) -> 2000 | O6: =ROUND(VLOOKUP($B6,'CTC Breakup'!$B$2:$O$51,11,0)/31*$I6,0) -> 1000 | P6: =ROUND(((VLOOKUP($B6,'CTC Breakup'!$B$2:$N$51,13,0)-VLOOKUP($B6,'CTC Breakup'!$B$2:$N$51,12,0))/22/9)*$J6,0) -> 0 | Q6: 0 | R6: =SUM(K6:Q6) -> 78333 | S6: =ROUND(K6*12%,0) -> 5000 | T6: =ROUND(IF(R6>100000,R6*30%,IF(R6>75000,R6*20%,IF(R6>50000,R6*5%,0))),0) -> 15667 | U6: 12500 | V6: =R6-S6-T6-U6 -> 45166 | X6: Total OT Hours | Y6: =SUM(tblPayroll[OT Hours]) -> 946
A7: 46023 | B7: ASG0008 | C7: 44886 | E7: Sales Manager | F7: Sales | G7: =VLOOKUP(tblPayroll[[#This Row],[Employee Id]],Table1[[Employee Id]:[Work Location]],13,0) -> Kolkata | H7: 0 | I7: =31-H7 -> 31 | J7: 20 | K7: =ROUND(VLOOKUP($B7,'CTC Breakup'!$B$2:$O$51,7,0)/31*$I7,0) -> 87500 | L7: =ROUND(VLOOKUP($B7,'CTC Breakup'!$B$2:$O$51,8,0)/31*$I7,0) -> 35000 | M7: =ROUND(VLOOKUP($B7,'CTC Breakup'!$B$2:$O$51,9,0)/31*$I7,0) -> 39000 | N7: =ROUND(VLOOKUP($B7,'CTC Breakup'!$B$2:$O$51,10,0)/31*$I7,0) -> 2000 | O7: =ROUND(VLOOKUP($B7,'CTC Breakup'!$B$2:$O$51,11,0)/31*$I7,0) -> 1000 | P7: =ROUND(((VLOOKUP($B7,'CTC Breakup'!$B$2:$N$51,13,0)-VLOOKUP($B7,'CTC Breakup'!$B$2:$N$51,12,0))/22/9)*$J7,0) -> 16616 | Q7: 31000 | R7: =SUM(K7:Q7) -> 212116 | S7: =ROUND(K7*12%,0) -> 10500 | T7: =ROUND(IF(R7>100000,R7*30%,IF(R7>75000,R7*20%,IF(R7>50000,R7*5%,0))),0) -> 63635 | U7: 0 | V7: =R7-S7-T7-U7 -> 137981
A8: 46023 | B8: ASG0009 | C8: 44893 | E8: Regional Sales Lead | F8: Sales | G8: =VLOOKUP(tblPayroll[[#This Row],[Employee Id]],Table1[[Employee Id]:[Work Location]],13,0) -> Hyderabad | H8: 0 | I8: =31-H8 -> 31 | J8: 19 | K8: =ROUND(VLOOKUP($B8,'CTC Breakup'!$B$2:$O$51,7,0)/31*$I8,0) -> 75000 | L8: =ROUND(VLOOKUP($B8,'CTC Breakup'!$B$2:$O$51,8,0)/31*$I8,0) -> 30000 | M8: =ROUND(VLOOKUP($B8,'CTC Breakup'!$B$2:$O$51,9,0)/31*$I8,0) -> 33000 | N8: =ROUND(VLOOKUP($B8,'CTC Breakup'!$B$2:$O$51,10,0)/31*$I8,0) -> 2000 | O8: =ROUND(VLOOKUP($B8,'CTC Breakup'!$B$2:$O$51,11,0)/31*$I8,0) -> 1000 | P8: =ROUND(((VLOOKUP($B8,'CTC Breakup'!$B$2:$N$51,13,0)-VLOOKUP($B8,'CTC Breakup'!$B$2:$N$51,12,0))/22/9)*$J8,0) -> 13530 | Q8: 27500 | R8: =SUM(K8:Q8) -> 182030 | S8: =ROUND(K8*12%,0) -> 9000 | T8: =ROUND(IF(R8>100000,R8*30%,IF(R8>75000,R8*20%,IF(R8>50000,R8*5%,0))),0) -> 54609 | U8: 0 | V8: =R8-S8-T8-U8 -> 118421 | X8: Total LOP Days | Y8: =SUM(tblPayroll[LOP Days]) -> 269
A9: 46023 | B9: ASG0010 | C9: 44907 | E9: Finance Manager | F9: Finance | G9: =VLOOKUP(tblPayroll[[#This Row],[Employee Id]],Table1[[Employee Id]:[Work Location]],13,0) -> Mumbai | H9: 0 | I9: =31-H9 -> 31 | J9: 0 | K9: =ROUND(VLOOKUP($B9,'CTC Breakup'!$B$2:$O$51,7,0)/31*$I9,0) -> 72917 | L9: =ROUND(VLOOKUP($B9,'CTC Breakup'!$B$2:$O$51,8,0)/31*$I9,0) -> 29167 | M9: =ROUND(VLOOKUP($B9,'CTC Breakup'!$B$2:$O$51,9,0)/31*$I9,0) -> 31999 | N9: =ROUND(VLOOKUP($B9,'CTC Breakup'!$B$2:$O$51,10,0)/31*$I9,0) -> 2000 | O9: =ROUND(VLOOKUP($B9,'CTC Breakup'!$B$2:$O$51,11,0)/31*$I9,0) -> 1000 | P9: =ROUND(((VLOOKUP($B9,'CTC Breakup'!$B$2:$N$51,13,0)-VLOOKUP($B9,'CTC Breakup'!$B$2:$N$51,12,0))/22/9)*$J9,0) -> 0 | Q9: 0 | R9: =SUM(K9:Q9) -> 137083 | S9: =ROUND(K9*12%,0) -> 8750 | T9: =ROUND(IF(R9>100000,R9*30%,IF(R9>75000,R9*20%,IF(R9>50000,R9*5%,0))),0) -> 41125 | U9: 0 | V9: =R9-S9-T9-U9 -> 87208
A10: 46023 | B10: ASG0012 | C10: 44956 | E10: Senior Sales Executive | F10: Sales | G10: =VLOOKUP(tblPayroll[[#This Row],[Employee Id]],Table1[[Employee Id]:[Work Location]],13,0) -> Chennai | H10: 6 | I10: =31-H10 -> 25 | J10: 0 | K10: =ROUND(VLOOKUP($B10,'CTC Breakup'!$B$2:$O$51,7,0)/31*$I10,0) -> 38643 | L10: =ROUND(VLOOKUP($B10,'CTC Breakup'!$B$2:$O$51,8,0)/31*$I10,0) -> 15457 | M10: =ROUND(VLOOKUP($B10,'CTC Breakup'!$B$2:$O$51,9,0)/31*$I10,0) -> 16128 | N10: =ROUND(VLOOKUP($B10,'CTC Breakup'!$B$2:$O$51,10,0)/31*$I10,0) -> 1613 | O10: =ROUND(VLOOKUP($B10,'CTC Breakup'!$B$2:$O$51,11,0)/31*$I10,0) -> 806 | P10: =ROUND(((VLOOKUP($B10,'CTC Breakup'!$B$2:$N$51,13,0)-VLOOKUP($B10,'CTC Breakup'!$B$2:$N$51,12,0))/22/9)*$J10,0) -> 0 | Q10: 21400 | R10: =SUM(K10:Q10) -> 94047 | S10: =ROUND(K10*12%,0) -> 4637 | T10: =ROUND(IF(R10>100000,R10*30%,IF(R10>75000,R10*20%,IF(R10>50000,R10*5%,0))),0) -> 18809 | U10: 0 | V10: =R10-S10-T10-U10 -> 70601 | X10: Costliest Location | Y10: =INDEX($G$2:$G$117, MATCH(MAX($V$2:$V$117), $V$2:$V$117, 0)) -> Kolkata
A11: 46023 | B11: ASG0013 | C11: 44963 | E11: Senior Data Analyst | F11: Analytics | G11: =VLOOKUP(tblPayroll[[#This Row],[Employee Id]],Table1[[Employee Id]:[Work Location]],13,0) -> Bangalore | H11: 0 | I11: =31-H11 -> 31 | J11: 0 | K11: =ROUND(VLOOKUP($B11,'CTC Breakup'!$B$2:$O$51,7,0)/31*$I11,0) -> 64584 | L11: =ROUND(VLOOKUP($B11,'CTC Breakup'!$B$2:$O$51,8,0)/31*$I11,0) -> 25834 | M11: =ROUND(VLOOKUP($B11,'CTC Breakup'!$B$2:$O$51,9,0)/31*$I11,0) -> 27999 | N11: =ROUND(VLOOKUP($B11,'CTC Breakup'!$B$2:$O$51,10,0)/31*$I11,0) -> 2000 | O11: =ROUND(VLOOKUP($B11,'CTC Breakup'!$B$2:$O$51,11,0)/31*$I11,0) -> 1000 | P11: =ROUND(((VLOOKUP($B11,'CTC Breakup'!$B$2:$N$51,13,0)-VLOOKUP($B11,'CTC Breakup'!$B$2:$N$51,12,0))/22/9)*$J11,0) -> 0 | Q11: 0 | R11: =SUM(K11:Q11) -> 121417 | S11: =ROUND(K11*12%,0) -> 7750 | T11: =ROUND(IF(R11>100000,R11*30%,IF(R11>75000,R11*20%,IF(R11>50000,R11*5%,0))),0) -> 36425 | U11: 0 | V11: =R11-S11-T11-U11 -> 77242
A12: 46023 | B12: ASG0015 | C12: 45033 | E12: Senior Data Analyst | F12: Analytics | G12: =VLOOKUP(tblPayroll[[#This Row],[Employee Id]],Table1[[Employee Id]:[Work Location]],13,0) -> Hyderabad | H12: 0 | I12: =31-H12 -> 31 | J12: 0 | K12: =ROUND(VLOOKUP($B12,'CTC Breakup'!$B$2:$O$51,7,0)/31*$I12,0) -> 61459 | L12: =ROUND(VLOOKUP($B12,'CTC Breakup'!$B$2:$O$51,8,0)/31*$I12,0) -> 24584 | M12: =ROUND(VLOOKUP($B12,'CTC Breakup'!$B$2:$O$51,9,0)/31*$I12,0) -> 26499 | N12: =ROUND(VLOOKUP($B12,'CTC Breakup'!$B$2:$O$51,10,0)/31*$I12,0) -> 2000 | O12: =ROUND(VLOOKUP($B12,'CTC Breakup'!$B$2:$O$51,11,0)/31*$I12,0) -> 1000 | P12: =ROUND(((VLOOKUP($B12,'CTC Breakup'!$B$2:$N$51,13,0)-VLOOKUP($B12,'CTC Breakup'!$B$2:$N$51,12,0))/22/9)*$J12,0) -> 0 | Q12: 0 | R12: =SUM(K12:Q12) -> 115542 | S12: =ROUND(K12*12%,0) -> 7375 | T12: =ROUND(IF(R12>100000,R12*30%,IF(R12>75000,R12*20%,IF(R12>50000,R12*5%,0))),0) -> 34663 | U12: 0 | V12: =R12-S12-T12-U12 -> 73504 | X12: Costliest Department | Y12: =INDEX($F$2:$F$117, MATCH(MAX($V$2:$V$117), $V$2:$V$117, 0)) -> Sales
A13: 46023 | B13: ASG0016 | C13: 45040 | E13: Senior Data Analyst | F13: Analytics | G13: =VLOOKUP(tblPayroll[[#This Row],[Employee Id]],Table1[[Employee Id]:[Work Location]],13,0) -> Bangalore | H13: 0 | I13: =31-H13 -> 31 | J13: 16 | K13: =ROUND(VLOOKUP($B13,'CTC Breakup'!$B$2:$O$51,7,0)/31*$I13,0) -> 78125 | L13: =ROUND(VLOOKUP($B13,'CTC Breakup'!$B$2:$O$51,8,0)/31*$I13,0) -> 31250 | M13: =ROUND(VLOOKUP($B13,'CTC Breakup'!$B$2:$O$51,9,0)/31*$I13,0) -> 34500 | N13: =ROUND(VLOOKUP($B13,'CTC Breakup'!$B$2:$O$51,10,0)/31*$I13,0) -> 2000 | O13: =ROUND(VLOOKUP($B13,'CTC Breakup'!$B$2:$O$51,11,0)/31*$I13,0) -> 1000 | P13: =ROUND(((VLOOKUP($B13,'CTC Breakup'!$B$2:$N$51,13,0)-VLOOKUP($B13,'CTC Breakup'!$B$2:$N$51,12,0))/22/9)*$J13,0) -> 11869 | Q13: 0 | R13: =SUM(K13:Q13) -> 158744 | S13: =ROUND(K13*12%,0) -> 9375 | T13: =ROUND(IF(R13>100000,R13*30%,IF(R13>75000,R13*20%,IF(R13>50000,R13*5%,0))),0) -> 47623 | U13: 0 | V13: =R13-S13-T13-U13 -> 101746
A14: 46023 | B14: ASG0017 | C14: 45048 | D14: 46055 | E14: Sr Accountant | F14: Finance | G14: =VLOOKUP(tblPayroll[[#This Row],[Employee Id]],Table1[[Employee Id]:[Work Location]],13,0) -> Chennai | H14: 6 | I14: =31-H14 -> 25 | J14: 0 | K14: =ROUND(VLOOKUP($B14,'CTC Breakup'!$B$2:$O$51,7,0)/31*$I14,0) -> 38643 | L14: =ROUND(VLOOKUP($B14,'CTC Breakup'!$B$2:$O$51,8,0)/31*$I14,0) -> 15457 | M14: =ROUND(VLOOKUP($B14,'CTC Breakup'!$B$2:$O$51,9,0)/31*$I14,0) -> 16128 | N14: =ROUND(VLOOKUP($B14,'CTC Breakup'!$B$2:$O$51,10,0)/31*$I14,0) -> 1613 | O14: =ROUND(VLOOKUP($B14,'CTC Breakup'!$B$2:$O$51,11,0)/31*$I14,0) -> 806 | P14: =ROUND(((VLOOKUP($B14,'CTC Breakup'!$B$2:$N$51,13,0)-VLOOKUP($B14,'CTC Breakup'!$B$2:$N$51,12,0))/22/9)*$J14,0) -> 0 | Q14: 0 | R14: =SUM(K14:Q14) -> 72647 | S14: =ROUND(K14*12%,0) -> 4637 | T14: =ROUND(IF(R14>100000,R14*30%,IF(R14>75000,R14*20%,IF(R14>50000,R14*10%,0))),0) -> 7265 | U14: 0 | V14: =R14-S14-T14-U14 -> 60745
A15: 46023 | B15: ASG0018 | C15: 45075 | E15: Sr Accountant | F15: Finance | G15: =VLOOKUP(tblPayroll[[#This Row],[Employee Id]],Table1[[Employee Id]:[Work Location]],13,0) -> Bangalore | H15: 7 | I15: =31-H15 -> 24 | J15: 0 | K15: =ROUND(VLOOKUP($B15,'CTC Breakup'!$B$2:$O$51,7,0)/31*$I15,0) -> 36290 | L15: =ROUND(VLOOKUP($B15,'CTC Breakup'!$B$2:$O$51,8,0)/31*$I15,0) -> 14516 | M15: =ROUND(VLOOKUP($B15,'CTC Breakup'!$B$2:$O$51,9,0)/31*$I15,0) -> 15097 | N15: =ROUND(VLOOKUP($B15,'CTC Breakup'!$B$2:$O$51,10,0)/31*$I15,0) -> 1548 | O15: =ROUND(VLOOKUP($B15,'CTC Breakup'!$B$2:$O$51,11,0)/31*$I15,0) -> 774 | P15: =ROUND(((VLOOKUP($B15,'CTC Breakup'!$B$2:$N$51,13,0)-VLOOKUP($B15,'CTC Breakup'!$B$2:$N$51,12,0))/22/9)*$J15,0) -> 0 | Q15: 0 | R15: =SUM(K15:Q15) -> 68225 | S15: =ROUND(K15*12%,0) -> 4355 | T15: =ROUND(IF(R15>100000,R15*30%,IF(R15>75000,R15*20%,IF(R15>50000,R15*10%,0))),0) -> 6823 | U15: 12400 | V15: =R15-S15-T15-U15 -> 44647
A16: 46023 | B16: ASG0019 | C16: 45170 | E16: Senior Sales Executive | F16: Sales | G16: =VLOOKUP(tblPayroll[[#This Row],[Employee Id]],Table1[[Employee Id]:[Work Location]],13,0) -> Mumbai | H16: 0 | I16: =31-H16 -> 31 | J16: 0 | K16: =ROUND(VLOOKUP($B16,'CTC Breakup'!$B$2:$O$51,7,0)/31*$I16,0) -> 45834 | L16: =ROUND(VLOOKUP($B16,'CTC Breakup'!$B$2:$O$51,8,0)/31*$I16,0) -> 18334 | M16: =ROUND(VLOOKUP($B16,'CTC Breakup'!$B$2:$O$51,9,0)/31*$I16,0) -> 18999 | N16: =ROUND(VLOOKUP($B16,'CTC Breakup'!$B$2:$O$51,10,0)/31*$I16,0) -> 2000 | O16: =ROUND(VLOOKUP($B16,'CTC Breakup'!$B$2:$O$51,11,0)/31*$I16,0) -> 1000 | P16: =ROUND(((VLOOKUP($B16,'CTC Breakup'!$B$2:$N$51,13,0)-VLOOKUP($B16,'CTC Breakup'!$B$2:$N$51,12,0))/22/9)*$J16,0) -> 0 | Q16: 20740 | R16: =SUM(K16:Q16) -> 106907 | S16: =ROUND(K16*12%,0) -> 5500 | T16: =ROUND(IF(R16>100000,R16*30%,IF(R16>75000,R16*20%,IF(R16>50000,R16*5%,0))),0) -> 32072 | U16: 11200 | V16: =R16-S16-T16-U16 -> 58135
A17: 46023 | B17: ASG0020 | C17: 45173 | E17: Sales Executive | F17: Sales | G17: =VLOOKUP(tblPayroll[[#This Row],[Employee Id]],Table1[[Employee Id]:[Work Location]],13,0) -> Kolkata | H17: 9 | I17: =31-H17 -> 22 | J17: 0 | K17: =ROUND(VLOOKUP($B17,'CTC Breakup'!$B$2:$O$51,7,0)/31*$I17,0) -> 23065 | L17: =ROUND(VLOOKUP($B17,'CTC Breakup'!$B$2:$O$51,8,0)/31*$I17,0) -> 9226 | M17: =ROUND(VLOOKUP($B17,'CTC Breakup'!$B$2:$O$51,9,0)/31*$I17,0) -> 11071 | N17: =ROUND(VLOOKUP($B17,'CTC Breakup'!$B$2:$O$51,10,0)/31*$I17,0) -> 0 | O17: =ROUND(VLOOKUP($B17,'CTC Breakup'!$B$2:$O$51,11,0)/31*$I17,0) -> 0 | P17: =ROUND(((VLOOKUP($B17,'CTC Breakup'!$B$2:$N$51,13,0)-VLOOKUP($B17,'CTC Breakup'!$B$2:$N$51,12,0))/22/9)*$J17,0) -> 0 | Q17: 14300 | R17: =SUM(K17:Q17) -> 57662 | S17: =ROUND(K17*12%,0) -> 2768 | T17: =ROUND(IF(R17>100000,R17*30%,IF(R17>75000,R17*20%,IF(R17>50000,R17*10%,0))),0) -> 5766 | U17: 0 | V17: =R17-S17-T17-U17 -> 49128
A18: 46023 | B18: ASG0022 | C18: 45236 | E18: Payroll Analyst | F18: Payroll | G18: =VLOOKUP(tblPayroll[[#This Row],[Employee Id]],Table1[[Employee Id]:[Work Location]],13,0) -> Mumbai | H18: 0 | I18: =31-H18 -> 31 | J18: 24 | K18: =ROUND(VLOOKUP($B18,'CTC Breakup'!$B$2:$O$51,7,0)/31*$I18,0) -> 28334 | L18: =ROUND(VLOOKUP($B18,'CTC Breakup'!$B$2:$O$51,8,0)/31*$I18,0) -> 11334 | M18: =ROUND(VLOOKUP($B18,'CTC Breakup'!$B$2:$O$51,9,0)/31*$I18,0) -> 13599 | N18: =ROUND(VLOOKUP($B18,'CTC Breakup'!$B$2:$O$51,10,0)/31*$I18,0) -> 0 | O18: =ROUND(VLOOKUP($B18,'CTC Breakup'!$B$2:$O$51,11,0)/31*$I18,0) -> 0 | P18: =ROUND(((VLOOKUP($B18,'CTC Breakup'!$B$2:$N$51,13,0)-VLOOKUP($B18,'CTC Breakup'!$B$2:$N$51,12,0))/22/9)*$J18,0) -> 6457 | Q18: 0 | R18: =SUM(K18:Q18) -> 59724 | S18: =ROUND(K18*12%,0) -> 3400 | T18: =ROUND(IF(R18>100000,R18*30%,IF(R18>75000,R18*20%,IF(R18>50000,R18*10%,0))),0) -> 5972 | U18: 0 | V18: =R18-S18-T18-U18 -> 50352
A19: 46023 | B19: ASG0023 | C19: 45320 | E19: HR Analyst | F19: HR | G19: =VLOOKUP(tblPayroll[[#This Row],[Employee Id]],Table1[[Employee Id]:[Work Location]],13,0) -> Hyderabad | H19: 6 | I19: =31-H19 -> 25 | J19: 0 | K19: =ROUND(VLOOKUP($B19,'CTC Breakup'!$B$2:$O$51,7,0)/31*$I19,0) -> 40323 | L19: =ROUND(VLOOKUP($B19,'CTC Breakup'!$B$2:$O$51,8,0)/31*$I19,0) -> 16129 | M19: =ROUND(VLOOKUP($B19,'CTC Breakup'!$B$2:$O$51,9,0)/31*$I19,0) -> 16935 | N19: =ROUND(VLOOKUP($B19,'CTC Breakup'!$B$2:$O$51,10,0)/31*$I19,0) -> 1613 | O19: =ROUND(VLOOKUP($B19,'CTC Breakup'!$B$2:$O$51,11,0)/31*$I19,0) -> 806 | P19: =ROUND(((VLOOKUP($B19,'CTC Breakup'!$B$2:$N$51,13,0)-VLOOKUP($B19,'CTC Breakup'!$B$2:$N$51,12,0))/22/9)*$J19,0) -> 0 | Q19: 0 | R19: =SUM(K19:Q19) -> 75806 | S19: =ROUND(K19*12%,0) -> 4839 | T19: =ROUND(IF(R19>100000,R19*30%,IF(R19>75000,R19*20%,IF(R19>50000,R19*5%,0))),0) -> 15161 | U19: 13800 | V19: =R19-S19-T19-U19 -> 42006
A20: 46023 | B20: ASG0024 | C20: 45327 | D20: 46084 | E20: Accounts Executive | F20: Finance | G20: =VLOOKUP(tblPayroll[[#This Row],[Employee Id]],Table1[[Employee Id]:[Work Location]],13,0) -> Kolkata | H20: 0 | I20: =31-H20 -> 31 | J20: 0 | K20: =ROUND(VLOOKUP($B20,'CTC Breakup'!$B$2:$O$51,7,0)/31*$I20,0) -> 32500 | L20: =ROUND(VLOOKUP($B20,'CTC Breakup'!$B$2:$O$51,8,0)/31*$I20,0) -> 13000 | M20: =ROUND(VLOOKUP($B20,'CTC Breakup'!$B$2:$O$51,9,0)/31*$I20,0) -> 15600 | N20: =ROUND(VLOOKUP($B20,'CTC Breakup'!$B$2:$O$51,10,0)/31*$I20,0) -> 0 | O20: =ROUND(VLOOKUP($B20,'CTC Breakup'!$B$2:$O$51,11,0)/31*$I20,0) -> 0 | P20: =ROUND(((VLOOKUP($B20,'CTC Breakup'!$B$2:$N$51,13,0)-VLOOKUP($B20,'CTC Breakup'!$B$2:$N$51,12,0))/22/9)*$J20,0) -> 0 | Q20: 0 | R20: =SUM(K20:Q20) -> 61100 | S20: =ROUND(K20*12%,0) -> 3900 | T20: =ROUND(IF(R20>100000,R20*30%,IF(R20>75000,R20*20%,IF(R20>50000,R20*10%,0))),0) -> 6110 | U20: 0 | V20: =R20-S20-T20-U20 -> 51090
A21: 46023 | B21: ASG0025 | C21: 45328 | E21: Accounts Executive | F21: Finance | G21: =VLOOKUP(tblPayroll[[#This Row],[Employee Id]],Table1[[Employee Id]:[Work Location]],13,0) -> Chennai | H21: 0 | I21: =31-H21 -> 31 | J21: 0 | K21: =ROUND(VLOOKUP($B21,'CTC Breakup'!$B$2:$O$51,7,0)/31*$I21,0) -> 30209 | L21: =ROUND(VLOOKUP($B21,'CTC Breakup'!$B$2:$O$51,8,0)/31*$I21,0) -> 12084 | M21: =ROUND(VLOOKUP($B21,'CTC Breakup'!$B$2:$O$51,9,0)/31*$I21,0) -> 14499 | N21: =ROUND(VLOOKUP($B21,'CTC Breakup'!$B$2:$O$51,10,0)/31*$I21,0) -> 0 | O21: =ROUND(VLOOKUP($B21,'CTC Breakup'!$B$2:$O$51,11,0)/31*$I21,0) -> 0 | P21: =ROUND(((VLOOKUP($B21,'CTC Breakup'!$B$2:$N$51,13,0)-VLOOKUP($B21,'CTC Breakup'!$B$2:$N$51,12,0))/22/9)*$J21,0) -> 0 | Q21: 0 | R21: =SUM(K21:Q21) -> 56792 | S21: =ROUND(K21*12%,0) -> 3625 | T21: =ROUND(IF(R21>100000,R21*30%,IF(R21>75000,R21*20%,IF(R21>50000,R21*10%,0))),0) -> 5679 | U21: 0 | V21: =R21-S21-T21-U21 -> 47488
A22: 46023 | B22: ASG0027 | C22: 45418 | E22: HR Analyst | F22: HR | G22: =VLOOKUP(tblPayroll[[#This Row],[Employee Id]],Table1[[Employee Id]:[Work Location]],13,0) -> Mumbai | H22: 0 | I22: =31-H22 -> 31 | J22: 0 | K22: =ROUND(VLOOKUP($B22,'CTC Breakup'!$B$2:$O$51,7,0)/31*$I22,0) -> 47917 | L22: =ROUND(VLOOKUP($B22,'CTC Breakup'!$B$2:$O$51,8,0)/31*$I22,0) -> 19167 | M22: =ROUND(VLOOKUP($B22,'CTC Breakup'!$B$2:$O$51,9,0)/31*$I22,0) -> 19999 | N22: =ROUND(VLOOKUP($B22,'CTC Breakup'!$B$2:$O$51,10,0)/31*$I22,0) -> 2000 | O22: =ROUND(VLOOKUP($B22,'CTC Breakup'!$B$2:$O$51,11,0)/31*$I22,0) -> 1000 | P22: =ROUND(((VLOOKUP($B22,'CTC Breakup'!$B$2:$N$51,13,0)-VLOOKUP($B22,'CTC Breakup'!$B$2:$N$51,12,0))/22/9)*$J22,0) -> 0 | Q22: 0 | R22: =SUM(K22:Q22) -> 90083 | S22: =ROUND(K22*12%,0) -> 5750 | T22: =ROUND(IF(R22>100000,R22*30%,IF(R22>75000,R22*20%,IF(R22>50000,R22*5%,0))),0) -> 18017 | U22: 0 | V22: =R22-S22-T22-U22 -> 66316
A23: 46023 | B23: ASG0028 | C23: 45502 | E23: Sales Trainee | F23: Sales | G23: =VLOOKUP(tblPayroll[[#This Row],[Employee Id]],Table1[[Employee Id]:[Work Location]],13,0) -> Hyderabad | H23: 0 | I23: =31-H23 -> 31 | J23: 17 | K23: =ROUND(VLOOKUP($B23,'CTC Breakup'!$B$2:$O$51,7,0)/31*$I23,0) -> 18750 | L23: =ROUND(VLOOKUP($B23,'CTC Breakup'!$B$2:$O$51,8,0)/31*$I23,0) -> 7500 | M23: =ROUND(VLOOKUP($B23,'CTC Breakup'!$B$2:$O$51,9,0)/31*$I23,0) -> 9000 | N23: =ROUND(VLOOKUP($B23,'CTC Breakup'!$B$2:$O$51,10,0)/31*$I23,0) -> 0 | O23: =ROUND(VLOOKUP($B23,'CTC Breakup'!$B$2:$O$51,11,0)/31*$I23,0) -> 0 | P23: =ROUND(((VLOOKUP($B23,'CTC Breakup'!$B$2:$N$51,13,0)-VLOOKUP($B23,'CTC Breakup'!$B$2:$N$51,12,0))/22/9)*$J23,0) -> 3027 | Q23: 9450 | R23: =SUM(K23:Q23) -> 47727 | S23: =ROUND(K23*12%,0) -> 2250 | T23: =ROUND(IF(R23>100000,R23*30%,IF(R23>75000,R23*20%,IF(R23>50000,R23*10%,0))),0) -> 0 | U23: 0 | V23: =R23-S23-T23-U23 -> 45477
A24: 46023 | B24: ASG0029 | C24: 45509 | E24: Payroll Analyst | F24: Payroll | G24: =VLOOKUP(tblPayroll[[#This Row],[Employee Id]],Table1[[Employee Id]:[Work Location]],13,0) -> Kolkata | H24: 0 | I24: =31-H24 -> 31 | J24: 0 | K24: =ROUND(VLOOKUP($B24,'CTC Breakup'!$B$2:$O$51,7,0)/31*$I24,0) -> 27084 | L24: =ROUND(VLOOKUP($B24,'CTC Breakup'!$B$2:$O$51,8,0)/31*$I24,0) -> 10834 | M24: =ROUND(VLOOKUP($B24,'CTC Breakup'!$B$2:$O$51,9,0)/31*$I24,0) -> 12999 | N24: =ROUND(VLOOKUP($B24,'CTC Breakup'!$B$2:$O$51,10,0)/31*$I24,0) -> 0 | O24: =ROUND(VLOOKUP($B24,'CTC Breakup'!$B$2:$O$51,11,0)/31*$I24,0) -> 0 | P24: =ROUND(((VLOOKUP($B24,'CTC Breakup'!$B$2:$N$51,13,0)-VLOOKUP($B24,'CTC Breakup'!$B$2:$N$51,12,0))/22/9)*$J24,0) -> 0 | Q24: 0 | R24: =SUM(K24:Q24) -> 50917 | S24: =ROUND(K24*12%,0) -> 3250 | T24: =ROUND(IF(R24>100000,R24*30%,IF(R24>75000,R24*20%,IF(R24>50000,R24*10%,0))),0) -> 5092 | U24: 0 | V24: =R24-S24-T24-U24 -> 42575
A25: 46023 | B25: ASG0030 | C25: 45537 | D25: 46098 | E25: Senior Data Analyst | F25: Analytics | G25: =VLOOKUP(tblPayroll[[#This Row],[Employee Id]],Table1[[Employee Id]:[Work Location]],13,0) -> Hyderabad | H25: 10 | I25: =31-H25 -> 21 | J25: 22 | K25: =ROUND(VLOOKUP($B25,'CTC Breakup'!$B$2:$O$51,7,0)/31*$I25,0) -> 40504 | L25: =ROUND(VLOOKUP($B25,'CTC Breakup'!$B$2:$O$51,8,0)/31*$I25,0) -> 16202 | M25: =ROUND(VLOOKUP($B25,'CTC Breakup'!$B$2:$O$51,9,0)/31*$I25,0) -> 17409 | N25: =ROUND(VLOOKUP($B25,'CTC Breakup'!$B$2:$O$51,10,0)/31*$I25,0) -> 1355 | O25: =ROUND(VLOOKUP($B25,'CTC Breakup'!$B$2:$O$51,11,0)/31*$I25,0) -> 677 | P25: =ROUND(((VLOOKUP($B25,'CTC Breakup'!$B$2:$N$51,13,0)-VLOOKUP($B25,'CTC Breakup'!$B$2:$N$51,12,0))/22/9)*$J25,0) -> 12490 | Q25: 0 | R25: =SUM(K25:Q25) -> 88637 | S25: =ROUND(K25*12%,0) -> 4860 | T25: =ROUND(IF(R25>100000,R25*30%,IF(R25>75000,R25*20%,IF(R25>50000,R25*5%,0))),0) -> 17727 | U25: 11100 | V25: =R25-S25-T25-U25 -> 54950
A26: 46023 | B26: ASG0031 | C26: 45579 | E26: Accounts Executive | F26: Finance | G26: =VLOOKUP(tblPayroll[[#This Row],[Employee Id]],Table1[[Employee Id]:[Work Location]],13,0) -> Bangalore | H26: 10 | I26: =31-H26 -> 21 | J26: 17 | K26: =ROUND(VLOOKUP($B26,'CTC Breakup'!$B$2:$O$51,7,0)/31*$I26,0) -> 19758 | L26: =ROUND(VLOOKUP($B26,'CTC Breakup'!$B$2:$O$51,8,0)/31*$I26,0) -> 7903 | M26: =ROUND(VLOOKUP($B26,'CTC Breakup'!$B$2:$O$51,9,0)/31*$I26,0) -> 9483 | N26: =ROUND(VLOOKUP($B26,'CTC Breakup'!$B$2:$O$51,10,0)/31*$I26,0) -> 0 | O26: =ROUND(VLOOKUP($B26,'CTC Breakup'!$B$2:$O$51,11,0)/31*$I26,0) -> 0 | P26: =ROUND(((VLOOKUP($B26,'CTC Breakup'!$B$2:$N$51,13,0)-VLOOKUP($B26,'CTC Breakup'!$B$2:$N$51,12,0))/22/9)*$J26,0) -> 4708 | Q26: 0 | R26: =SUM(K26:Q26) -> 41852 | S26: =ROUND(K26*12%,0) -> 2371 | T26: =ROUND(IF(R26>100000,R26*30%,IF(R26>75000,R26*20%,IF(R26>50000,R26*5%,0))),0) -> 0 | U26: 11400 | V26: =R26-S26-T26-U26 -> 28081
A27: 46023 | B27: ASG0032 | C27: 45607 | E27: HR Executive | F27: HR | G27: =VLOOKUP(tblPayroll[[#This Row],[Employee Id]],Table1[[Employee Id]:[Work Location]],13,0) -> Chennai | H27: 0 | I27: =31-H27 -> 31 | J27: 0 | K27: =ROUND(VLOOKUP($B27,'CTC Breakup'!$B$2:$O$51,7,0)/31*$I27,0) -> 31250 | L27: =ROUND(VLOOKUP($B27,'CTC Breakup'!$B$2:$O$51,8,0)/31*$I27,0) -> 12500 | M27: =ROUND(VLOOKUP($B27,'CTC Breakup'!$B$2:$O$51,9,0)/31*$I27,0) -> 15000 | N27: =ROUND(VLOOKUP($B27,'CTC Breakup'!$B$2:$O$51,10,0)/31*$I27,0) -> 0 | O27: =ROUND(VLOOKUP($B27,'CTC Breakup'!$B$2:$O$51,11,0)/31*$I27,0) -> 0 | P27: =ROUND(((VLOOKUP($B27,'CTC Breakup'!$B$2:$N$51,13,0)-VLOOKUP($B27,'CTC Breakup'!$B$2:$N$51,12,0))/22/9)*$J27,0) -> 0 | Q27: 0 | R27: =SUM(K27:Q27) -> 58750 | S27: =ROUND(K27*12%,0) -> 3750 | T27: =ROUND(IF(R27>100000,R27*30%,IF(R27>75000,R27*20%,IF(R27>50000,R27*10%,0))),0) -> 5875 | U27: 0 | V27: =R27-S27-T27-U27 -> 49125
A28: 46023 | B28: ASG0033 | C28: 45614 | E28: Data Analyst | F28: Analytics | G28: =VLOOKUP(tblPayroll[[#This Row],[Employee Id]],Table1[[Employee Id]:[Work Location]],13,0) -> Bangalore | H28: 0 | I28: =31-H28 -> 31 | J28: 0 | K28: =ROUND(VLOOKUP($B28,'CTC Breakup'!$B$2:$O$51,7,0)/31*$I28,0) -> 52084 | L28: =ROUND(VLOOKUP($B28,'CTC Breakup'!$B$2:$O$51,8,0)/31*$I28,0) -> 20834 | M28: =ROUND(VLOOKUP($B28,'CTC Breakup'!$B$2:$O$51,9,0)/31*$I28,0) -> 21999 | N28: =ROUND(VLOOKUP($B28,'CTC Breakup'!$B$2:$O$51,10,0)/31*$I28,0) -> 2000 | O28: =ROUND(VLOOKUP($B28,'CTC Breakup'!$B$2:$O$51,11,0)/31*$I28,0) -> 1000 | P28: =ROUND(((VLOOKUP($B28,'CTC Breakup'!$B$2:$N$51,13,0)-VLOOKUP($B28,'CTC Breakup'!$B$2:$N$51,12,0))/22/9)*$J28,0) -> 0 | Q28: 0 | R28: =SUM(K28:Q28) -> 97917 | S28: =ROUND(K28*12%,0) -> 6250 | T28: =ROUND(IF(R28>100000,R28*30%,IF(R28>75000,R28*20%,IF(R28>50000,R28*5%,0))),0) -> 19583 | U28: 0 | V28: =R28-S28-T28-U28 -> 72084
A29: 46023 | B29: ASG0034 | C29: 45649 | D29: 46041 | E29: HR Executive | F29: HR | G29: =VLOOKUP(tblPayroll[[#This Row],[Employee Id]],Table1[[Employee Id]:[Work Location]],13,0) -> Chennai | H29: 0 | I29: 19 | J29: 17 | K29: =ROUND(VLOOKUP($B29,'CTC Breakup'!$B$2:$O$51,7,0)/31*$I29,0) -> 15961 | L29: =ROUND(VLOOKUP($B29,'CTC Breakup'!$B$2:$O$51,8,0)/31*$I29,0) -> 6385 | M29: =ROUND(VLOOKUP($B29,'CTC Breakup'!$B$2:$O$51,9,0)/31*$I29,0) -> 7661 | N29: =ROUND(VLOOKUP($B29,'CTC Breakup'!$B$2:$O$51,10,0)/31*$I29,0) -> 0 | O29: =ROUND(VLOOKUP($B29,'CTC Breakup'!$B$2:$O$51,11,0)/31*$I29,0) -> 0 | P29: =ROUND(((VLOOKUP($B29,'CTC Breakup'!$B$2:$N$51,13,0)-VLOOKUP($B29,'CTC Breakup'!$B$2:$N$51,12,0))/22/9)*$J29,0) -> 4203 | Q29: 0 | R29: =SUM(K29:Q29) -> 34210 | S29: =ROUND(K29*12%,0) -> 1915 | T29: =ROUND(IF(R29>100000,R29*30%,IF(R29>75000,R29*20%,IF(R29>50000,R29*5%,0))),0) -> 0 | U29: 0 | V29: =R29-S29-T29-U29 -> 32295
A30: 46023 | B30: ASG0035 | C30: 45663 | E30: HR Executive | F30: HR | G30: =VLOOKUP(tblPayroll[[#This Row],[Employee Id]],Table1[[Employee Id]:[Work Location]],13,0) -> Mumbai | H30: 0 | I30: =31-H30 -> 31 | J30: 25 | K30: =ROUND(VLOOKUP($B30,'CTC Breakup'!$B$2:$O$51,7,0)/31*$I30,0) -> 25000 | L30: =ROUND(VLOOKUP($B30,'CTC Breakup'!$B$2:$O$51,8,0)/31*$I30,0) -> 10000 | M30: =ROUND(VLOOKUP($B30,'CTC Breakup'!$B$2:$O$51,9,0)/31*$I30,0) -> 12000 | N30: =ROUND(VLOOKUP($B30,'CTC Breakup'!$B$2:$O$51,10,0)/31*$I30,0) -> 0 | O30: =ROUND(VLOOKUP($B30,'CTC Breakup'!$B$2:$O$51,11,0)/31*$I30,0) -> 0 | P30: =ROUND(((VLOOKUP($B30,'CTC Breakup'!$B$2:$N$51,13,0)-VLOOKUP($B30,'CTC Breakup'!$B$2:$N$51,12,0))/22/9)*$J30,0) -> 5934 | Q30: 0 | R30: =SUM(K30:Q30) -> 52934 | S30: =ROUND(K30*12%,0) -> 3000 | T30: =ROUND(IF(R30>100000,R30*30%,IF(R30>75000,R30*20%,IF(R30>50000,R30*10%,0))),0) -> 5293 | U30: 0 | V30: =R30-S30-T30-U30 -> 44641
A31: 46023 | B31: ASG0036 | C31: 45782 | E31: Payroll Executive | F31: Payroll | G31: =VLOOKUP(tblPayroll[[#This Row],[Employee Id]],Table1[[Employee Id]:[Work Location]],13,0) -> Chennai | H31: 0 | I31: =31-H31 -> 31 | J31: 23 | K31: =ROUND(VLOOKUP($B31,'CTC Breakup'!$B$2:$O$51,7,0)/31*$I31,0) -> 19792 | L31: =ROUND(VLOOKUP($B31,'CTC Breakup'!$B$2:$O$51,8,0)/31*$I31,0) -> 7917 | M31: =ROUND(VLOOKUP($B31,'CTC Breakup'!$B$2:$O$51,9,0)/31*$I31,0) -> 9499 | N31: =ROUND(VLOOKUP($B31,'CTC Breakup'!$B$2:$O$51,10,0)/31*$I31,0) -> 0 | O31: =ROUND(VLOOKUP($B31,'CTC Breakup'!$B$2:$O$51,11,0)/31*$I31,0) -> 0 | P31: =ROUND(((VLOOKUP($B31,'CTC Breakup'!$B$2:$N$51,13,0)-VLOOKUP($B31,'CTC Breakup'!$B$2:$N$51,12,0))/22/9)*$J31,0) -> 4322 | Q31: 0 | R31: =SUM(K31:Q31) -> 41530 | S31: =ROUND(K31*12%,0) -> 2375 | T31: =ROUND(IF(R31>100000,R31*30%,IF(R31>75000,R31*20%,IF(R31>50000,R31*5%,0))),0) -> 0 | U31: 0 | V31: =R31-S31-T31-U31 -> 39155
A32: 46023 | B32: ASG0038 | C32: 45852 | E32: Accounts Trainee | F32: Finance | G32: =VLOOKUP(tblPayroll[[#This Row],[Employee Id]],Table1[[Employee Id]:[Work Location]],13,0) -> Mumbai | H32: 0 | I32: =31-H32 -> 31 | J32: 25 | K32: =ROUND(VLOOKUP($B32,'CTC Breakup'!$B$2:$O$51,7,0)/31*$I32,0) -> 18750 | L32: =ROUND(VLOOKUP($B32,'CTC Breakup'!$B$2:$O$51,8,0)/31*$I32,0) -> 7500 | M32: =ROUND(VLOOKUP($B32,'CTC Breakup'!$B$2:$O$51,9,0)/31*$I32,0) -> 9000 | N32: =ROUND(VLOOKUP($B32,'CTC Breakup'!$B$2:$O$51,10,0)/31*$I32,0) -> 0 | O32: =ROUND(VLOOKUP($B32,'CTC Breakup'!$B$2:$O$51,11,0)/31*$I32,0) -> 0 | P32: =ROUND(((VLOOKUP($B32,'CTC Breakup'!$B$2:$N$51,13,0)-VLOOKUP($B32,'CTC Breakup'!$B$2:$N$51,12,0))/22/9)*$J32,0) -> 4451 | Q32: 0 | R32: =SUM(K32:Q32) -> 39701 | S32: =ROUND(K32*12%,0) -> 2250 | T32: =ROUND(IF(R32>100000,R32*30%,IF(R32>75000,R32*20%,IF(R32>50000,R32*5%,0))),0) -> 0 | U32: 0 | V32: =R32-S32-T32-U32 -> 37451
A33: 46023 | B33: ASG0039 | C33: 45901 | E33: BI Developer | F33: Analytics | G33: =VLOOKUP(tblPayroll[[#This Row],[Employee Id]],Table1[[Employee Id]:[Work Location]],13,0) -> Kolkata | H33: 0 | I33: =31-H33 -> 31 | J33: 20 | K33: =ROUND(VLOOKUP($B33,'CTC Breakup'!$B$2:$O$51,7,0)/31*$I33,0) -> 53125 | L33: =ROUND(VLOOKUP($B33,'CTC Breakup'!$B$2:$O$51,8,0)/31*$I33,0) -> 21250 | M33: =ROUND(VLOOKUP($B33,'CTC Breakup'!$B$2:$O$51,9,0)/31*$I33,0) -> 22500 | N33: =ROUND(VLOOKUP($B33,'CTC Breakup'!$B$2:$O$51,10,0)/31*$I33,0) -> 2000 | O33: =ROUND(VLOOKUP($B33,'CTC Breakup'!$B$2:$O$51,11,0)/31*$I33,0) -> 1000 | P33: =ROUND(((VLOOKUP($B33,'CTC Breakup'!$B$2:$N$51,13,0)-VLOOKUP($B33,'CTC Breakup'!$B$2:$N$51,12,0))/22/9)*$J33,0) -> 10088 | Q33: 0 | R33: =SUM(K33:Q33) -> 109963 | S33: =ROUND(K33*12%,0) -> 6375 | T33: =ROUND(IF(R33>100000,R33*30%,IF(R33>75000,R33*20%,IF(R33>50000,R33*5%,0))),0) -> 32989 | U33: 0 | V33: =R33-S33-T33-U33 -> 70599
A34: 46023 | B34: ASG0040 | C34: 45908 | D34: 46077 | E34: Payroll Executive | F34: Payroll | G34: =VLOOKUP(tblPayroll[[#This Row],[Employee Id]],Table1[[Employee Id]:[Work Location]],13,0) -> Mumbai | H34: 0 | I34: =31-H34 -> 31 | J34: 0 | K34: =ROUND(VLOOKUP($B34,'CTC Breakup'!$B$2:$O$51,7,0)/31*$I34,0) -> 19792 | L34: =ROUND(VLOOKUP($B34,'CTC Breakup'!$B$2:$O$51,8,0)/31*$I34,0) -> 7917 | M34: =ROUND(VLOOKUP($B34,'CTC Breakup'!$B$2:$O$51,9,0)/31*$I34,0) -> 9499 | N34: =ROUND(VLOOKUP($B34,'CTC Breakup'!$B$2:$O$51,10,0)/31*$I34,0) -> 0 | O34: =ROUND(VLOOKUP($B34,'CTC Breakup'!$B$2:$O$51,11,0)/31*$I34,0) -> 0 | P34: =ROUND(((VLOOKUP($B34,'CTC Breakup'!$B$2:$N$51,13,0)-VLOOKUP($B34,'CTC Breakup'!$B$2:$N$51,12,0))/22/9)*$J34,0) -> 0 | Q34: 0 | R34: =SUM(K34:Q34) -> 37208 | S34: =ROUND(K34*12%,0) -> 2375 | T34: =ROUND(IF(R34>100000,R34*30%,IF(R34>75000,R34*20%,IF(R34>50000,R34*5%,0))),0) -> 0 | U34: 0 | V34: =R34-S34-T34-U34 -> 34833
A35: 46023 | B35: ASG0041 | C35: 45978 | E35: Data Analyst | F35: Analytics | G35: =VLOOKUP(tblPayroll[[#This Row],[Employee Id]],Table1[[Employee Id]:[Work Location]],13,0) -> Chennai | H35: 0 | I35: =31-H35 -> 31 | J35: 18 | K35: =ROUND(VLOOKUP($B35,'CTC Breakup'!$B$2:$O$51,7,0)/31*$I35,0) -> 49167 | L35: =ROUND(VLOOKUP($B35,'CTC Breakup'!$B$2:$O$51,8,0)/31*$I35,0) -> 19667 | M35: =ROUND(VLOOKUP($B35,'CTC Breakup'!$B$2:$O$51,9,0)/31*$I35,0) -> 20599 | N35: =ROUND(VLOOKUP($B35,'CTC Breakup'!$B$2:$O$51,10,0)/31*$I35,0) -> 2000 | O35: =ROUND(VLOOKUP($B35,'CTC Breakup'!$B$2:$O$51,11,0)/31*$I35,0) -> 1000 | P35: =ROUND(((VLOOKUP($B35,'CTC Breakup'!$B$2:$N$51,13,0)-VLOOKUP($B35,'CTC Breakup'!$B$2:$N$51,12,0))/22/9)*$J35,0) -> 8403 | Q35: 0 | R35: =SUM(K35:Q35) -> 100836 | S35: =ROUND(K35*12%,0) -> 5900 | T35: =ROUND(IF(R35>100000,R35*30%,IF(R35>75000,R35*20%,IF(R35>50000,R35*5%,0))),0) -> 30251 | U35: 0 | V35: =R35-S35-T35-U35 -> 64685
A36: 46023 | B36: ASG0042 | C36: 45992 | E36: Sales Trainee | F36: Sales | G36: =VLOOKUP(tblPayroll[[#This Row],[Employee Id]],Table1[[Employee Id]:[Work Location]],13,0) -> Chennai | H36: 0 | I36: =31-H36 -> 31 | J36: 0 | K36: =ROUND(VLOOKUP($B36,'CTC Breakup'!$B$2:$O$51,7,0)/31*$I36,0) -> 18750 | L36: =ROUND(VLOOKUP($B36,'CTC Breakup'!$B$2:$O$51,8,0)/31*$I36,0) -> 7500 | M36: =ROUND(VLOOKUP($B36,'CTC Breakup'!$B$2:$O$51,9,0)/31*$I36,0) -> 9000 | N36: =ROUND(VLOOKUP($B36,'CTC Breakup'!$B$2:$O$51,10,0)/31*$I36,0) -> 0 | O36: =ROUND(VLOOKUP($B36,'CTC Breakup'!$B$2:$O$51,11,0)/31*$I36,0) -> 0 | P36: =ROUND(((VLOOKUP($B36,'CTC Breakup'!$B$2:$N$51,13,0)-VLOOKUP($B36,'CTC Breakup'!$B$2:$N$51,12,0))/22/9)*$J36,0) -> 0 | Q36: 8360 | R36: =SUM(K36:Q36) -> 43610 | S36: =ROUND(K36*12%,0) -> 2250 | T36: =ROUND(IF(R36>100000,R36*30%,IF(R36>75000,R36*20%,IF(R36>50000,R36*5%,0))),0) -> 0 | U36: 0 | V36: =R36-S36-T36-U36 -> 41360
A37: 46023 | B37: ASG0043 | C37: 46027 | E37: HR Executive | F37: HR | G37: =VLOOKUP(tblPayroll[[#This Row],[Employee Id]],Table1[[Employee Id]:[Work Location]],13,0) -> Bangalore | H37: 0 | I37: =31-H37 -> 31 | J37: 0 | K37: =ROUND(VLOOKUP($B37,'CTC Breakup'!$B$2:$O$51,7,0)/31*$I37,0) -> 23959 | L37: =ROUND(VLOOKUP($B37,'CTC Breakup'!$B$2:$O$51,8,0)/31*$I37,0) -> 9584 | M37: =ROUND(VLOOKUP($B37,'CTC Breakup'!$B$2:$O$51,9,0)/31*$I37,0) -> 11499 | N37: =ROUND(VLOOKUP($B37,'CTC Breakup'!$B$2:$O$51,10,0)/31*$I37,0) -> 0 | O37: =ROUND(VLOOKUP($B37,'CTC Breakup'!$B$2:$O$51,11,0)/31*$I37,0) -> 0 | P37: =ROUND(((VLOOKUP($B37,'CTC Breakup'!$B$2:$N$51,13,0)-VLOOKUP($B37,'CTC Breakup'!$B$2:$N$51,12,0))/22/9)*$J37,0) -> 0 | Q37: 0 | R37: =SUM(K37:Q37) -> 45042 | S37: =ROUND(K37*12%,0) -> 2875 | T37: =ROUND(IF(R37>100000,R37*30%,IF(R37>75000,R37*20%,IF(R37>50000,R37*5%,0))),0) -> 0 | U37: 0 | V37: =R37-S37-T37-U37 -> 42167
A38: 46023 | B38: ASG0044 | C38: 46041 | E38: Data Analyst | F38: Analytics | G38: =VLOOKUP(tblPayroll[[#This Row],[Employee Id]],Table1[[Employee Id]:[Work Location]],13,0) -> Kolkata | H38: 6 | I38: =31-H38 -> 25 | J38: 0 | K38: =ROUND(VLOOKUP($B38,'CTC Breakup'!$B$2:$O$51,7,0)/31*$I38,0) -> 38643 | L38: =ROUND(VLOOKUP($B38,'CTC Breakup'!$B$2:$O$51,8,0)/31*$I38,0) -> 15457 | M38: =ROUND(VLOOKUP($B38,'CTC Breakup'!$B$2:$O$51,9,0)/31*$I38,0) -> 16128 | N38: =ROUND(VLOOKUP($B38,'CTC Breakup'!$B$2:$O$51,10,0)/31*$I38,0) -> 1613 | O38: =ROUND(VLOOKUP($B38,'CTC Breakup'!$B$2:$O$51,11,0)/31*$I38,0) -> 806 | P38: =ROUND(((VLOOKUP($B38,'CTC Breakup'!$B$2:$N$51,13,0)-VLOOKUP($B38,'CTC Breakup'!$B$2:$N$51,12,0))/22/9)*$J38,0) -> 0 | Q38: 0 | R38: =SUM(K38:Q38) -> 72647 | S38: =ROUND(K38*12%,0) -> 4637 | T38: =ROUND(IF(R38>100000,R38*30%,IF(R38>75000,R38*20%,IF(R38>50000,R38*10%,0))),0) -> 7265 | U38: 11500 | V38: =R38-S38-T38-U38 -> 49245
A39: 46054 | B39: ASG0001 | C39: 44593 | E39: HR Manager | F39: HR | G39: =VLOOKUP(tblPayroll[[#This Row],[Employee Id]],Table1[[Employee Id]:[Work Location]],13,0) -> Bangalore | H39: 0 | I39: =28-H39 -> 28 | J39: 21 | K39: =ROUND(VLOOKUP($B39,'CTC Breakup'!$B$2:$O$51,7,0)/28*$I39,0) -> 77084 | L39: =ROUND(VLOOKUP($B39,'CTC Breakup'!$B$2:$O$51,8,0)/28*$I39,0) -> 30834 | M39: =ROUND(VLOOKUP($B39,'CTC Breakup'!$B$2:$O$51,9,0)/28*$I39,0) -> 33999 | N39: =ROUND(VLOOKUP($B39,'CTC Breakup'!$B$2:$O$51,10,0)/28*$I39,0) -> 2000 | O39: =ROUND(VLOOKUP($B39,'CTC Breakup'!$B$2:$O$51,11,0)/28*$I39,0) -> 1000 | P39: =ROUND(((VLOOKUP($B39,'CTC Breakup'!$B$2:$N$51,13,0)-VLOOKUP($B39,'CTC Breakup'!$B$2:$N$51,12,0))/22/9)*$J39,0) -> 15370 | Q39: 0 | R39: =SUM(K39:Q39) -> 160287 | S39: =ROUND(K39*12%,0) -> 9250 | T39: =ROUND(IF(R39>100000,R39*30%,IF(R39>75000,R39*20%,IF(R39>50000,R39*10%,0))),0) -> 48086 | U39: 11500 | V39: =R39-S39-T39-U39 -> 91451
A40: 46054 | B40: ASG0002 | C40: 44613 | E40: Analytics Manager | F40: Analytics | G40: =VLOOKUP(tblPayroll[[#This Row],[Employee Id]],Table1[[Employee Id]:[Work Location]],13,0) -> Chennai | H40: 0 | I40: =28-H40 -> 28 | J40: 0 | K40: =ROUND(VLOOKUP($B40,'CTC Breakup'!$B$2:$O$51,7,0)/28*$I40,0) -> 104167 | L40: =ROUND(VLOOKUP($B40,'CTC Breakup'!$B$2:$O$51,8,0)/28*$I40,0) -> 41667 | M40: =ROUND(VLOOKUP($B40,'CTC Breakup'!$B$2:$O$51,9,0)/28*$I40,0) -> 49999 | N40: =ROUND(VLOOKUP($B40,'CTC Breakup'!$B$2:$O$51,10,0)/28*$I40,0) -> 0 | O40: =ROUND(VLOOKUP($B40,'CTC Breakup'!$B$2:$O$51,11,0)/28*$I40,0) -> 0 | P40: =ROUND(((VLOOKUP($B40,'CTC Breakup'!$B$2:$N$51,13,0)-VLOOKUP($B40,'CTC Breakup'!$B$2:$N$51,12,0))/22/9)*$J40,0) -> 0 | Q40: 0 | R40: =SUM(K40:Q40) -> 195833 | S40: =ROUND(K40*12%,0) -> 12500 | T40: =ROUND(IF(R40>100000,R40*30%,IF(R40>75000,R40*20%,IF(R40>50000,R40*10%,0))),0) -> 58750 | U40: 0 | V40: =R40-S40-T40-U40 -> 124583
A41: 46054 | B41: ASG0003 | C41: 44634 | E41: HR Manager | F41: HR | G41: =VLOOKUP(tblPayroll[[#This Row],[Employee Id]],Table1[[Employee Id]:[Work Location]],13,0) -> Bangalore | H41: 7 | I41: =28-H41 -> 21 | J41: 0 | K41: =ROUND(VLOOKUP($B41,'CTC Breakup'!$B$2:$O$51,7,0)/28*$I41,0) -> 54688 | L41: =ROUND(VLOOKUP($B41,'CTC Breakup'!$B$2:$O$51,8,0)/28*$I41,0) -> 21875 | M41: =ROUND(VLOOKUP($B41,'CTC Breakup'!$B$2:$O$51,9,0)/28*$I41,0) -> 23999 | N41: =ROUND(VLOOKUP($B41,'CTC Breakup'!$B$2:$O$51,10,0)/28*$I41,0) -> 1500 | O41: =ROUND(VLOOKUP($B41,'CTC Breakup'!$B$2:$O$51,11,0)/28*$I41,0) -> 750 | P41: =ROUND(((VLOOKUP($B41,'CTC Breakup'!$B$2:$N$51,13,0)-VLOOKUP($B41,'CTC Breakup'!$B$2:$N$51,12,0))/22/9)*$J41,0) -> 0 | Q41: =ROUND((VLOOKUP($B41,'CTC Breakup'!$B$2:$N$51,13,0)-VLOOKUP($B41,'CTC Breakup'!$B$2:$N$51,12,0))/(22*9)*$J41*2,0) -> 0 | R41: =SUM(K41:Q41) -> 102812 | S41: =ROUND(K41*12%,0) -> 6563 | T41: =ROUND(IF(R41>100000,R41*30%,IF(R41>75000,R41*20%,IF(R41>50000,R41*10%,0))),0) -> 30844 | U41: 0 | V41: =R41-S41-T41-U41 -> 65405
A42: 46054 | B42: ASG0005 | C42: 44697 | E42: Payroll Manager | F42: Payroll | G42: =VLOOKUP(tblPayroll[[#This Row],[Employee Id]],Table1[[Employee Id]:[Work Location]],13,0) -> Chennai | H42: 11 | I42: =28-H42 -> 17 | J42: 0 | K42: =ROUND(VLOOKUP($B42,'CTC Breakup'!$B$2:$O$51,7,0)/28*$I42,0) -> 43006 | L42: =ROUND(VLOOKUP($B42,'CTC Breakup'!$B$2:$O$51,8,0)/28*$I42,0) -> 17203 | M42: =ROUND(VLOOKUP($B42,'CTC Breakup'!$B$2:$O$51,9,0)/28*$I42,0) -> 18821 | N42: =ROUND(VLOOKUP($B42,'CTC Breakup'!$B$2:$O$51,10,0)/28*$I42,0) -> 1214 | O42: =ROUND(VLOOKUP($B42,'CTC Breakup'!$B$2:$O$51,11,0)/28*$I42,0) -> 607 | P42: =ROUND(((VLOOKUP($B42,'CTC Breakup'!$B$2:$N$51,13,0)-VLOOKUP($B42,'CTC Breakup'!$B$2:$N$51,12,0))/22/9)*$J42,0) -> 0 | Q42: 0 | R42: =SUM(K42:Q42) -> 80851 | S42: =ROUND(K42*12%,0) -> 5161 | T42: =ROUND(IF(R42>100000,R42*30%,IF(R42>75000,R42*20%,IF(R42>50000,R42*10%,0))),0) -> 16170 | U42: 0 | V42: =R42-S42-T42-U42 -> 59520
A43: 46054 | B43: ASG0006 | C43: 44704 | E43: Senior Payroll Analyst | F43: Payroll | G43: =VLOOKUP(tblPayroll[[#This Row],[Employee Id]],Table1[[Employee Id]:[Work Location]],13,0) -> Mumbai | H43: 0 | I43: =28-H43 -> 28 | J43: 25 | K43: =ROUND(VLOOKUP($B43,'CTC Breakup'!$B$2:$O$51,7,0)/28*$I43,0) -> 41667 | L43: =ROUND(VLOOKUP($B43,'CTC Breakup'!$B$2:$O$51,8,0)/28*$I43,0) -> 16667 | M43: =ROUND(VLOOKUP($B43,'CTC Breakup'!$B$2:$O$51,9,0)/28*$I43,0) -> 16999 | N43: =ROUND(VLOOKUP($B43,'CTC Breakup'!$B$2:$O$51,10,0)/28*$I43,0) -> 2000 | O43: =ROUND(VLOOKUP($B43,'CTC Breakup'!$B$2:$O$51,11,0)/28*$I43,0) -> 1000 | P43: =ROUND(((VLOOKUP($B43,'CTC Breakup'!$B$2:$N$51,13,0)-VLOOKUP($B43,'CTC Breakup'!$B$2:$N$51,12,0))/22/9)*$J43,0) -> 9891 | Q43: 0 | R43: =SUM(K43:Q43) -> 88224 | S43: =ROUND(K43*12%,0) -> 5000 | T43: =ROUND(IF(R43>100000,R43*30%,IF(R43>75000,R43*20%,IF(R43>50000,R43*10%,0))),0) -> 17645 | U43: 10800 | V43: =R43-S43-T43-U43 -> 54779
A44: 46054 | B44: ASG0008 | C44: 44886 | E44: Sales Manager | F44: Sales | G44: =VLOOKUP(tblPayroll[[#This Row],[Employee Id]],Table1[[Employee Id]:[Work Location]],13,0) -> Kolkata | H44: 0 | I44: =28-H44 -> 28 | J44: 0 | K44: =ROUND(VLOOKUP($B44,'CTC Breakup'!$B$2:$O$51,7,0)/28*$I44,0) -> 87500 | L44: =ROUND(VLOOKUP($B44,'CTC Breakup'!$B$2:$O$51,8,0)/28*$I44,0) -> 35000 | M44: =ROUND(VLOOKUP($B44,'CTC Breakup'!$B$2:$O$51,9,0)/28*$I44,0) -> 39000 | N44: =ROUND(VLOOKUP($B44,'CTC Breakup'!$B$2:$O$51,10,0)/28*$I44,0) -> 2000 | O44: =ROUND(VLOOKUP($B44,'CTC Breakup'!$B$2:$O$51,11,0)/28*$I44,0) -> 1000 | P44: =ROUND(((VLOOKUP($B44,'CTC Breakup'!$B$2:$N$51,13,0)-VLOOKUP($B44,'CTC Breakup'!$B$2:$N$51,12,0))/22/9)*$J44,0) -> 0 | Q44: 27800 | R44: =SUM(K44:Q44) -> 192300 | S44: =ROUND(K44*12%,0) -> 10500 | T44: =ROUND(IF(R44>100000,R44*30%,IF(R44>75000,R44*20%,IF(R44>50000,R44*10%,0))),0) -> 57690 | U44: 0 | V44: =R44-S44-T44-U44 -> 124110
A45: 46054 | B45: ASG0009 | C45: 44893 | E45: Regional Sales Lead | F45: Sales | G45: =VLOOKUP(tblPayroll[[#This Row],[Employee Id]],Table1[[Employee Id]:[Work Location]],13,0) -> Hyderabad | H45: 0 | I45: =28-H45 -> 28 | J45: 0 | K45: =ROUND(VLOOKUP($B45,'CTC Breakup'!$B$2:$O$51,7,0)/28*$I45,0) -> 75000 | L45: =ROUND(VLOOKUP($B45,'CTC Breakup'!$B$2:$O$51,8,0)/28*$I45,0) -> 30000 | M45: =ROUND(VLOOKUP($B45,'CTC Breakup'!$B$2:$O$51,9,0)/28*$I45,0) -> 33000 | N45: =ROUND(VLOOKUP($B45,'CTC Breakup'!$B$2:$O$51,10,0)/28*$I45,0) -> 2000 | O45: =ROUND(VLOOKUP($B45,'CTC Breakup'!$B$2:$O$51,11,0)/28*$I45,0) -> 1000 | P45: =ROUND(((VLOOKUP($B45,'CTC Breakup'!$B$2:$N$51,13,0)-VLOOKUP($B45,'CTC Breakup'!$B$2:$N$51,12,0))/22/9)*$J45,0) -> 0 | Q45: 22880 | R45: =SUM(K45:Q45) -> 163880 | S45: =ROUND(K45*12%,0) -> 9000 | T45: =ROUND(IF(R45>100000,R45*30%,IF(R45>75000,R45*20%,IF(R45>50000,R45*10%,0))),0) -> 49164 | U45: 0 | V45: =R45-S45-T45-U45 -> 105716
A46: 46054 | B46: ASG0010 | C46: 44907 | E46: Finance Manager | F46: Finance | G46: =VLOOKUP(tblPayroll[[#This Row],[Employee Id]],Table1[[Employee Id]:[Work Location]],13,0) -> Mumbai | H46: 0 | I46: =28-H46 -> 28 | J46: 0 | K46: =ROUND(VLOOKUP($B46,'CTC Breakup'!$B$2:$O$51,7,0)/28*$I46,0) -> 72917 | L46: =ROUND(VLOOKUP($B46,'CTC Breakup'!$B$2:$O$51,8,0)/28*$I46,0) -> 29167 | M46: =ROUND(VLOOKUP($B46,'CTC Breakup'!$B$2:$O$51,9,0)/28*$I46,0) -> 31999 | N46: =ROUND(VLOOKUP($B46,'CTC Breakup'!$B$2:$O$51,10,0)/28*$I46,0) -> 2000 | O46: =ROUND(VLOOKUP($B46,'CTC Breakup'!$B$2:$O$51,11,0)/28*$I46,0) -> 1000 | P46: =ROUND(((VLOOKUP($B46,'CTC Breakup'!$B$2:$N$51,13,0)-VLOOKUP($B46,'CTC Breakup'!$B$2:$N$51,12,0))/22/9)*$J46,0) -> 0 | Q46: 0 | R46: =SUM(K46:Q46) -> 137083 | S46: =ROUND(K46*12%,0) -> 8750 | T46: =ROUND(IF(R46>100000,R46*30%,IF(R46>75000,R46*20%,IF(R46>50000,R46*10%,0))),0) -> 41125 | U46: 0 | V46: =R46-S46-T46-U46 -> 87208
A47: 46054 | B47: ASG0012 | C47: 44956 | E47: Senior Sales Executive | F47: Sales | G47: =VLOOKUP(tblPayroll[[#This Row],[Employee Id]],Table1[[Employee Id]:[Work Location]],13,0) -> Chennai | H47: 5 | I47: =28-H47 -> 23 | J47: 20 | K47: =ROUND(VLOOKUP($B47,'CTC Breakup'!$B$2:$O$51,7,0)/28*$I47,0) -> 39360 | L47: =ROUND(VLOOKUP($B47,'CTC Breakup'!$B$2:$O$51,8,0)/28*$I47,0) -> 15744 | M47: =ROUND(VLOOKUP($B47,'CTC Breakup'!$B$2:$O$51,9,0)/28*$I47,0) -> 16428 | N47: =ROUND(VLOOKUP($B47,'CTC Breakup'!$B$2:$O$51,10,0)/28*$I47,0) -> 1643 | O47: =ROUND(VLOOKUP($B47,'CTC Breakup'!$B$2:$O$51,11,0)/28*$I47,0) -> 821 | P47: =ROUND(((VLOOKUP($B47,'CTC Breakup'!$B$2:$N$51,13,0)-VLOOKUP($B47,'CTC Breakup'!$B$2:$N$51,12,0))/22/9)*$J47,0) -> 9099 | Q47: 18260 | R47: =SUM(K47:Q47) -> 101355 | S47: =ROUND(K47*12%,0) -> 4723 | T47: =ROUND(IF(R47>100000,R47*30%,IF(R47>75000,R47*20%,IF(R47>50000,R47*10%,0))),0) -> 30407 | U47: 0 | V47: =R47-S47-T47-U47 -> 66225
A48: 46054 | B48: ASG0013 | C48: 44963 | E48: Senior Data Analyst | F48: Analytics | G48: =VLOOKUP(tblPayroll[[#This Row],[Employee Id]],Table1[[Employee Id]:[Work Location]],13,0) -> Bangalore | H48: 0 | I48: =28-H48 -> 28 | J48: 0 | K48: =ROUND(VLOOKUP($B48,'CTC Breakup'!$B$2:$O$51,7,0)/28*$I48,0) -> 64584 | L48: =ROUND(VLOOKUP($B48,'CTC Breakup'!$B$2:$O$51,8,0)/28*$I48,0) -> 25834 | M48: =ROUND(VLOOKUP($B48,'CTC Breakup'!$B$2:$O$51,9,0)/28*$I48,0) -> 27999 | N48: =ROUND(VLOOKUP($B48,'CTC Breakup'!$B$2:$O$51,10,0)/28*$I48,0) -> 2000 | O48: =ROUND(VLOOKUP($B48,'CTC Breakup'!$B$2:$O$51,11,0)/28*$I48,0) -> 1000 | P48: =ROUND(((VLOOKUP($B48,'CTC Breakup'!$B$2:$N$51,13,0)-VLOOKUP($B48,'CTC Breakup'!$B$2:$N$51,12,0))/22/9)*$J48,0) -> 0 | Q48: 0 | R48: =SUM(K48:Q48) -> 121417 | S48: =ROUND(K48*12%,0) -> 7750 | T48: =ROUND(IF(R48>100000,R48*30%,IF(R48>75000,R48*20%,IF(R48>50000,R48*10%,0))),0) -> 36425 | U48: 0 | V48: =R48-S48-T48-U48 -> 77242
A49: 46054 | B49: ASG0015 | C49: 45033 | E49: Senior Data Analyst | F49: Analytics | G49: =VLOOKUP(tblPayroll[[#This Row],[Employee Id]],Table1[[Employee Id]:[Work Location]],13,0) -> Hyderabad | H49: 0 | I49: =28-H49 -> 28 | J49: 0 | K49: =ROUND(VLOOKUP($B49,'CTC Breakup'!$B$2:$O$51,7,0)/28*$I49,0) -> 61459 | L49: =ROUND(VLOOKUP($B49,'CTC Breakup'!$B$2:$O$51,8,0)/28*$I49,0) -> 24584 | M49: =ROUND(VLOOKUP($B49,'CTC Breakup'!$B$2:$O$51,9,0)/28*$I49,0) -> 26499 | N49: =ROUND(VLOOKUP($B49,'CTC Breakup'!$B$2:$O$51,10,0)/28*$I49,0) -> 2000 | O49: =ROUND(VLOOKUP($B49,'CTC Breakup'!$B$2:$O$51,11,0)/28*$I49,0) -> 1000 | P49: =ROUND(((VLOOKUP($B49,'CTC Breakup'!$B$2:$N$51,13,0)-VLOOKUP($B49,'CTC Breakup'!$B$2:$N$51,12,0))/22/9)*$J49,0) -> 0 | Q49: 0 | R49: =SUM(K49:Q49) -> 115542 | S49: =ROUND(K49*12%,0) -> 7375 | T49: =ROUND(IF(R49>100000,R49*30%,IF(R49>75000,R49*20%,IF(R49>50000,R49*10%,0))),0) -> 34663 | U49: 0 | V49: =R49-S49-T49-U49 -> 73504
A50: 46054 | B50: ASG0016 | C50: 45040 | E50: Senior Data Analyst | F50: Analytics | G50: =VLOOKUP(tblPayroll[[#This Row],[Employee Id]],Table1[[Employee Id]:[Work Location]],13,0) -> Bangalore | H50: 0 | I50: =28-H50 -> 28 | J50: 0 | K50: =ROUND(VLOOKUP($B50,'CTC Breakup'!$B$2:$O$51,7,0)/28*$I50,0) -> 78125 | L50: =ROUND(VLOOKUP($B50,'CTC Breakup'!$B$2:$O$51,8,0)/28*$I50,0) -> 31250 | M50: =ROUND(VLOOKUP($B50,'CTC Breakup'!$B$2:$O$51,9,0)/28*$I50,0) -> 34500 | N50: =ROUND(VLOOKUP($B50,'CTC Breakup'!$B$2:$O$51,10,0)/28*$I50,0) -> 2000 | O50: =ROUND(VLOOKUP($B50,'CTC Breakup'!$B$2:$O$51,11,0)/28*$I50,0) -> 1000 | P50: =ROUND(((VLOOKUP($B50,'CTC Breakup'!$B$2:$N$51,13,0)-VLOOKUP($B50,'CTC Breakup'!$B$2:$N$51,12,0))/22/9)*$J50,0) -> 0 | Q50: 0 | R50: =SUM(K50:Q50) -> 146875 | S50: =ROUND(K50*12%,0) -> 9375 | T50: =ROUND(IF(R50>100000,R50*30%,IF(R50>75000,R50*20%,IF(R50>50000,R50*10%,0))),0) -> 44063 | U50: 0 | V50: =R50-S50-T50-U50 -> 93437
A51: 46054 | B51: ASG0017 | C51: 45048 | D51: 46055 | E51: Sr Accountant | F51: Finance | G51: =VLOOKUP(tblPayroll[[#This Row],[Employee Id]],Table1[[Employee Id]:[Work Location]],13,0) -> Chennai | H51: 0 | I51: 2 | J51: 24 | K51: =ROUND(VLOOKUP($B51,'CTC Breakup'!$B$2:$O$51,7,0)/28*$I51,0) -> 3423 | L51: =ROUND(VLOOKUP($B51,'CTC Breakup'!$B$2:$O$51,8,0)/28*$I51,0) -> 1369 | M51: =ROUND(VLOOKUP($B51,'CTC Breakup'!$B$2:$O$51,9,0)/28*$I51,0) -> 1429 | N51: =ROUND(VLOOKUP($B51,'CTC Breakup'!$B$2:$O$51,10,0)/28*$I51,0) -> 143 | O51: =ROUND(VLOOKUP($B51,'CTC Breakup'!$B$2:$O$51,11,0)/28*$I51,0) -> 71 | P51: =ROUND(((VLOOKUP($B51,'CTC Breakup'!$B$2:$N$51,13,0)-VLOOKUP($B51,'CTC Breakup'!$B$2:$N$51,12,0))/22/9)*$J51,0) -> 10919 | Q51: 0 | R51: =SUM(K51:Q51) -> 17354 | S51: =ROUND(K51*12%,0) -> 411 | T51: =ROUND(IF(R51>100000,R51*30%,IF(R51>75000,R51*20%,IF(R51>50000,R51*10%,0))),0) -> 0 | U51: 14800 | V51: =R51-S51-T51-U51 -> 2143
A52: 46054 | B52: ASG0018 | C52: 45075 | E52: Sr Accountant | F52: Finance | G52: =VLOOKUP(tblPayroll[[#This Row],[Employee Id]],Table1[[Employee Id]:[Work Location]],13,0) -> Bangalore | H52: 11 | I52: =28-H52 -> 17 | J52: 16 | K52: =ROUND(VLOOKUP($B52,'CTC Breakup'!$B$2:$O$51,7,0)/28*$I52,0) -> 28460 | L52: =ROUND(VLOOKUP($B52,'CTC Breakup'!$B$2:$O$51,8,0)/28*$I52,0) -> 11384 | M52: =ROUND(VLOOKUP($B52,'CTC Breakup'!$B$2:$O$51,9,0)/28*$I52,0) -> 11839 | N52: =ROUND(VLOOKUP($B52,'CTC Breakup'!$B$2:$O$51,10,0)/28*$I52,0) -> 1214 | O52: =ROUND(VLOOKUP($B52,'CTC Breakup'!$B$2:$O$51,11,0)/28*$I52,0) -> 607 | P52: =ROUND(((VLOOKUP($B52,'CTC Breakup'!$B$2:$N$51,13,0)-VLOOKUP($B52,'CTC Breakup'!$B$2:$N$51,12,0))/22/9)*$J52,0) -> 7121 | Q52: 0 | R52: =SUM(K52:Q52) -> 60625 | S52: =ROUND(K52*12%,0) -> 3415 | T52: =ROUND(IF(R52>100000,R52*30%,IF(R52>75000,R52*20%,IF(R52>50000,R52*10%,0))),0) -> 6063 | U52: 0 | V52: =R52-S52-T52-U52 -> 51147
A53: 46054 | B53: ASG0019 | C53: 45170 | E53: Senior Sales Executive | F53: Sales | G53: =VLOOKUP(tblPayroll[[#This Row],[Employee Id]],Table1[[Employee Id]:[Work Location]],13,0) -> Mumbai | H53: 10 | I53: =28-H53 -> 18 | J53: 0 | K53: =ROUND(VLOOKUP($B53,'CTC Breakup'!$B$2:$O$51,7,0)/28*$I53,0) -> 29465 | L53: =ROUND(VLOOKUP($B53,'CTC Breakup'!$B$2:$O$51,8,0)/28*$I53,0) -> 11786 | M53: =ROUND(VLOOKUP($B53,'CTC Breakup'!$B$2:$O$51,9,0)/28*$I53,0) -> 12214 | N53: =ROUND(VLOOKUP($B53,'CTC Breakup'!$B$2:$O$51,10,0)/28*$I53,0) -> 1286 | O53: =ROUND(VLOOKUP($B53,'CTC Breakup'!$B$2:$O$51,11,0)/28*$I53,0) -> 643 | P53: =ROUND(((VLOOKUP($B53,'CTC Breakup'!$B$2:$N$51,13,0)-VLOOKUP($B53,'CTC Breakup'!$B$2:$N$51,12,0))/22/9)*$J53,0) -> 0 | Q53: 18390 | R53: =SUM(K53:Q53) -> 73784 | S53: =ROUND(K53*12%,0) -> 3536 | T53: =ROUND(IF(R53>100000,R53*30%,IF(R53>75000,R53*20%,IF(R53>50000,R53*10%,0))),0) -> 7378 | U53: 10500 | V53: =R53-S53-T53-U53 -> 52370
A54: 46054 | B54: ASG0020 | C54: 45173 | E54: Sales Executive | F54: Sales | G54: =VLOOKUP(tblPayroll[[#This Row],[Employee Id]],Table1[[Employee Id]:[Work Location]],13,0) -> Kolkata | H54: 11 | I54: =28-H54 -> 17 | J54: 17 | K54: =ROUND(VLOOKUP($B54,'CTC Breakup'!$B$2:$O$51,7,0)/28*$I54,0) -> 19732 | L54: =ROUND(VLOOKUP($B54,'CTC Breakup'!$B$2:$O$51,8,0)/28*$I54,0) -> 7893 | M54: =ROUND(VLOOKUP($B54,'CTC Breakup'!$B$2:$O$51,9,0)/28*$I54,0) -> 9471 | N54: =ROUND(VLOOKUP($B54,'CTC Breakup'!$B$2:$O$51,10,0)/28*$I54,0) -> 0 | O54: =ROUND(VLOOKUP($B54,'CTC Breakup'!$B$2:$O$51,11,0)/28*$I54,0) -> 0 | P54: =ROUND(((VLOOKUP($B54,'CTC Breakup'!$B$2:$N$51,13,0)-VLOOKUP($B54,'CTC Breakup'!$B$2:$N$51,12,0))/22/9)*$J54,0) -> 5246 | Q54: 11350 | R54: =SUM(K54:Q54) -> 53692 | S54: =ROUND(K54*12%,0) -> 2368 | T54: =ROUND(IF(R54>100000,R54*30%,IF(R54>75000,R54*20%,IF(R54>50000,R54*10%,0))),0) -> 5369 | U54: 0 | V54: =R54-S54-T54-U54 -> 45955
A55: 46054 | B55: ASG0022 | C55: 45236 | E55: Payroll Analyst | F55: Payroll | G55: =VLOOKUP(tblPayroll[[#This Row],[Employee Id]],Table1[[Employee Id]:[Work Location]],13,0) -> Mumbai | H55: 0 | I55: =28-H55 -> 28 | J55: 0 | K55: =ROUND(VLOOKUP($B55,'CTC Breakup'!$B$2:$O$51,7,0)/28*$I55,0) -> 28334 | L55: =ROUND(VLOOKUP($B55,'CTC Breakup'!$B$2:$O$51,8,0)/28*$I55,0) -> 11334 | M55: =ROUND(VLOOKUP($B55,'CTC Breakup'!$B$2:$O$51,9,0)/28*$I55,0) -> 13599 | N55: =ROUND(VLOOKUP($B55,'CTC Breakup'!$B$2:$O$51,10,0)/28*$I55,0) -> 0 | O55: =ROUND(VLOOKUP($B55,'CTC Breakup'!$B$2:$O$51,11,0)/28*$I55,0) -> 0 | P55: =ROUND(((VLOOKUP($B55,'CTC Breakup'!$B$2:$N$51,13,0)-VLOOKUP($B55,'CTC Breakup'!$B$2:$N$51,12,0))/22/9)*$J55,0) -> 0 | Q55: 0 | R55: =SUM(K55:Q55) -> 53267 | S55: =ROUND(K55*12%,0) -> 3400 | T55: =ROUND(IF(R55>100000,R55*30%,IF(R55>75000,R55*20%,IF(R55>50000,R55*10%,0))),0) -> 5327 | U55: 0 | V55: =R55-S55-T55-U55 -> 44540
A56: 46054 | B56: ASG0023 | C56: 45320 | E56: HR Analyst | F56: HR | G56: =VLOOKUP(tblPayroll[[#This Row],[Employee Id]],Table1[[Employee Id]:[Work Location]],13,0) -> Hyderabad | H56: 0 | I56: =28-H56 -> 28 | J56: 0 | K56: =ROUND(VLOOKUP($B56,'CTC Breakup'!$B$2:$O$51,7,0)/28*$I56,0) -> 50000 | L56: =ROUND(VLOOKUP($B56,'CTC Breakup'!$B$2:$O$51,8,0)/28*$I56,0) -> 20000 | M56: =ROUND(VLOOKUP($B56,'CTC Breakup'!$B$2:$O$51,9,0)/28*$I56,0) -> 21000 | N56: =ROUND(VLOOKUP($B56,'CTC Breakup'!$B$2:$O$51,10,0)/28*$I56,0) -> 2000 | O56: =ROUND(VLOOKUP($B56,'CTC Breakup'!$B$2:$O$51,11,0)/28*$I56,0) -> 1000 | P56: =ROUND(((VLOOKUP($B56,'CTC Breakup'!$B$2:$N$51,13,0)-VLOOKUP($B56,'CTC Breakup'!$B$2:$N$51,12,0))/22/9)*$J56,0) -> 0 | Q56: 0 | R56: =SUM(K56:Q56) -> 94000 | S56: =ROUND(K56*12%,0) -> 6000 | T56: =ROUND(IF(R56>100000,R56*30%,IF(R56>75000,R56*20%,IF(R56>50000,R56*10%,0))),0) -> 18800 | U56: 0 | V56: =R56-S56-T56-U56 -> 69200
A57: 46054 | B57: ASG0024 | C57: 45327 | D57: 46084 | E57: Accounts Executive | F57: Finance | G57: =VLOOKUP(tblPayroll[[#This Row],[Employee Id]],Table1[[Employee Id]:[Work Location]],13,0) -> Kolkata | H57: 0 | I57: =28-H57 -> 28 | J57: 24 | K57: =ROUND(VLOOKUP($B57,'CTC Breakup'!$B$2:$O$51,7,0)/28*$I57,0) -> 32500 | L57: =ROUND(VLOOKUP($B57,'CTC Breakup'!$B$2:$O$51,8,0)/28*$I57,0) -> 13000 | M57: =ROUND(VLOOKUP($B57,'CTC Breakup'!$B$2:$O$51,9,0)/28*$I57,0) -> 15600 | N57: =ROUND(VLOOKUP($B57,'CTC Breakup'!$B$2:$O$51,10,0)/28*$I57,0) -> 0 | O57: =ROUND(VLOOKUP($B57,'CTC Breakup'!$B$2:$O$51,11,0)/28*$I57,0) -> 0 | P57: =ROUND(((VLOOKUP($B57,'CTC Breakup'!$B$2:$N$51,13,0)-VLOOKUP($B57,'CTC Breakup'!$B$2:$N$51,12,0))/22/9)*$J57,0) -> 7406 | Q57: 0 | R57: =SUM(K57:Q57) -> 68506 | S57: =ROUND(K57*12%,0) -> 3900 | T57: =ROUND(IF(R57>100000,R57*30%,IF(R57>75000,R57*20%,IF(R57>50000,R57*10%,0))),0) -> 6851 | U57: 0 | V57: =R57-S57-T57-U57 -> 57755
A58: 46054 | B58: ASG0025 | C58: 45328 | E58: Accounts Executive | F58: Finance | G58: =VLOOKUP(tblPayroll[[#This Row],[Employee Id]],Table1[[Employee Id]:[Work Location]],13,0) -> Chennai | H58: 7 | I58: =28-H58 -> 21 | J58: 0 | K58: =ROUND(VLOOKUP($B58,'CTC Breakup'!$B$2:$O$51,7,0)/28*$I58,0) -> 22657 | L58: =ROUND(VLOOKUP($B58,'CTC Breakup'!$B$2:$O$51,8,0)/28*$I58,0) -> 9063 | M58: =ROUND(VLOOKUP($B58,'CTC Breakup'!$B$2:$O$51,9,0)/28*$I58,0) -> 10874 | N58: =ROUND(VLOOKUP($B58,'CTC Breakup'!$B$2:$O$51,10,0)/28*$I58,0) -> 0 | O58: =ROUND(VLOOKUP($B58,'CTC Breakup'!$B$2:$O$51,11,0)/28*$I58,0) -> 0 | P58: =ROUND(((VLOOKUP($B58,'CTC Breakup'!$B$2:$N$51,13,0)-VLOOKUP($B58,'CTC Breakup'!$B$2:$N$51,12,0))/22/9)*$J58,0) -> 0 | Q58: 0 | R58: =SUM(K58:Q58) -> 42594 | S58: =ROUND(K58*12%,0) -> 2719 | T58: =ROUND(IF(R58>100000,R58*30%,IF(R58>75000,R58*20%,IF(R58>50000,R58*10%,0))),0) -> 0 | U58: 0 | V58: =R58-S58-T58-U58 -> 39875
A59: 46054 | B59: ASG0027 | C59: 45418 | E59: HR Analyst | F59: HR | G59: =VLOOKUP(tblPayroll[[#This Row],[Employee Id]],Table1[[Employee Id]:[Work Location]],13,0) -> Mumbai | H59: 0 | I59: =28-H59 -> 28 | J59: 22 | K59: =ROUND(VLOOKUP($B59,'CTC Breakup'!$B$2:$O$51,7,0)/28*$I59,0) -> 47917 | L59: =ROUND(VLOOKUP($B59,'CTC Breakup'!$B$2:$O$51,8,0)/28*$I59,0) -> 19167 | M59: =ROUND(VLOOKUP($B59,'CTC Breakup'!$B$2:$O$51,9,0)/28*$I59,0) -> 19999 | N59: =ROUND(VLOOKUP($B59,'CTC Breakup'!$B$2:$O$51,10,0)/28*$I59,0) -> 2000 | O59: =ROUND(VLOOKUP($B59,'CTC Breakup'!$B$2:$O$51,11,0)/28*$I59,0) -> 1000 | P59: =ROUND(((VLOOKUP($B59,'CTC Breakup'!$B$2:$N$51,13,0)-VLOOKUP($B59,'CTC Breakup'!$B$2:$N$51,12,0))/22/9)*$J59,0) -> 10009 | Q59: 0 | R59: =SUM(K59:Q59) -> 100092 | S59: =ROUND(K59*12%,0) -> 5750 | T59: =ROUND(IF(R59>100000,R59*30%,IF(R59>75000,R59*20%,IF(R59>50000,R59*10%,0))),0) -> 30028 | U59: 0 | V59: =R59-S59-T59-U59 -> 64314
A60: 46054 | B60: ASG0028 | C60: 45502 | E60: Sales Trainee | F60: Sales | G60: =VLOOKUP(tblPayroll[[#This Row],[Employee Id]],Table1[[Employee Id]:[Work Location]],13,0) -> Hyderabad | H60: 0 | I60: =28-H60 -> 28 | J60: 21 | K60: =ROUND(VLOOKUP($B60,'CTC Breakup'!$B$2:$O$51,7,0)/28*$I60,0) -> 18750 | L60: =ROUND(VLOOKUP($B60,'CTC Breakup'!$B$2:$O$51,8,0)/28*$I60,0) -> 7500 | M60: =ROUND(VLOOKUP($B60,'CTC Breakup'!$B$2:$O$51,9,0)/28*$I60,0) -> 9000 | N60: =ROUND(VLOOKUP($B60,'CTC Breakup'!$B$2:$O$51,10,0)/28*$I60,0) -> 0 | O60: =ROUND(VLOOKUP($B60,'CTC Breakup'!$B$2:$O$51,11,0)/28*$I60,0) -> 0 | P60: =ROUND(((VLOOKUP($B60,'CTC Breakup'!$B$2:$N$51,13,0)-VLOOKUP($B60,'CTC Breakup'!$B$2:$N$51,12,0))/22/9)*$J60,0) -> 3739 | Q60: 6870 | R60: =SUM(K60:Q60) -> 45859 | S60: =ROUND(K60*12%,0) -> 2250 | T60: =ROUND(IF(R60>100000,R60*30%,IF(R60>75000,R60*20%,IF(R60>50000,R60*10%,0))),0) -> 0 | U60: 0 | V60: =R60-S60-T60-U60 -> 43609
A61: 46054 | B61: ASG0029 | C61: 45509 | E61: Payroll Analyst | F61: Payroll | G61: =VLOOKUP(tblPayroll[[#This Row],[Employee Id]],Table1[[Employee Id]:[Work Location]],13,0) -> Kolkata | H61: 0 | I61: =28-H61 -> 28 | J61: 0 | K61: =ROUND(VLOOKUP($B61,'CTC Breakup'!$B$2:$O$51,7,0)/28*$I61,0) -> 27084 | L61: =ROUND(VLOOKUP($B61,'CTC Breakup'!$B$2:$O$51,8,0)/28*$I61,0) -> 10834 | M61: =ROUND(VLOOKUP($B61,'CTC Breakup'!$B$2:$O$51,9,0)/28*$I61,0) -> 12999 | N61: =ROUND(VLOOKUP($B61,'CTC Breakup'!$B$2:$O$51,10,0)/28*$I61,0) -> 0 | O61: =ROUND(VLOOKUP($B61,'CTC Breakup'!$B$2:$O$51,11,0)/28*$I61,0) -> 0 | P61: =ROUND(((VLOOKUP($B61,'CTC Breakup'!$B$2:$N$51,13,0)-VLOOKUP($B61,'CTC Breakup'!$B$2:$N$51,12,0))/22/9)*$J61,0) -> 0 | Q61: 0 | R61: =SUM(K61:Q61) -> 50917 | S61: =ROUND(K61*12%,0) -> 3250 | T61: =ROUND(IF(R61>100000,R61*30%,IF(R61>75000,R61*20%,IF(R61>50000,R61*10%,0))),0) -> 5092 | U61: 0 | V61: =R61-S61-T61-U61 -> 42575
A62: 46054 | B62: ASG0030 | C62: 45537 | D62: 46098 | E62: Senior Data Analyst | F62: Analytics | G62: =VLOOKUP(tblPayroll[[#This Row],[Employee Id]],Table1[[Employee Id]:[Work Location]],13,0) -> Hyderabad | H62: 0 | I62: =28-H62 -> 28 | J62: 22 | K62: =ROUND(VLOOKUP($B62,'CTC Breakup'!$B$2:$O$51,7,0)/28*$I62,0) -> 59792 | L62: =ROUND(VLOOKUP($B62,'CTC Breakup'!$B$2:$O$51,8,0)/28*$I62,0) -> 23917 | M62: =ROUND(VLOOKUP($B62,'CTC Breakup'!$B$2:$O$51,9,0)/28*$I62,0) -> 25699 | N62: =ROUND(VLOOKUP($B62,'CTC Breakup'!$B$2:$O$51,10,0)/28*$I62,0) -> 2000 | O62: =ROUND(VLOOKUP($B62,'CTC Breakup'!$B$2:$O$51,11,0)/28*$I62,0) -> 1000 | P62: =ROUND(((VLOOKUP($B62,'CTC Breakup'!$B$2:$N$51,13,0)-VLOOKUP($B62,'CTC Breakup'!$B$2:$N$51,12,0))/22/9)*$J62,0) -> 12490 | Q62: 0 | R62: =SUM(K62:Q62) -> 124898 | S62: =ROUND(K62*12%,0) -> 7175 | T62: =ROUND(IF(R62>100000,R62*30%,IF(R62>75000,R62*20%,IF(R62>50000,R62*10%,0))),0) -> 37469 | U62: 11600 | V62: =R62-S62-T62-U62 -> 68654
A63: 46054 | B63: ASG0031 | C63: 45579 | E63: Accounts Executive | F63: Finance | G63: =VLOOKUP(tblPayroll[[#This Row],[Employee Id]],Table1[[Employee Id]:[Work Location]],13,0) -> Bangalore | H63: 5 | I63: =28-H63 -> 23 | J63: 0 | K63: =ROUND(VLOOKUP($B63,'CTC Breakup'!$B$2:$O$51,7,0)/28*$I63,0) -> 23959 | L63: =ROUND(VLOOKUP($B63,'CTC Breakup'!$B$2:$O$51,8,0)/28*$I63,0) -> 9584 | M63: =ROUND(VLOOKUP($B63,'CTC Breakup'!$B$2:$O$51,9,0)/28*$I63,0) -> 11499 | N63: =ROUND(VLOOKUP($B63,'CTC Breakup'!$B$2:$O$51,10,0)/28*$I63,0) -> 0 | O63: =ROUND(VLOOKUP($B63,'CTC Breakup'!$B$2:$O$51,11,0)/28*$I63,0) -> 0 | P63: =ROUND(((VLOOKUP($B63,'CTC Breakup'!$B$2:$N$51,13,0)-VLOOKUP($B63,'CTC Breakup'!$B$2:$N$51,12,0))/22/9)*$J63,0) -> 0 | Q63: 0 | R63: =SUM(K63:Q63) -> 45042 | S63: =ROUND(K63*12%,0) -> 2875 | T63: =ROUND(IF(R63>100000,R63*30%,IF(R63>75000,R63*20%,IF(R63>50000,R63*10%,0))),0) -> 0 | U63: 0 | V63: =R63-S63-T63-U63 -> 42167
A64: 46054 | B64: ASG0032 | C64: 45607 | E64: HR Executive | F64: HR | G64: =VLOOKUP(tblPayroll[[#This Row],[Employee Id]],Table1[[Employee Id]:[Work Location]],13,0) -> Chennai | H64: 10 | I64: =28-H64 -> 18 | J64: 0 | K64: =ROUND(VLOOKUP($B64,'CTC Breakup'!$B$2:$O$51,7,0)/28*$I64,0) -> 20089 | L64: =ROUND(VLOOKUP($B64,'CTC Breakup'!$B$2:$O$51,8,0)/28*$I64,0) -> 8036 | M64: =ROUND(VLOOKUP($B64,'CTC Breakup'!$B$2:$O$51,9,0)/28*$I64,0) -> 9643 | N64: =ROUND(VLOOKUP($B64,'CTC Breakup'!$B$2:$O$51,10,0)/28*$I64,0) -> 0 | O64: =ROUND(VLOOKUP($B64,'CTC Breakup'!$B$2:$O$51,11,0)/28*$I64,0) -> 0 | P64: =ROUND(((VLOOKUP($B64,'CTC Breakup'!$B$2:$N$51,13,0)-VLOOKUP($B64,'CTC Breakup'!$B$2:$N$51,12,0))/22/9)*$J64,0) -> 0 | Q64: 0 | R64: =SUM(K64:Q64) -> 37768 | S64: =ROUND(K64*12%,0) -> 2411 | T64: =ROUND(IF(R64>100000,R64*30%,IF(R64>75000,R64*20%,IF(R64>50000,R64*10%,0))),0) -> 0 | U64: 14600 | V64: =R64-S64-T64-U64 -> 20757
A65: 46054 | B65: ASG0033 | C65: 45614 | E65: Data Analyst | F65: Analytics | G65: =VLOOKUP(tblPayroll[[#This Row],[Employee Id]],Table1[[Employee Id]:[Work Location]],13,0) -> Bangalore | H65: 7 | I65: =28-H65 -> 21 | J65: 25 | K65: =ROUND(VLOOKUP($B65,'CTC Breakup'!$B$2:$O$51,7,0)/28*$I65,0) -> 39063 | L65: =ROUND(VLOOKUP($B65,'CTC Breakup'!$B$2:$O$51,8,0)/28*$I65,0) -> 15626 | M65: =ROUND(VLOOKUP($B65,'CTC Breakup'!$B$2:$O$51,9,0)/28*$I65,0) -> 16499 | N65: =ROUND(VLOOKUP($B65,'CTC Breakup'!$B$2:$O$51,10,0)/28*$I65,0) -> 1500 | O65: =ROUND(VLOOKUP($B65,'CTC Breakup'!$B$2:$O$51,11,0)/28*$I65,0) -> 750 | P65: =ROUND(((VLOOKUP($B65,'CTC Breakup'!$B$2:$N$51,13,0)-VLOOKUP($B65,'CTC Breakup'!$B$2:$N$51,12,0))/22/9)*$J65,0) -> 12363 | Q65: 0 | R65: =SUM(K65:Q65) -> 85801 | S65: =ROUND(K65*12%,0) -> 4688 | T65: =ROUND(IF(R65>100000,R65*30%,IF(R65>75000,R65*20%,IF(R65>50000,R65*10%,0))),0) -> 17160 | U65: 0 | V65: =R65-S65-T65-U65 -> 63953
A66: 46054 | B66: ASG0035 | C66: 45663 | E66: HR Executive | F66: HR | G66: =VLOOKUP(tblPayroll[[#This Row],[Employee Id]],Table1[[Employee Id]:[Work Location]],13,0) -> Mumbai | H66: 0 | I66: =28-H66 -> 28 | J66: 0 | K66: =ROUND(VLOOKUP($B66,'CTC Breakup'!$B$2:$O$51,7,0)/28*$I66,0) -> 25000 | L66: =ROUND(VLOOKUP($B66,'CTC Breakup'!$B$2:$O$51,8,0)/28*$I66,0) -> 10000 | M66: =ROUND(VLOOKUP($B66,'CTC Breakup'!$B$2:$O$51,9,0)/28*$I66,0) -> 12000 | N66: =ROUND(VLOOKUP($B66,'CTC Breakup'!$B$2:$O$51,10,0)/28*$I66,0) -> 0 | O66: =ROUND(VLOOKUP($B66,'CTC Breakup'!$B$2:$O$51,11,0)/28*$I66,0) -> 0 | P66: =ROUND(((VLOOKUP($B66,'CTC Breakup'!$B$2:$N$51,13,0)-VLOOKUP($B66,'CTC Breakup'!$B$2:$N$51,12,0))/22/9)*$J66,0) -> 0 | Q66: 0 | R66: =SUM(K66:Q66) -> 47000 | S66: =ROUND(K66*12%,0) -> 3000 | T66: =ROUND(IF(R66>100000,R66*30%,IF(R66>75000,R66*20%,IF(R66>50000,R66*10%,0))),0) -> 0 | U66: 0 | V66: =R66-S66-T66-U66 -> 44000
A67: 46054 | B67: ASG0036 | C67: 45782 | E67: Payroll Executive | F67: Payroll | G67: =VLOOKUP(tblPayroll[[#This Row],[Employee Id]],Table1[[Employee Id]:[Work Location]],13,0) -> Chennai | H67: 0 | I67: =28-H67 -> 28 | J67: 0 | K67: =ROUND(VLOOKUP($B67,'CTC Breakup'!$B$2:$O$51,7,0)/28*$I67,0) -> 19792 | L67: =ROUND(VLOOKUP($B67,'CTC Breakup'!$B$2:$O$51,8,0)/28*$I67,0) -> 7917 | M67: =ROUND(VLOOKUP($B67,'CTC Breakup'!$B$2:$O$51,9,0)/28*$I67,0) -> 9499 | N67: =ROUND(VLOOKUP($B67,'CTC Breakup'!$B$2:$O$51,10,0)/28*$I67,0) -> 0 | O67: =ROUND(VLOOKUP($B67,'CTC Breakup'!$B$2:$O$51,11,0)/28*$I67,0) -> 0 | P67: =ROUND(((VLOOKUP($B67,'CTC Breakup'!$B$2:$N$51,13,0)-VLOOKUP($B67,'CTC Breakup'!$B$2:$N$51,12,0))/22/9)*$J67,0) -> 0 | Q67: 0 | R67: =SUM(K67:Q67) -> 37208 | S67: =ROUND(K67*12%,0) -> 2375 | T67: =ROUND(IF(R67>100000,R67*30%,IF(R67>75000,R67*20%,IF(R67>50000,R67*10%,0))),0) -> 0 | U67: 0 | V67: =R67-S67-T67-U67 -> 34833
A68: 46054 | B68: ASG0038 | C68: 45852 | E68: Accounts Trainee | F68: Finance | G68: =VLOOKUP(tblPayroll[[#This Row],[Employee Id]],Table1[[Employee Id]:[Work Location]],13,0) -> Mumbai | H68: 0 | I68: =28-H68 -> 28 | J68: 25 | K68: =ROUND(VLOOKUP($B68,'CTC Breakup'!$B$2:$O$51,7,0)/28*$I68,0) -> 18750 | L68: =ROUND(VLOOKUP($B68,'CTC Breakup'!$B$2:$O$51,8,0)/28*$I68,0) -> 7500 | M68: =ROUND(VLOOKUP($B68,'CTC Breakup'!$B$2:$O$51,9,0)/28*$I68,0) -> 9000 | N68: =ROUND(VLOOKUP($B68,'CTC Breakup'!$B$2:$O$51,10,0)/28*$I68,0) -> 0 | O68: =ROUND(VLOOKUP($B68,'CTC Breakup'!$B$2:$O$51,11,0)/28*$I68,0) -> 0 | P68: =ROUND(((VLOOKUP($B68,'CTC Breakup'!$B$2:$N$51,13,0)-VLOOKUP($B68,'CTC Breakup'!$B$2:$N$51,12,0))/22/9)*$J68,0) -> 4451 | Q68: 0 | R68: =SUM(K68:Q68) -> 39701 | S68: =ROUND(K68*12%,0) -> 2250 | T68: =ROUND(IF(R68>100000,R68*30%,IF(R68>75000,R68*20%,IF(R68>50000,R68*10%,0))),0) -> 0 | U68: 0 | V68: =R68-S68-T68-U68 -> 37451
A69: 46054 | B69: ASG0039 | C69: 45901 | E69: BI Developer | F69: Analytics | G69: =VLOOKUP(tblPayroll[[#This Row],[Employee Id]],Table1[[Employee Id]:[Work Location]],13,0) -> Kolkata | H69: 6 | I69: =28-H69 -> 22 | J69: 0 | K69: =ROUND(VLOOKUP($B69,'CTC Breakup'!$B$2:$O$51,7,0)/28*$I69,0) -> 41741 | L69: =ROUND(VLOOKUP($B69,'CTC Breakup'!$B$2:$O$51,8,0)/28*$I69,0) -> 16696 | M69: =ROUND(VLOOKUP($B69,'CTC Breakup'!$B$2:$O$51,9,0)/28*$I69,0) -> 17679 | N69: =ROUND(VLOOKUP($B69,'CTC Breakup'!$B$2:$O$51,10,0)/28*$I69,0) -> 1571 | O69: =ROUND(VLOOKUP($B69,'CTC Breakup'!$B$2:$O$51,11,0)/28*$I69,0) -> 786 | P69: =ROUND(((VLOOKUP($B69,'CTC Breakup'!$B$2:$N$51,13,0)-VLOOKUP($B69,'CTC Breakup'!$B$2:$N$51,12,0))/22/9)*$J69,0) -> 0 | Q69: 0 | R69: =SUM(K69:Q69) -> 78473 | S69: =ROUND(K69*12%,0) -> 5009 | T69: =ROUND(IF(R69>100000,R69*30%,IF(R69>75000,R69*20%,IF(R69>50000,R69*10%,0))),0) -> 15695 | U69: 0 | V69: =R69-S69-T69-U69 -> 57769
A70: 46054 | B70: ASG0040 | C70: 45908 | D70: 46077 | E70: Payroll Executive | F70: Payroll | G70: =VLOOKUP(tblPayroll[[#This Row],[Employee Id]],Table1[[Employee Id]:[Work Location]],13,0) -> Mumbai | H70: 0 | I70: 24 | J70: 22 | K70: =ROUND(VLOOKUP($B70,'CTC Breakup'!$B$2:$O$51,7,0)/28*$I70,0) -> 16965 | L70: =ROUND(VLOOKUP($B70,'CTC Breakup'!$B$2:$O$51,8,0)/28*$I70,0) -> 6786 | M70: =ROUND(VLOOKUP($B70,'CTC Breakup'!$B$2:$O$51,9,0)/28*$I70,0) -> 8142 | N70: =ROUND(VLOOKUP($B70,'CTC Breakup'!$B$2:$O$51,10,0)/28*$I70,0) -> 0 | O70: =ROUND(VLOOKUP($B70,'CTC Breakup'!$B$2:$O$51,11,0)/28*$I70,0) -> 0 | P70: =ROUND(((VLOOKUP($B70,'CTC Breakup'!$B$2:$N$51,13,0)-VLOOKUP($B70,'CTC Breakup'!$B$2:$N$51,12,0))/22/9)*$J70,0) -> 4134 | Q70: 0 | R70: =SUM(K70:Q70) -> 36027 | S70: =ROUND(K70*12%,0) -> 2036 | T70: =ROUND(IF(R70>100000,R70*30%,IF(R70>75000,R70*20%,IF(R70>50000,R70*10%,0))),0) -> 0 | U70: 0 | V70: =R70-S70-T70-U70 -> 33991
A71: 46054 | B71: ASG0041 | C71: 45978 | E71: Data Analyst | F71: Analytics | G71: =VLOOKUP(tblPayroll[[#This Row],[Employee Id]],Table1[[Employee Id]:[Work Location]],13,0) -> Chennai | H71: 8 | I71: =28-H71 -> 20 | J71: 0 | K71: =ROUND(VLOOKUP($B71,'CTC Breakup'!$B$2:$O$51,7,0)/28*$I71,0) -> 35119 | L71: =ROUND(VLOOKUP($B71,'CTC Breakup'!$B$2:$O$51,8,0)/28*$I71,0) -> 14048 | M71: =ROUND(VLOOKUP($B71,'CTC Breakup'!$B$2:$O$51,9,0)/28*$I71,0) -> 14714 | N71: =ROUND(VLOOKUP($B71,'CTC Breakup'!$B$2:$O$51,10,0)/28*$I71,0) -> 1429 | O71: =ROUND(VLOOKUP($B71,'CTC Breakup'!$B$2:$O$51,11,0)/28*$I71,0) -> 714 | P71: =ROUND(((VLOOKUP($B71,'CTC Breakup'!$B$2:$N$51,13,0)-VLOOKUP($B71,'CTC Breakup'!$B$2:$N$51,12,0))/22/9)*$J71,0) -> 0 | Q71: 0 | R71: =SUM(K71:Q71) -> 66024 | S71: =ROUND(K71*12%,0) -> 4214 | T71: =ROUND(IF(R71>100000,R71*30%,IF(R71>75000,R71*20%,IF(R71>50000,R71*10%,0))),0) -> 6602 | U71: 0 | V71: =R71-S71-T71-U71 -> 55208
A72: 46054 | B72: ASG0042 | C72: 45992 | E72: Sales Trainee | F72: Sales | G72: =VLOOKUP(tblPayroll[[#This Row],[Employee Id]],Table1[[Employee Id]:[Work Location]],13,0) -> Chennai | H72: 0 | I72: =28-H72 -> 28 | J72: 0 | K72: =ROUND(VLOOKUP($B72,'CTC Breakup'!$B$2:$O$51,7,0)/28*$I72,0) -> 18750 | L72: =ROUND(VLOOKUP($B72,'CTC Breakup'!$B$2:$O$51,8,0)/28*$I72,0) -> 7500 | M72: =ROUND(VLOOKUP($B72,'CTC Breakup'!$B$2:$O$51,9,0)/28*$I72,0) -> 9000 | N72: =ROUND(VLOOKUP($B72,'CTC Breakup'!$B$2:$O$51,10,0)/28*$I72,0) -> 0 | O72: =ROUND(VLOOKUP($B72,'CTC Breakup'!$B$2:$O$51,11,0)/28*$I72,0) -> 0 | P72: =ROUND(((VLOOKUP($B72,'CTC Breakup'!$B$2:$N$51,13,0)-VLOOKUP($B72,'CTC Breakup'!$B$2:$N$51,12,0))/22/9)*$J72,0) -> 0 | Q72: 6910 | R72: =SUM(K72:Q72) -> 42160 | S72: =ROUND(K72*12%,0) -> 2250 | T72: =ROUND(IF(R72>100000,R72*30%,IF(R72>75000,R72*20%,IF(R72>50000,R72*10%,0))),0) -> 0 | U72: 0 | V72: =R72-S72-T72-U72 -> 39910
A73: 46054 | B73: ASG0043 | C73: 46027 | E73: HR Executive | F73: HR | G73: =VLOOKUP(tblPayroll[[#This Row],[Employee Id]],Table1[[Employee Id]:[Work Location]],13,0) -> Bangalore | H73: 0 | I73: =28-H73 -> 28 | J73: 20 | K73: =ROUND(VLOOKUP($B73,'CTC Breakup'!$B$2:$O$51,7,0)/28*$I73,0) -> 23959 | L73: =ROUND(VLOOKUP($B73,'CTC Breakup'!$B$2:$O$51,8,0)/28*$I73,0) -> 9584 | M73: =ROUND(VLOOKUP($B73,'CTC Breakup'!$B$2:$O$51,9,0)/28*$I73,0) -> 11499 | N73: =ROUND(VLOOKUP($B73,'CTC Breakup'!$B$2:$O$51,10,0)/28*$I73,0) -> 0 | O73: =ROUND(VLOOKUP($B73,'CTC Breakup'!$B$2:$O$51,11,0)/28*$I73,0) -> 0 | P73: =ROUND(((VLOOKUP($B73,'CTC Breakup'!$B$2:$N$51,13,0)-VLOOKUP($B73,'CTC Breakup'!$B$2:$N$51,12,0))/22/9)*$J73,0) -> 4550 | Q73: 0 | R73: =SUM(K73:Q73) -> 49592 | S73: =ROUND(K73*12%,0) -> 2875 | T73: =ROUND(IF(R73>100000,R73*30%,IF(R73>75000,R73*20%,IF(R73>50000,R73*10%,0))),0) -> 0 | U73: 0 | V73: =R73-S73-T73-U73 -> 46717
A74: 46054 | B74: ASG0044 | C74: 46041 | E74: Data Analyst | F74: Analytics | G74: =VLOOKUP(tblPayroll[[#This Row],[Employee Id]],Table1[[Employee Id]:[Work Location]],13,0) -> Kolkata | H74: 0 | I74: =28-H74 -> 28 | J74: 25 | K74: =ROUND(VLOOKUP($B74,'CTC Breakup'!$B$2:$O$51,7,0)/28*$I74,0) -> 47917 | L74: =ROUND(VLOOKUP($B74,'CTC Breakup'!$B$2:$O$51,8,0)/28*$I74,0) -> 19167 | M74: =ROUND(VLOOKUP($B74,'CTC Breakup'!$B$2:$O$51,9,0)/28*$I74,0) -> 19999 | N74: =ROUND(VLOOKUP($B74,'CTC Breakup'!$B$2:$O$51,10,0)/28*$I74,0) -> 2000 | O74: =ROUND(VLOOKUP($B74,'CTC Breakup'!$B$2:$O$51,11,0)/28*$I74,0) -> 1000 | P74: =ROUND(((VLOOKUP($B74,'CTC Breakup'!$B$2:$N$51,13,0)-VLOOKUP($B74,'CTC Breakup'!$B$2:$N$51,12,0))/22/9)*$J74,0) -> 11374 | Q74: 0 | R74: =SUM(K74:Q74) -> 101457 | S74: =ROUND(K74*12%,0) -> 5750 | T74: =ROUND(IF(R74>100000,R74*30%,IF(R74>75000,R74*20%,IF(R74>50000,R74*10%,0))),0) -> 30437 | U74: 12400 | V74: =R74-S74-T74-U74 -> 52870
A75: 46054 | B75: ASG0045 | C75: 46056 | E75: Accounts Trainee | F75: Finance | G75: =VLOOKUP(tblPayroll[[#This Row],[Employee Id]],Table1[[Employee Id]:[Work Location]],13,0) -> Hyderabad | H75: 0 | I75: =28-H75 -> 28 | J75: 0 | K75: =ROUND(VLOOKUP($B75,'CTC Breakup'!$B$2:$O$51,7,0)/28*$I75,0) -> 18750 | L75: =ROUND(VLOOKUP($B75,'CTC Breakup'!$B$2:$O$51,8,0)/28*$I75,0) -> 7500 | M75: =ROUND(VLOOKUP($B75,'CTC Breakup'!$B$2:$O$51,9,0)/28*$I75,0) -> 9000 | N75: =ROUND(VLOOKUP($B75,'CTC Breakup'!$B$2:$O$51,10,0)/28*$I75,0) -> 0 | O75: =ROUND(VLOOKUP($B75,'CTC Breakup'!$B$2:$O$51,11,0)/28*$I75,0) -> 0 | P75: =ROUND(((VLOOKUP($B75,'CTC Breakup'!$B$2:$N$51,13,0)-VLOOKUP($B75,'CTC Breakup'!$B$2:$N$51,12,0))/22/9)*$J75,0) -> 0 | Q75: 0 | R75: =SUM(K75:Q75) -> 35250 | S75: =ROUND(K75*12%,0) -> 2250 | T75: =ROUND(IF(R75>100000,R75*30%,IF(R75>75000,R75*20%,IF(R75>50000,R75*10%,0))),0) -> 0 | U75: 0 | V75: =R75-S75-T75-U75 -> 33000
A76: 46054 | B76: ASG0046 | C76: 46062 | E76: HR Executive | F76: HR | G76: =VLOOKUP(tblPayroll[[#This Row],[Employee Id]],Table1[[Employee Id]:[Work Location]],13,0) -> Chennai | H76: 0 | I76: =28-H76 -> 28 | J76: 0 | K76: =ROUND(VLOOKUP($B76,'CTC Breakup'!$B$2:$O$51,7,0)/28*$I76,0) -> 23959 | L76: =ROUND(VLOOKUP($B76,'CTC Breakup'!$B$2:$O$51,8,0)/28*$I76,0) -> 9584 | M76: =ROUND(VLOOKUP($B76,'CTC Breakup'!$B$2:$O$51,9,0)/28*$I76,0) -> 11499 | N76: =ROUND(VLOOKUP($B76,'CTC Breakup'!$B$2:$O$51,10,0)/28*$I76,0) -> 0 | O76: =ROUND(VLOOKUP($B76,'CTC Breakup'!$B$2:$O$51,11,0)/28*$I76,0) -> 0 | P76: =ROUND(((VLOOKUP($B76,'CTC Breakup'!$B$2:$N$51,13,0)-VLOOKUP($B76,'CTC Breakup'!$B$2:$N$51,12,0))/22/9)*$J76,0) -> 0 | Q76: 0 | R76: =SUM(K76:Q76) -> 45042 | S76: =ROUND(K76*12%,0) -> 2875 | T76: =ROUND(IF(R76>100000,R76*30%,IF(R76>75000,R76*20%,IF(R76>50000,R76*10%,0))),0) -> 0 | U76: 0 | V76: =R76-S76-T76-U76 -> 42167
A77: 46054 | B77: ASG0047 | C77: 46063 | E77: HR Executive | F77: HR | G77: =VLOOKUP(tblPayroll[[#This Row],[Employee Id]],Table1[[Employee Id]:[Work Location]],13,0) -> Bangalore | H77: 0 | I77: =28-H77 -> 28 | J77: 17 | K77: =ROUND(VLOOKUP($B77,'CTC Breakup'!$B$2:$O$51,7,0)/28*$I77,0) -> 23959 | L77: =ROUND(VLOOKUP($B77,'CTC Breakup'!$B$2:$O$51,8,0)/28*$I77,0) -> 9584 | M77: =ROUND(VLOOKUP($B77,'CTC Breakup'!$B$2:$O$51,9,0)/28*$I77,0) -> 11499 | N77: =ROUND(VLOOKUP($B77,'CTC Breakup'!$B$2:$O$51,10,0)/28*$I77,0) -> 0 | O77: =ROUND(VLOOKUP($B77,'CTC Breakup'!$B$2:$O$51,11,0)/28*$I77,0) -> 0 | P77: =ROUND(((VLOOKUP($B77,'CTC Breakup'!$B$2:$N$51,13,0)-VLOOKUP($B77,'CTC Breakup'!$B$2:$N$51,12,0))/22/9)*$J77,0) -> 3867 | Q77: 0 | R77: =SUM(K77:Q77) -> 48909 | S77: =ROUND(K77*12%,0) -> 2875 | T77: =ROUND(IF(R77>100000,R77*30%,IF(R77>75000,R77*20%,IF(R77>50000,R77*10%,0))),0) -> 0 | U77: 0 | V77: =R77-S77-T77-U77 -> 46034
A78: 46082 | B78: ASG0001 | C78: 44593 | E78: HR Manager | F78: HR | G78: =VLOOKUP(tblPayroll[[#This Row],[Employee Id]],Table1[[Employee Id]:[Work Location]],13,0) -> Bangalore | H78: 5 | I78: =31-H78 -> 26 | J78: 0 | K78: =ROUND(VLOOKUP($B78,'CTC Breakup'!$B$2:$O$51,7,0)/31*$I78,0) -> 64651 | L78: =ROUND(VLOOKUP($B78,'CTC Breakup'!$B$2:$O$51,8,0)/31*$I78,0) -> 25861 | M78: =ROUND(VLOOKUP($B78,'CTC Breakup'!$B$2:$O$51,9,0)/31*$I78,0) -> 28515 | N78: =ROUND(VLOOKUP($B78,'CTC Breakup'!$B$2:$O$51,10,0)/31*$I78,0) -> 1677 | O78: =ROUND(VLOOKUP($B78,'CTC Breakup'!$B$2:$O$51,11,0)/31*$I78,0) -> 839 | P78: =ROUND(((VLOOKUP($B78,'CTC Breakup'!$B$2:$N$51,13,0)-VLOOKUP($B78,'CTC Breakup'!$B$2:$N$51,12,0))/22/9)*$J78,0) -> 0 | Q78: 0 | R78: =SUM(K78:Q78) -> 121543 | S78: =ROUND(K78*12%,0) -> 7758 | T78: =ROUND(IF(R78>100000,R78*30%,IF(R78>75000,R78*20%,IF(R78>50000,R78*10%,0))),0) -> 36463 | U78: 0 | V78: =R78-S78-T78-U78 -> 77322
A79: 46082 | B79: ASG0002 | C79: 44613 | E79: Analytics Manager | F79: Analytics | G79: =VLOOKUP(tblPayroll[[#This Row],[Employee Id]],Table1[[Employee Id]:[Work Location]],13,0) -> Chennai | H79: 0 | I79: =31-H79 -> 31 | J79: 0 | K79: =ROUND(VLOOKUP($B79,'CTC Breakup'!$B$2:$O$51,7,0)/31*$I79,0) -> 104167 | L79: =ROUND(VLOOKUP($B79,'CTC Breakup'!$B$2:$O$51,8,0)/31*$I79,0) -> 41667 | M79: =ROUND(VLOOKUP($B79,'CTC Breakup'!$B$2:$O$51,9,0)/31*$I79,0) -> 49999 | N79: =ROUND(VLOOKUP($B79,'CTC Breakup'!$B$2:$O$51,10,0)/31*$I79,0) -> 0 | O79: =ROUND(VLOOKUP($B79,'CTC Breakup'!$B$2:$O$51,11,0)/31*$I79,0) -> 0 | P79: =ROUND(((VLOOKUP($B79,'CTC Breakup'!$B$2:$N$51,13,0)-VLOOKUP($B79,'CTC Breakup'!$B$2:$N$51,12,0))/22/9)*$J79,0) -> 0 | Q79: 0 | R79: =SUM(K79:Q79) -> 195833 | S79: =ROUND(K79*12%,0) -> 12500 | T79: =ROUND(IF(R79>100000,R79*30%,IF(R79>75000,R79*20%,IF(R79>50000,R79*10%,0))),0) -> 58750 | U79: 0 | V79: =R79-S79-T79-U79 -> 124583
A80: 46082 | B80: ASG0003 | C80: 44634 | E80: HR Manager | F80: HR | G80: =VLOOKUP(tblPayroll[[#This Row],[Employee Id]],Table1[[Employee Id]:[Work Location]],13,0) -> Bangalore | H80: 9 | I80: =31-H80 -> 22 | J80: 18 | K80: =ROUND(VLOOKUP($B80,'CTC Breakup'!$B$2:$O$51,7,0)/31*$I80,0) -> 51748 | L80: =ROUND(VLOOKUP($B80,'CTC Breakup'!$B$2:$O$51,8,0)/31*$I80,0) -> 20699 | M80: =ROUND(VLOOKUP($B80,'CTC Breakup'!$B$2:$O$51,9,0)/31*$I80,0) -> 22709 | N80: =ROUND(VLOOKUP($B80,'CTC Breakup'!$B$2:$O$51,10,0)/31*$I80,0) -> 1419 | O80: =ROUND(VLOOKUP($B80,'CTC Breakup'!$B$2:$O$51,11,0)/31*$I80,0) -> 710 | P80: =ROUND(((VLOOKUP($B80,'CTC Breakup'!$B$2:$N$51,13,0)-VLOOKUP($B80,'CTC Breakup'!$B$2:$N$51,12,0))/22/9)*$J80,0) -> 12462 | Q80: 0 | R80: =SUM(K80:Q80) -> 109747 | S80: =ROUND(K80*12%,0) -> 6210 | T80: =ROUND(IF(R80>100000,R80*30%,IF(R80>75000,R80*20%,IF(R80>50000,R80*10%,0))),0) -> 32924 | U80: 0 | V80: =R80-S80-T80-U80 -> 70613
A81: 46082 | B81: ASG0005 | C81: 44697 | E81: Payroll Manager | F81: Payroll | G81: =VLOOKUP(tblPayroll[[#This Row],[Employee Id]],Table1[[Employee Id]:[Work Location]],13,0) -> Chennai | H81: 9 | I81: =31-H81 -> 22 | J81: 19 | K81: =ROUND(VLOOKUP($B81,'CTC Breakup'!$B$2:$O$51,7,0)/31*$I81,0) -> 50269 | L81: =ROUND(VLOOKUP($B81,'CTC Breakup'!$B$2:$O$51,8,0)/31*$I81,0) -> 20108 | M81: =ROUND(VLOOKUP($B81,'CTC Breakup'!$B$2:$O$51,9,0)/31*$I81,0) -> 21999 | N81: =ROUND(VLOOKUP($B81,'CTC Breakup'!$B$2:$O$51,10,0)/31*$I81,0) -> 1419 | O81: =ROUND(VLOOKUP($B81,'CTC Breakup'!$B$2:$O$51,11,0)/31*$I81,0) -> 710 | P81: =ROUND(((VLOOKUP($B81,'CTC Breakup'!$B$2:$N$51,13,0)-VLOOKUP($B81,'CTC Breakup'!$B$2:$N$51,12,0))/22/9)*$J81,0) -> 12779 | Q81: 0 | R81: =SUM(K81:Q81) -> 107284 | S81: =ROUND(K81*12%,0) -> 6032 | T81: =ROUND(IF(R81>100000,R81*30%,IF(R81>75000,R81*20%,IF(R81>50000,R81*10%,0))),0) -> 32185 | U81: 0 | V81: =R81-S81-T81-U81 -> 69067
A82: 46082 | B82: ASG0006 | C82: 44704 | E82: Senior Payroll Analyst | F82: Payroll | G82: =VLOOKUP(tblPayroll[[#This Row],[Employee Id]],Table1[[Employee Id]:[Work Location]],13,0) -> Mumbai | H82: 0 | I82: =31-H82 -> 31 | J82: 0 | K82: =ROUND(VLOOKUP($B82,'CTC Breakup'!$B$2:$O$51,7,0)/31*$I82,0) -> 41667 | L82: =ROUND(VLOOKUP($B82,'CTC Breakup'!$B$2:$O$51,8,0)/31*$I82,0) -> 16667 | M82: =ROUND(VLOOKUP($B82,'CTC Breakup'!$B$2:$O$51,9,0)/31*$I82,0) -> 16999 | N82: =ROUND(VLOOKUP($B82,'CTC Breakup'!$B$2:$O$51,10,0)/31*$I82,0) -> 2000 | O82: =ROUND(VLOOKUP($B82,'CTC Breakup'!$B$2:$O$51,11,0)/31*$I82,0) -> 1000 | P82: =ROUND(((VLOOKUP($B82,'CTC Breakup'!$B$2:$N$51,13,0)-VLOOKUP($B82,'CTC Breakup'!$B$2:$N$51,12,0))/22/9)*$J82,0) -> 0 | Q82: 0 | R82: =SUM(K82:Q82) -> 78333 | S82: =ROUND(K82*12%,0) -> 5000 | T82: =ROUND(IF(R82>100000,R82*30%,IF(R82>75000,R82*20%,IF(R82>50000,R82*10%,0))),0) -> 15667 | U82: 13300 | V82: =R82-S82-T82-U82 -> 44366
A83: 46082 | B83: ASG0008 | C83: 44886 | E83: Sales Manager | F83: Sales | G83: =VLOOKUP(tblPayroll[[#This Row],[Employee Id]],Table1[[Employee Id]:[Work Location]],13,0) -> Kolkata | H83: 0 | I83: =31-H83 -> 31 | J83: 0 | K83: =ROUND(VLOOKUP($B83,'CTC Breakup'!$B$2:$O$51,7,0)/31*$I83,0) -> 87500 | L83: =ROUND(VLOOKUP($B83,'CTC Breakup'!$B$2:$O$51,8,0)/31*$I83,0) -> 35000 | M83: =ROUND(VLOOKUP($B83,'CTC Breakup'!$B$2:$O$51,9,0)/31*$I83,0) -> 39000 | N83: =ROUND(VLOOKUP($B83,'CTC Breakup'!$B$2:$O$51,10,0)/31*$I83,0) -> 2000 | O83: =ROUND(VLOOKUP($B83,'CTC Breakup'!$B$2:$O$51,11,0)/31*$I83,0) -> 1000 | P83: =ROUND(((VLOOKUP($B83,'CTC Breakup'!$B$2:$N$51,13,0)-VLOOKUP($B83,'CTC Breakup'!$B$2:$N$51,12,0))/22/9)*$J83,0) -> 0 | Q83: 38500 | R83: =SUM(K83:Q83) -> 203000 | S83: =ROUND(K83*12%,0) -> 10500 | T83: =ROUND(IF(R83>100000,R83*30%,IF(R83>75000,R83*20%,IF(R83>50000,R83*10%,0))),0) -> 60900 | U83: 0 | V83: =R83-S83-T83-U83 -> 131600
A84: 46082 | B84: ASG0009 | C84: 44893 | E84: Regional Sales Lead | F84: Sales | G84: =VLOOKUP(tblPayroll[[#This Row],[Employee Id]],Table1[[Employee Id]:[Work Location]],13,0) -> Hyderabad | H84: 0 | I84: =31-H84 -> 31 | J84: 19 | K84: =ROUND(VLOOKUP($B84,'CTC Breakup'!$B$2:$O$51,7,0)/31*$I84,0) -> 75000 | L84: =ROUND(VLOOKUP($B84,'CTC Breakup'!$B$2:$O$51,8,0)/31*$I84,0) -> 30000 | M84: =ROUND(VLOOKUP($B84,'CTC Breakup'!$B$2:$O$51,9,0)/31*$I84,0) -> 33000 | N84: =ROUND(VLOOKUP($B84,'CTC Breakup'!$B$2:$O$51,10,0)/31*$I84,0) -> 2000 | O84: =ROUND(VLOOKUP($B84,'CTC Breakup'!$B$2:$O$51,11,0)/31*$I84,0) -> 1000 | P84: =ROUND(((VLOOKUP($B84,'CTC Breakup'!$B$2:$N$51,13,0)-VLOOKUP($B84,'CTC Breakup'!$B$2:$N$51,12,0))/22/9)*$J84,0) -> 13530 | Q84: 32190 | R84: =SUM(K84:Q84) -> 186720 | S84: =ROUND(K84*12%,0) -> 9000 | T84: =ROUND(IF(R84>100000,R84*30%,IF(R84>75000,R84*20%,IF(R84>50000,R84*10%,0))),0) -> 56016 | U84: 0 | V84: =R84-S84-T84-U84 -> 121704
A85: 46082 | B85: ASG0010 | C85: 44907 | E85: Finance Manager | F85: Finance | G85: =VLOOKUP(tblPayroll[[#This Row],[Employee Id]],Table1[[Employee Id]:[Work Location]],13,0) -> Mumbai | H85: 10 | I85: =31-H85 -> 21 | J85: 19 | K85: =ROUND(VLOOKUP($B85,'CTC Breakup'!$B$2:$O$51,7,0)/31*$I85,0) -> 49395 | L85: =ROUND(VLOOKUP($B85,'CTC Breakup'!$B$2:$O$51,8,0)/31*$I85,0) -> 19758 | M85: =ROUND(VLOOKUP($B85,'CTC Breakup'!$B$2:$O$51,9,0)/31*$I85,0) -> 21677 | N85: =ROUND(VLOOKUP($B85,'CTC Breakup'!$B$2:$O$51,10,0)/31*$I85,0) -> 1355 | O85: =ROUND(VLOOKUP($B85,'CTC Breakup'!$B$2:$O$51,11,0)/31*$I85,0) -> 677 | P85: =ROUND(((VLOOKUP($B85,'CTC Breakup'!$B$2:$N$51,13,0)-VLOOKUP($B85,'CTC Breakup'!$B$2:$N$51,12,0))/22/9)*$J85,0) -> 13154 | Q85: 0 | R85: =SUM(K85:Q85) -> 106016 | S85: =ROUND(K85*12%,0) -> 5927 | T85: =ROUND(IF(R85>100000,R85*30%,IF(R85>75000,R85*20%,IF(R85>50000,R85*10%,0))),0) -> 31805 | U85: 0 | V85: =R85-S85-T85-U85 -> 68284
A86: 46082 | B86: ASG0012 | C86: 44956 | E86: Senior Sales Executive | F86: Sales | G86: =VLOOKUP(tblPayroll[[#This Row],[Employee Id]],Table1[[Employee Id]:[Work Location]],13,0) -> Chennai | H86: 6 | I86: =31-H86 -> 25 | J86: 0 | K86: =ROUND(VLOOKUP($B86,'CTC Breakup'!$B$2:$O$51,7,0)/31*$I86,0) -> 38643 | L86: =ROUND(VLOOKUP($B86,'CTC Breakup'!$B$2:$O$51,8,0)/31*$I86,0) -> 15457 | M86: =ROUND(VLOOKUP($B86,'CTC Breakup'!$B$2:$O$51,9,0)/31*$I86,0) -> 16128 | N86: =ROUND(VLOOKUP($B86,'CTC Breakup'!$B$2:$O$51,10,0)/31*$I86,0) -> 1613 | O86: =ROUND(VLOOKUP($B86,'CTC Breakup'!$B$2:$O$51,11,0)/31*$I86,0) -> 806 | P86: =ROUND(((VLOOKUP($B86,'CTC Breakup'!$B$2:$N$51,13,0)-VLOOKUP($B86,'CTC Breakup'!$B$2:$N$51,12,0))/22/9)*$J86,0) -> 0 | Q86: 27600 | R86: =SUM(K86:Q86) -> 100247 | S86: =ROUND(K86*12%,0) -> 4637 | T86: =ROUND(IF(R86>100000,R86*30%,IF(R86>75000,R86*20%,IF(R86>50000,R86*10%,0))),0) -> 30074 | U86: 0 | V86: =R86-S86-T86-U86 -> 65536
A87: 46082 | B87: ASG0013 | C87: 44963 | E87: Senior Data Analyst | F87: Analytics | G87: =VLOOKUP(tblPayroll[[#This Row],[Employee Id]],Table1[[Employee Id]:[Work Location]],13,0) -> Bangalore | H87: 0 | I87: =31-H87 -> 31 | J87: 0 | K87: =ROUND(VLOOKUP($B87,'CTC Breakup'!$B$2:$O$51,7,0)/31*$I87,0) -> 64584 | L87: =ROUND(VLOOKUP($B87,'CTC Breakup'!$B$2:$O$51,8,0)/31*$I87,0) -> 25834 | M87: =ROUND(VLOOKUP($B87,'CTC Breakup'!$B$2:$O$51,9,0)/31*$I87,0) -> 27999 | N87: =ROUND(VLOOKUP($B87,'CTC Breakup'!$B$2:$O$51,10,0)/31*$I87,0) -> 2000 | O87: =ROUND(VLOOKUP($B87,'CTC Breakup'!$B$2:$O$51,11,0)/31*$I87,0) -> 1000 | P87: =ROUND(((VLOOKUP($B87,'CTC Breakup'!$B$2:$N$51,13,0)-VLOOKUP($B87,'CTC Breakup'!$B$2:$N$51,12,0))/22/9)*$J87,0) -> 0 | Q87: 0 | R87: =SUM(K87:Q87) -> 121417 | S87: =ROUND(K87*12%,0) -> 7750 | T87: =ROUND(IF(R87>100000,R87*30%,IF(R87>75000,R87*20%,IF(R87>50000,R87*10%,0))),0) -> 36425 | U87: 0 | V87: =R87-S87-T87-U87 -> 77242
A88: 46082 | B88: ASG0015 | C88: 45033 | E88: Senior Data Analyst | F88: Analytics | G88: =VLOOKUP(tblPayroll[[#This Row],[Employee Id]],Table1[[Employee Id]:[Work Location]],13,0) -> Hyderabad | H88: 0 | I88: =31-H88 -> 31 | J88: 0 | K88: =ROUND(VLOOKUP($B88,'CTC Breakup'!$B$2:$O$51,7,0)/31*$I88,0) -> 61459 | L88: =ROUND(VLOOKUP($B88,'CTC Breakup'!$B$2:$O$51,8,0)/31*$I88,0) -> 24584 | M88: =ROUND(VLOOKUP($B88,'CTC Breakup'!$B$2:$O$51,9,0)/31*$I88,0) -> 26499 | N88: =ROUND(VLOOKUP($B88,'CTC Breakup'!$B$2:$O$51,10,0)/31*$I88,0) -> 2000 | O88: =ROUND(VLOOKUP($B88,'CTC Breakup'!$B$2:$O$51,11,0)/31*$I88,0) -> 1000 | P88: =ROUND(((VLOOKUP($B88,'CTC Breakup'!$B$2:$N$51,13,0)-VLOOKUP($B88,'CTC Breakup'!$B$2:$N$51,12,0))/22/9)*$J88,0) -> 0 | Q88: 0 | R88: =SUM(K88:Q88) -> 115542 | S88: =ROUND(K88*12%,0) -> 7375 | T88: =ROUND(IF(R88>100000,R88*30%,IF(R88>75000,R88*20%,IF(R88>50000,R88*10%,0))),0) -> 34663 | U88: 0 | V88: =R88-S88-T88-U88 -> 73504
A89: 46082 | B89: ASG0016 | C89: 45040 | E89: Senior Data Analyst | F89: Analytics | G89: =VLOOKUP(tblPayroll[[#This Row],[Employee Id]],Table1[[Employee Id]:[Work Location]],13,0) -> Bangalore | H89: 10 | I89: =31-H89 -> 21 | J89: 0 | K89: =ROUND(VLOOKUP($B89,'CTC Breakup'!$B$2:$O$51,7,0)/31*$I89,0) -> 52923 | L89: =ROUND(VLOOKUP($B89,'CTC Breakup'!$B$2:$O$51,8,0)/31*$I89,0) -> 21169 | M89: =ROUND(VLOOKUP($B89,'CTC Breakup'!$B$2:$O$51,9,0)/31*$I89,0) -> 23371 | N89: =ROUND(VLOOKUP($B89,'CTC Breakup'!$B$2:$O$51,10,0)/31*$I89,0) -> 1355 | O89: =ROUND(VLOOKUP($B89,'CTC Breakup'!$B$2:$O$51,11,0)/31*$I89,0) -> 677 | P89: =ROUND(((VLOOKUP($B89,'CTC Breakup'!$B$2:$N$51,13,0)-VLOOKUP($B89,'CTC Breakup'!$B$2:$N$51,12,0))/22/9)*$J89,0) -> 0 | Q89: 0 | R89: =SUM(K89:Q89) -> 99495 | S89: =ROUND(K89*12%,0) -> 6351 | T89: =ROUND(IF(R89>100000,R89*30%,IF(R89>75000,R89*20%,IF(R89>50000,R89*10%,0))),0) -> 19899 | U89: 0 | V89: =R89-S89-T89-U89 -> 73245
... A94: 46082 | B94: ASG0023 | C94: 45320 | E94: HR Analyst | F94: HR | G94: =VLOOKUP(tblPayroll[[#This Row],[Employee Id]],Table1[[Employee Id]:[Work Location]],13,0) -> Hyderabad | H94: 6 | I94: =31-H94 -> 25 | J94: 0 | K94: =ROUND(VLOOKUP($B94,'CTC Breakup'!$B$2:$O$51,7,0)/31*$I94,0) -> 40323 | L94: =ROUND(VLOOKUP($B94,'CTC Breakup'!$B$2:$O$51,8,0)/31*$I94,0) -> 16129 | M94: =ROUND(VLOOKUP($B94,'CTC Breakup'!$B$2:$O$51,9,0)/31*$I94,0) -> 16935 | N94: =ROUND(VLOOKUP($B94,'CTC Breakup'!$B$2:$O$51,10,0)/31*$I94,0) -> 1613 | O94: =ROUND(VLOOKUP($B94,'CTC Breakup'!$B$2:$O$51,11,0)/31*$I94,0) -> 806 | P94: =ROUND(((VLOOKUP($B94,'CTC Breakup'!$B$2:$N$51,13,0)-VLOOKUP($B94,'CTC Breakup'!$B$2:$N$51,12,0))/22/9)*$J94,0) -> 0 | Q94: 0 | R94: =SUM(K94:Q94) -> 75806 | S94: =ROUND(K94*12%,0) -> 4839 | T94: =ROUND(IF(R94>100000,R94*30%,IF(R94>75000,R94*20%,IF(R94>50000,R94*10%,0))),0) -> 15161 | U94: 0 | V94: =R94-S94-T94-U94 -> 55806
A95: 46082 | B95: ASG0024 | C95: 45327 | D95: 46084 | E95: Accounts Executive | F95: Finance | G95: =VLOOKUP(tblPayroll[[#This Row],[Employee Id]],Table1[[Employee Id]:[Work Location]],13,0) -> Kolkata | H95: 0 | I95: 3 | J95: 19 | K95: =ROUND(VLOOKUP($B95,'CTC Breakup'!$B$2:$O$51,7,0)/31*$I95,0) -> 3145 | L95: =ROUND(VLOOKUP($B95,'CTC Breakup'!$B$2:$O$51,8,0)/31*$I95,0) -> 1258 | M95: =ROUND(VLOOKUP($B95,'CTC Breakup'!$B$2:$O$51,9,0)/31*$I95,0) -> 1510 | N95: =ROUND(VLOOKUP($B95,'CTC Breakup'!$B$2:$O$51,10,0)/31*$I95,0) -> 0 | O95: =ROUND(VLOOKUP($B95,'CTC Breakup'!$B$2:$O$51,11,0)/31*$I95,0) -> 0 | P95: =ROUND(((VLOOKUP($B95,'CTC Breakup'!$B$2:$N$51,13,0)-VLOOKUP($B95,'CTC Breakup'!$B$2:$N$51,12,0))/22/9)*$J95,0) -> 5863 | Q95: 0 | R95: =SUM(K95:Q95) -> 11776 | S95: =ROUND(K95*12%,0) -> 377 | T95: =ROUND(IF(R95>100000,R95*30%,IF(R95>75000,R95*20%,IF(R95>50000,R95*10%,0))),0) -> 0 | U95: 14400 | V95: =R95-S95-T95-U95 -> -3001
A96: 46082 | B96: ASG0025 | C96: 45328 | E96: Accounts Executive | F96: Finance | G96: =VLOOKUP(tblPayroll[[#This Row],[Employee Id]],Table1[[Employee Id]:[Work Location]],13,0) -> Chennai | H96: 10 | I96: =31-H96 -> 21 | J96: 19 | K96: =ROUND(VLOOKUP($B96,'CTC Breakup'!$B$2:$O$51,7,0)/31*$I96,0) -> 20464 | L96: =ROUND(VLOOKUP($B96,'CTC Breakup'!$B$2:$O$51,8,0)/31*$I96,0) -> 8186 | M96: =ROUND(VLOOKUP($B96,'CTC Breakup'!$B$2:$O$51,9,0)/31*$I96,0) -> 9822 | N96: =ROUND(VLOOKUP($B96,'CTC Breakup'!$B$2:$O$51,10,0)/31*$I96,0) -> 0 | O96: =ROUND(VLOOKUP($B96,'CTC Breakup'!$B$2:$O$51,11,0)/31*$I96,0) -> 0 | P96: =ROUND(((VLOOKUP($B96,'CTC Breakup'!$B$2:$N$51,13,0)-VLOOKUP($B96,'CTC Breakup'!$B$2:$N$51,12,0))/22/9)*$J96,0) -> 5450 | Q96: 0 | R96: =SUM(K96:Q96) -> 43922 | S96: =ROUND(K96*12%,0) -> 2456 | T96: =ROUND(IF(R96>100000,R96*30%,IF(R96>75000,R96*20%,IF(R96>50000,R96*10%,0))),0) -> 0 | U96: 0 | V96: =R96-S96-T96-U96 -> 41466
A97: 46082 | B97: ASG0027 | C97: 45418 | E97: HR Analyst | F97: HR | G97: =VLOOKUP(tblPayroll[[#This Row],[Employee Id]],Table1[[Employee Id]:[Work Location]],13,0) -> Mumbai | H97: 0 | I97: =31-H97 -> 31 | J97: 0 | K97: =ROUND(VLOOKUP($B97,'CTC Breakup'!$B$2:$O$51,7,0)/31*$I97,0) -> 47917 | L97: =ROUND(VLOOKUP($B97,'CTC Breakup'!$B$2:$O$51,8,0)/31*$I97,0) -> 19167 | M97: =ROUND(VLOOKUP($B97,'CTC Breakup'!$B$2:$O$51,9,0)/31*$I97,0) -> 19999 | N97: =ROUND(VLOOKUP($B97,'CTC Breakup'!$B$2:$O$51,10,0)/31*$I97,0) -> 2000 | O97: =ROUND(VLOOKUP($B97,'CTC Breakup'!$B$2:$O$51,11,0)/31*$I97,0) -> 1000 | P97: =ROUND(((VLOOKUP($B97,'CTC Breakup'!$B$2:$N$51,13,0)-VLOOKUP($B97,'CTC Breakup'!$B$2:$N$51,12,0))/22/9)*$J97,0) -> 0 | Q97: 0 | R97: =SUM(K97:Q97) -> 90083 | S97: =ROUND(K97*12%,0) -> 5750 | T97: =ROUND(IF(R97>100000,R97*30%,IF(R97>75000,R97*20%,IF(R97>50000,R97*10%,0))),0) -> 18017 | U97: 0 | V97: =R97-S97-T97-U97 -> 66316
A98: 46082 | B98: ASG0028 | C98: 45502 | E98: Sales Trainee | F98: Sales | G98: =VLOOKUP(tblPayroll[[#This Row],[Employee Id]],Table1[[Employee Id]:[Work Location]],13,0) -> Hyderabad | H98: 0 | I98: =31-H98 -> 31 | J98: 0 | K98: =ROUND(VLOOKUP($B98,'CTC Breakup'!$B$2:$O$51,7,0)/31*$I98,0) -> 18750 | L98: =ROUND(VLOOKUP($B98,'CTC Breakup'!$B$2:$O$51,8,0)/31*$I98,0) -> 7500 | M98: =ROUND(VLOOKUP($B98,'CTC Breakup'!$B$2:$O$51,9,0)/31*$I98,0) -> 9000 | N98: =ROUND(VLOOKUP($B98,'CTC Breakup'!$B$2:$O$51,10,0)/31*$I98,0) -> 0 | O98: =ROUND(VLOOKUP($B98,'CTC Breakup'!$B$2:$O$51,11,0)/31*$I98,0) -> 0 | P98: =ROUND(((VLOOKUP($B98,'CTC Breakup'!$B$2:$N$51,13,0)-VLOOKUP($B98,'CTC Breakup'!$B$2:$N$51,12,0))/22/9)*$J98,0) -> 0 | Q98: 16090 | R98: =SUM(K98:Q98) -> 51340 | S98: =ROUND(K98*12%,0) -> 2250 | T98: =ROUND(IF(R98>100000,R98*30%,IF(R98>75000,R98*20%,IF(R98>50000,R98*10%,0))),0) -> 5134 | U98: 0 | V98: =R98-S98-T98-U98 -> 43956
A99: 46082 | B99: ASG0029 | C99: 45509 | E99: Payroll Analyst | F99: Payroll | G99: =VLOOKUP(tblPayroll[[#This Row],[Employee Id]],Table1[[Employee Id]:[Work Location]],13,0) -> Kolkata | H99: 0 | I99: =31-H99 -> 31 | J99: 0 | K99: =ROUND(VLOOKUP($B99,'CTC Breakup'!$B$2:$O$51,7,0)/31*$I99,0) -> 27084 | L99: =ROUND(VLOOKUP($B99,'CTC Breakup'!$B$2:$O$51,8,0)/31*$I99,0) -> 10834 | M99: =ROUND(VLOOKUP($B99,'CTC Breakup'!$B$2:$O$51,9,0)/31*$I99,0) -> 12999 | N99: =ROUND(VLOOKUP($B99,'CTC Breakup'!$B$2:$O$51,10,0)/31*$I99,0) -> 0 | O99: =ROUND(VLOOKUP($B99,'CTC Breakup'!$B$2:$O$51,11,0)/31*$I99,0) -> 0 | P99: =ROUND(((VLOOKUP($B99,'CTC Breakup'!$B$2:$N$51,13,0)-VLOOKUP($B99,'CTC Breakup'!$B$2:$N$51,12,0))/22/9)*$J99,0) -> 0 | Q99: 0 | R99: =SUM(K99:Q99) -> 50917 | S99: =ROUND(K99*12%,0) -> 3250 | T99: =ROUND(IF(R99>100000,R99*30%,IF(R99>75000,R99*20%,IF(R99>50000,R99*10%,0))),0) -> 5092 | U99: 0 | V99: =R99-S99-T99-U99 -> 42575
A100: 46082 | B100: ASG0030 | C100: 45537 | D100: 46098 | E100: Senior Data Analyst | F100: Analytics | G100: =VLOOKUP(tblPayroll[[#This Row],[Employee Id]],Table1[[Employee Id]:[Work Location]],13,0) -> Hyderabad | H100: 3 | I100: 14 | J100: 21 | K100: =ROUND(VLOOKUP($B100,'CTC Breakup'!$B$2:$O$51,7,0)/31*$I100,0) -> 27003 | L100: =ROUND(VLOOKUP($B100,'CTC Breakup'!$B$2:$O$51,8,0)/31*$I100,0) -> 10801 | M100: =ROUND(VLOOKUP($B100,'CTC Breakup'!$B$2:$O$51,9,0)/31*$I100,0) -> 11606 | N100: =ROUND(VLOOKUP($B100,'CTC Breakup'!$B$2:$O$51,10,0)/31*$I100,0) -> 903 | O100: =ROUND(VLOOKUP($B100,'CTC Breakup'!$B$2:$O$51,11,0)/31*$I100,0) -> 452 | P100: =ROUND(((VLOOKUP($B100,'CTC Breakup'!$B$2:$N$51,13,0)-VLOOKUP($B100,'CTC Breakup'!$B$2:$N$51,12,0))/22/9)*$J100,0) -> 11922 | Q100: 0 | R100: =SUM(K100:Q100) -> 62687 | S100: =ROUND(K100*12%,0) -> 3240 | T100: =ROUND(IF(R100>100000,R100*30%,IF(R100>75000,R100*20%,IF(R100>50000,R100*10%,0))),0) -> 6269 | U100: 13400 | V100: =R100-S100-T100-U100 -> 39778
A101: 46082 | B101: ASG0031 | C101: 45579 | E101: Accounts Executive | F101: Finance | G101: =VLOOKUP(tblPayroll[[#This Row],[Employee Id]],Table1[[Employee Id]:[Work Location]],13,0) -> Bangalore | H101: 0 | I101: =31-H101 -> 31 | J101: 0 | K101: =ROUND(VLOOKUP($B101,'CTC Breakup'!$B$2:$O$51,7,0)/31*$I101,0) -> 29167 | L101: =ROUND(VLOOKUP($B101,'CTC Breakup'!$B$2:$O$51,8,0)/31*$I101,0) -> 11667 | M101: =ROUND(VLOOKUP($B101,'CTC Breakup'!$B$2:$O$51,9,0)/31*$I101,0) -> 13999 | N101: =ROUND(VLOOKUP($B101,'CTC Breakup'!$B$2:$O$51,10,0)/31*$I101,0) -> 0 | O101: =ROUND(VLOOKUP($B101,'CTC Breakup'!$B$2:$O$51,11,0)/31*$I101,0) -> 0 | P101: =ROUND(((VLOOKUP($B101,'CTC Breakup'!$B$2:$N$51,13,0)-VLOOKUP($B101,'CTC Breakup'!$B$2:$N$51,12,0))/22/9)*$J101,0) -> 0 | Q101: 0 | R101: =SUM(K101:Q101) -> 54833 | S101: =ROUND(K101*12%,0) -> 3500 | T101: =ROUND(IF(R101>100000,R101*30%,IF(R101>75000,R101*20%,IF(R101>50000,R101*10%,0))),0) -> 5483 | U101: 0 | V101: =R101-S101-T101-U101 -> 45850
A102: 46082 | B102: ASG0032 | C102: 45607 | E102: HR Executive | F102: HR | G102: =VLOOKUP(tblPayroll[[#This Row],[Employee Id]],Table1[[Employee Id]:[Work Location]],13,0) -> Chennai | H102: 0 | I102: =31-H102 -> 31 | J102: 0 | K102: =ROUND(VLOOKUP($B102,'CTC Breakup'!$B$2:$O$51,7,0)/31*$I102,0) -> 31250 | L102: =ROUND(VLOOKUP($B102,'CTC Breakup'!$B$2:$O$51,8,0)/31*$I102,0) -> 12500 | M102: =ROUND(VLOOKUP($B102,'CTC Breakup'!$B$2:$O$51,9,0)/31*$I102,0) -> 15000 | N102: =ROUND(VLOOKUP($B102,'CTC Breakup'!$B$2:$O$51,10,0)/31*$I102,0) -> 0 | O102: =ROUND(VLOOKUP($B102,'CTC Breakup'!$B$2:$O$51,11,0)/31*$I102,0) -> 0 | P102: =ROUND(((VLOOKUP($B102,'CTC Breakup'!$B$2:$N$51,13,0)-VLOOKUP($B102,'CTC Breakup'!$B$2:$N$51,12,0))/22/9)*$J102,0) -> 0 | Q102: 0 | R102: =SUM(K102:Q102) -> 58750 | S102: =ROUND(K102*12%,0) -> 3750 | T102: =ROUND(IF(R102>100000,R102*30%,IF(R102>75000,R102*20%,IF(R102>50000,R102*10%,0))),0) -> 5875 | U102: 10500 | V102: =R102-S102-T102-U102 -> 38625
A103: 46082 | B103: ASG0033 | C103: 45614 | E103: Data Analyst | F103: Analytics | G103: =VLOOKUP(tblPayroll[[#This Row],[Employee Id]],Table1[[Employee Id]:[Work Location]],13,0) -> Bangalore | H103: 0 | I103: =31-H103 -> 31 | J103: 24 | K103: =ROUND(VLOOKUP($B103,'CTC Breakup'!$B$2:$O$51,7,0)/31*$I103,0) -> 52084 | L103: =ROUND(VLOOKUP($B103,'CTC Breakup'!$B$2:$O$51,8,0)/31*$I103,0) -> 20834 | M103: =ROUND(VLOOKUP($B103,'CTC Breakup'!$B$2:$O$51,9,0)/31*$I103,0) -> 21999 | N103: =ROUND(VLOOKUP($B103,'CTC Breakup'!$B$2:$O$51,10,0)/31*$I103,0) -> 2000 | O103: =ROUND(VLOOKUP($B103,'CTC Breakup'!$B$2:$O$51,11,0)/31*$I103,0) -> 1000 | P103: =ROUND(((VLOOKUP($B103,'CTC Breakup'!$B$2:$N$51,13,0)-VLOOKUP($B103,'CTC Breakup'!$B$2:$N$51,12,0))/22/9)*$J103,0) -> 11869 | Q103: 0 | R103: =SUM(K103:Q103) -> 109786 | S103: =ROUND(K103*12%,0) -> 6250 | T103: =ROUND(IF(R103>100000,R103*30%,IF(R103>75000,R103*20%,IF(R103>50000,R103*10%,0))),0) -> 32936 | U103: 0 | V103: =R103-S103-T103-U103 -> 70600
A104: 46082 | B104: ASG0035 | C104: 45663 | E104: HR Executive | F104: HR | G104: =VLOOKUP(tblPayroll[[#This Row],[Employee Id]],Table1[[Employee Id]:[Work Location]],13,0) -> Mumbai | H104: 0 | I104: =31-H104 -> 31 | J104: 0 | K104: =ROUND(VLOOKUP($B104,'CTC Breakup'!$B$2:$O$51,7,0)/31*$I104,0) -> 25000 | L104: =ROUND(VLOOKUP($B104,'CTC Breakup'!$B$2:$O$51,8,0)/31*$I104,0) -> 10000 | M104: =ROUND(VLOOKUP($B104,'CTC Breakup'!$B$2:$O$51,9,0)/31*$I104,0) -> 12000 | N104: =ROUND(VLOOKUP($B104,'CTC Breakup'!$B$2:$O$51,10,0)/31*$I104,0) -> 0 | O104: =ROUND(VLOOKUP($B104,'CTC Breakup'!$B$2:$O$51,11,0)/31*$I104,0) -> 0 | P104: =ROUND(((VLOOKUP($B104,'CTC Breakup'!$B$2:$N$51,13,0)-VLOOKUP($B104,'CTC Breakup'!$B$2:$N$51,12,0))/22/9)*$J104,0) -> 0 | Q104: 0 | R104: =SUM(K104:Q104) -> 47000 | S104: =ROUND(K104*12%,0) -> 3000 | T104: =ROUND(IF(R104>100000,R104*30%,IF(R104>75000,R104*20%,IF(R104>50000,R104*10%,0))),0) -> 0 | U104: 0 | V104: =R104-S104-T104-U104 -> 44000
...

Sheet Pivot Tables - Payroll
A1: Sum of Net Salary | B1: Column Labels | F1: Sum of Net Salary | G1: Column Labels | K1: Month | L1: Sum of Gross Salary | M1: Sum of Net Salary | O1: Department | P1: Sum of OT Hours
A2: Department | B2: 46023 | C2: 46054 | D2: 46082 | F2: Location | G2: 46023 | H2: 46054 | I2: 46082 | K2: 46023 | L2: 3229498 | M2: 2261671 | O2: Analytics | P2: 216
A3: Analytics | B3: 648450 | C3: 667220 | D3: 636131 | F3: Bangalore | G3: 539154 | H3: 577553 | I3: 574229 | K3: 46054 | L3: 3187501 | M3: 2256144 | O3: Finance | P3: 205
A4: Finance | B4: 356710 | C4: 350746 | D4: 322527 | F4: Chennai | G4: 563439 | H4: 485221 | I4: 530713 | K4: 46082 | L4: 3219625 | M4: 2292472 | O4: HR | P4: 206
A5: HR | B5: 449737 | C5: 490045 | D5: 483688 | F5: Hyderabad | G5: 334358 | H5: 393683 | I5: 451070 | O5: Payroll | P5: 147
A6: Payroll | B6: 285671 | C6: 270238 | D6: 273409 | F6: Kolkata | G6: 400618 | H6: 381034 | I6: 344279 | O6: Sales | P6: 172
A7: Sales | B7: 521103 | C7: 477895 | D7: 576717 | F7: Mumbai | G7: 424102 | H7: 418653 | I7: 392181
L21: Department | M21: Sum of Employee PF | N21: Sum of Income Tax
L22: 46023 | M22: 189103 | N22: 694824
L23: 46054 | M23: 187854 | N23: 657303
L24: 46082 | M24: 184918 | N24: 662435
A26: Department | B26: Sum of LOP Days
A27: Bangalore | B27: 77
A28: Chennai | B28: 95
A29: Hyderabad | B29: 25
A30: Kolkata | B30: 43
A31: Mumbai | B31: 29

Sheet Dashboard for Emp Payroll

Sheet Business Insights for Payroll
